Workbook
Name \T: #REF!
Name __Count: 9
Name _01_01_99: #REF!
Name _01_02_99: #REF!
Name _01_03_99: #REF!
Name _01_04_99: #REF!
Name _01_05_99: #REF!
Name _01_06_99: #REF!
Name _01_07_99: #REF!
Name _01_08_1999: #REF!
Name _01_11_2001: #N/A
Name _0300625210_025_1: #REF!
Name _0301167362_1: #REF!
Name _0600038118_3: #REF!
Name _1: #REF!
Name _1_20001_TblF0902JDE: #REF!
Name _1000A01: #N/A
Name _1111: #REF!
Name _11MAÕ_HAØNG: #REF!
Name _13MAÕ_SOÁ_THUEÁ: #REF!
Name _15ÑÔN_GIAÙ: #REF!
Name _1600377828_1: #REF!
Name _17SOÁ_CTÖØ: #REF!
Name _18SOÁ_LÖÔÏNG: #REF!
Name _1BA2500: #REF!
Name _1BA3250: #REF!
Name _1BA400P: #REF!
Name _1CAP001: #REF!
Name _1CAP011: #REF!
Name _1CAP012: #REF!
Name _1CDHT03: #REF!
Name _1CHANG2: #REF!
Name _1DADOI1: #REF!
Name _1DAU002: #REF!
Name _1DDAY03: #REF!
Name _1DDTT01: #REF!
Name _1FCO101: #REF!
Name _1GIA101: #REF!
Name _1LA1001: #REF!
Name _1MCCBO2: #REF!
Name _1PKCAP1: #REF!
Name _1PKIEN2: #REF!
Name _1PKTT01: #REF!
Name _1TCD101: #REF!
Name _1TCD201: #REF!
Name _1TCD203: #REF!
Name _1TD2001: #REF!
Name _1TIHT01: #REF!
Name _1TIHT06: #REF!
Name _1TIHT07: #REF!
Name _1TRU121: #REF!
Name _2: #REF!
Name _20TEÂN_HAØNG: #REF!
Name _22TEÂN_KHAÙCH_HAØ: #REF!
Name _24THAØNH_TIEÀN: #REF!
Name _26TRÒ_GIAÙ: #REF!
Name _2700138984_1: #REF!
Name _28TRÒ_GIAÙ__VAT: #REF!
Name _2900326167_1: #REF!
Name _2BLA100: #REF!

Sheet EPS,P.E, P.B
B1: Today price | C1: 18200
C3: 2010 | D3: 2011 | E3: 2012 | F3: 2013 | G3: 2014 | H3: 2015 | I3: 2016 | J3: 2017 | K3: 2018 | L3: 2019
B4: NPAT (VND'b) | C4: ='P&L'!C30 -> 72.079287 | D4: ='P&L'!D30 -> 24.591496 | E4: ='P&L'!E30 -> 57.859951 | F4: ='P&L'!F30 -> 82.763994 | G4: ='P&L'!G30 -> 167.83449 | H4: ='P&L'!H30 -> 0.337 | I4: ='P&L'!I30 -> 0.50305051 | J4: ='P&L'!J30 -> 0.73327004 | ... L4: ='P&L'!L30 -> 1.1377904
B5: Year-end share count (mn) | C5: =#REF!/10 -> #REF! | D5: =#REF!/10 -> #REF! | E5: =#REF!/10 -> #REF! | F5: =#REF!/10 -> #REF! | G5: =#REF!/10 -> #REF! | H5: 116.87 | I5: =H5 -> 116.87 | J5: =I5 -> 116.87 | K5: =#REF!/10 -> #REF! | L5: =#REF!/10 -> #REF!
B6: Private placement | D6: 5.2 | E6: 10 | G6: 11.64 | H6: 25.7
B7: ESOP | C7: 0.4 | D7: 0.8 | F7: 0.3 | H7: 0.3
B8: Right issue | C8: 7.6 | D8: 10 | G8: 10.56
B9: Share dividend | F9: 10.4996 | H9: 5.245
B10: Share dividend (to be issued) | H10: 10.625
B11: Adjusted year-end share count | C11: =I11-SUM(D6:J7) -> 62.93 | D11: =I11-SUM(E6:J7) -> 68.93 | E11: =I11-SUM(F6:J7) -> 78.93 | F11: =I11-SUM(G6:J7) -> 79.23 | G11: =I11-SUM(H6:J7) -> 90.87 | H11: =H5-H10 -> 106.245 | I11: =I5 -> 116.87 | J11: =J5 -> 116.87 | K11: =K5 -> #REF! | L11: =L5 -> #REF!
B12: Fully diluted share count | C12: =C11+$H$10 -> 73.555 | D12: =D11+$H$10 -> 79.555 | E12: =E11+$H$10 -> 89.555 | F12: =F11+$H$10 -> 89.855 | G12: =G11+$H$10 -> 101.495 | H12: =H10+H11 -> 116.87 | I12: =H12 -> 116.87 | J12: =I12 -> 116.87
B13: EPS | C13: =C4/C11*1000 -> 1145.3883 | D13: =D4/D11*1000 -> 356.76043 | E13: =E4/E11*1000 -> 733.05399 | F13: =F4/F11*1000 -> 1044.6042 | G13: =G4/G11*1000 -> 1846.9736 | H13: =H4/H12*1000 -> 2.8835458 | I13: =I4/I12*1000 -> 4.3043596 | J13: =J4/J12*1000 -> 6.2742367 | K13: =K4/K11*1000 -> #REF! | L13: =L4/L11*1000 -> #REF!
B15: P/E | C15: =$C$1/C13 -> 15.889808 | D15: =$C$1/D13 -> 51.014627 | E15: =$C$1/E13 -> 24.827639 | F15: =$C$1/F13 -> 17.422866 | G15: =$C$1/G13 -> 9.8539579 | H15: =$C$1/H13 -> 6311.6736 | I15: =$C$1/I13 -> 4228.2712 | J15: =$C$1/J13 -> 2900.7513 | ... L15: =$C$1/L13 -> #REF!
B18: Total Equity | C18: =#REF! -> #REF! | D18: =#REF! -> #REF! | E18: =#REF! -> #REF! | F18: =#REF! -> #REF! | G18: =#REF! -> #REF! | H18: =#REF! -> #REF! | I18: =#REF! -> #REF! | J18: =#REF! -> #REF!
B19: Minority interest | C19: =#REF! -> #REF! | D19: =#REF! -> #REF! | E19: =#REF! -> #REF! | F19: =#REF! -> #REF! | G19: =#REF! -> #REF! | H19: =#REF! -> #REF! | I19: =#REF! -> #REF! | J19: =#REF! -> #REF!
B20: Book value | C20: =(C18-C19)/C11*10^3 -> #REF! | D20: =(D18-D19)/D11*10^3 -> #REF! | E20: =(E18-E19)/E11*10^3 -> #REF! | F20: =(F18-F19)/F11*10^3 -> #REF! | G20: =(G18-G19)/G11*10^3 -> #REF! | H20: =(H18-H19)/H12*10^3 -> #REF! | I20: =(I18-I19)/I12*10^3 -> #REF! | J20: =(J18-J19)/J12*10^3 -> #REF!
B22: P/B | C22: =$C$1/C20 -> #REF! | D22: =$C$1/D20 -> #REF! | E22: =$C$1/E20 -> #REF! | F22: =$C$1/F20 -> #REF! | G22: =$C$1/G20 -> #REF! | H22: =$C$1/H20 -> #REF! | I22: =$C$1/I20 -> #REF! | J22: =$C$1/J20 -> #REF!

Sheet Voulme
A2: 42254 | B2: 16.1 | C2: 16.1 | D2: -0.3 (-1.8 %) | F2: 793220 | G2: 12791000000 | H2: 0 | I2: 0 | J2: 16.3 | K2: 16.4 | L2: 15.9
A3: 42251 | B3: 16.4 | C3: 16.4 | D3: -0.1 (-0.6 %) | F3: 858160 | G3: 14075000000 | H3: 0 | I3: 0 | J3: 16.5 | K3: 16.6 | L3: 16.2
A4: 42250 | B4: 16.5 | C4: 16.5 | D4: -0.3 (-1.8 %) | F4: 1521750 | G4: 25356000000 | H4: 0 | I4: 0 | J4: 16.7 | K4: 17 | L4: 16.4
A5: 42248 | B5: 16.8 | C5: 16.8 | D5: 0.9 (5.7 %) | F5: 1980100 | G5: 32790000000 | H5: 0 | I5: 0 | J5: 15.8 | K5: 17 | L5: 15.8
A6: 42247 | B6: 15.9 | C6: 15.9 | D6: -0.4 (-2.5 %) | F6: 1335790 | G6: 21301000000 | H6: 0 | I6: 0 | J6: 16.1 | K6: 16.2 | L6: 15.8
A7: 42244 | B7: 16.3 | C7: 16.3 | D7: 0.2 (1.2 %) | F7: 1437130 | G7: 23200000000 | H7: 0 | I7: 0 | J7: 16.4 | K7: 16.4 | L7: 15.9
A8: 42243 | B8: 16.1 | C8: 16.1 | D8: 0.5 (3.2 %) | F8: 2543790 | G8: 40979000000 | H8: 50000 | I8: 830000000 | J8: 16 | K8: 16.3 | L8: 16
A9: 42242 | B9: 15.6 | C9: 15.6 | D9: 1.0 (6.8 %) | F9: 2470020 | G9: 37976000000 | H9: 70000 | I9: 1050000000 | J9: 14.8 | K9: 15.6 | L9: 14.8
A10: 42241 | B10: 14.6 | C10: 14.6 | D10: -0.7 (-4.6 %) | F10: 2569560 | G10: 37706000000 | H10: 0 | I10: 0 | J10: 14.4 | K10: 15.3 | L10: 14.3
A11: 42240 | B11: 15.3 | C11: 15.3 | D11: -1.1 (-6.7 %) | F11: 1865240 | G11: 28758000000 | H11: 0 | I11: 0 | J11: 15.9 | K11: 16 | L11: 15.3
A12: 42237 | B12: 16.4 | C12: 16.4 | D12: -0.3 (-1.8 %) | F12: 2457840 | G12: 39270000000 | H12: 0 | I12: 0 | J12: 16.4 | K12: 16.4 | L12: 15.6
A13: 42236 | B13: 16.7 | C13: 16.7 | D13: -0.2 (-1.2 %) | F13: 1381340 | G13: 23238000000 | H13: 0 | I13: 0 | J13: 16.9 | K13: 17.1 | L13: 16.6
... A31: 42212 | B31: 18.8 | C31: 18.8 | D31: 0.3 (1.6 %) | F31: 1531510 | G31: 28477000000 | H31: 0 | I31: 0 | J31: 18.4 | K31: 18.8 | L31: 18.4
G34: =SUM(G2:G31) -> 910022000000 | I34: =SUM(I2:I31) -> 1880000000
F36: =SUM(F34:I34)/30 -> 3.0396733e+10
F37: =F36/21890 -> 1388612.8
F38: =F37/10^6 -> 1.3886128

Sheet EPS
A1: 3 | B1: EPS AND P/E CALCULATION TEMPLATE | M1: IMPORTANT NOTES:
B2: NOTE: | C2: figures in blue font should be hard-coded in manually; figures in black font are automatically calculated | M2: It is necessary to treat Rights Issues as dilutive because the rights can be transfered and results in a change in capital - similar to a new issuance where the original shareholder will be diluted.
C4: COMPANY TICKER | D4: DXG | M4: The bonus element of rights issue must be calculated. The bonus shares must be added to prior periods. If this is not done, EPS growth will be "penalized" for those shares. Refer to theorectical ex-rights price calculation. In this example for DXG, this HAS NOT been done yet.
G5: UPCOMING RIGHTS ISSUE IN 2016
C6: Current share price | D6: =Valuation!#REF! -> #REF! | G6: Rights Issue/Placement | J6: 0 | M6: We will forego time adjustments and will assume capital is raised at the beginning of the year. This is to "contain" the full dilution impact within the same year. Using weighted average will allow the dilution to "spill over" resulting in lower EPS growth in the following year. I feel it is more important to understand the what is happening in terms of capital changes versus pursuing pinpoint accuracy. To see an example of this effect change Time Weight from 100% to 50% in year to 2013 then check impact on EPS growth vs. NPAT growth.
C7: Theorectical Ex-Rights Price | D7: =Valuation!#REF! -> #REF! | G7: Exercise Price | J7: 10000
C8: Include upcoming Rights Issue | D8: No | G8: Fair value shares | J8: =(J6*J7)/D6 -> #REF! | M8: If we include upcoming share expansions that result in change in capital, it is necessary to adjust the stock price to calculate multiples.
C9: Current reporting year | D9: 2015 | G9: Bonus element | J9: =J6-J8 -> #REF! | M9: If upcoming share expansion does not result in change in capital, use market price, as there will be no changes in EPS growth or PER.
D11: Historical | I11: Forecast
D12: =$D$9-5 -> 2010 | E12: =D12+1 -> 2011 | F12: =E12+1 -> 2012 | G12: =F12+1 -> 2013 | H12: =G12+1 -> 2014 | I12: =H12+1 -> 2015 | J12: =I12+1 -> 2016 | K12: =J12+1 -> 2017
C13: TIME WEIGHT | D13: 1 | E13: 1 | F13: 1 | G13: 1 | H13: 1 | I13: 1 | J13: 1 | K13: 1
C14: NPAT less MI, adjusted | D14: ='P&L'!C32-D15 -> 66.531287 | E14: ='P&L'!D32-E15 -> 18.887496 | F14: ='P&L'!E32-F15 -> 54.551951 | G14: ='P&L'!F32-G15 -> 47.291502 | H14: ='P&L'!G32-H15 -> 94.563846 | I14: ='P&L'!H32-I15 -> 0.2473 | J14: ='P&L'!I32-J15 -> 0.41859244 | K14: ='P&L'!J32-K15 -> 0.64232233 | M14: NPAT less Minority Interest, excluding after tax exceptional items and deduct contribution to employee bonus
C15: --> Adj of bonus welfare fund (C200) | D15: 5.548 | E15: 5.704 | F15: 3.308 | G15: 5.682 | H15: 19.363 | I15: ='P&L'!H30*10% -> 0.0337 | J15: ='P&L'!I30*10% -> 0.050305051 | K15: ='P&L'!J30*10% -> 0.073327004
C16: Begin | D16: 8 | E16: 16 | F16: 32 | G16: 42 | H16: 52.799681 | I16: 75 | J16: =I25 -> #REF! | K16: =J25 -> #REF!
C17: Breakdown of new shares added each year:
B18: Dilutive - Change in capital resources | C18: Private placement | E18: 5.2 | F18: 10 | H18: 11.64 | I18: 25.7
C19: Follow-on share offerings
C20: Rights issue (fair value) | D20: 6.6 | E20: 9 | H20: 8 | J20: =IF(D8="YES",J8,0) -> 0 | M20: Note I have made abitrary changes to completed rights issues i.e split fair and bonus to illustrate. These are not actual figures. Rights issue for 2016 is properly calculated
B21: Non-Dilutive - no change in capital resources | C21: Rights issue (bonus element) | D21: 1 | E21: 1 | H21: 2.6 | J21: =IF(D8="YES",J9,0) -> 0
C22: Share dividend | G22: 10.4996 | I22: =5.545+10.6 -> 16.145 | M22: For further reference see link below.
C23: Bonus shares | M23: http://accounting-simplified.com/ifrs/ias-33-eps/basic/rights-issue.html#adjustment
C25: Year end count unadjusted | D25: =SUM(D16:D23) -> 15.6 | E25: =SUM(E16:E23) -> 31.2 | F25: =SUM(F16:F23) -> 42 | G25: =SUM(G16:G23) -> 52.4996 | H25: =SUM(H16:H23) -> 75.039681 | I25: =Equity!#REF! -> #REF! | J25: =Equity!#REF! -> #REF! | K25: =Equity!#REF! -> #REF!
C26: Adjusted share count (m) | D26: =D16+(D13* SUM(D18:D20))+SUM(D21:$J23) -> 45.8446 | E26: =E16+(E13* SUM(E18:E20))+SUM(E21:$J23) -> 60.4446 | F26: =F16+(F13* SUM(F18:F20))+SUM(F21:$J23) -> 71.2446 | G26: =G16+(G13* SUM(G18:G20))+SUM(G21:$J23) -> 71.2446 | H26: =H16+(H13* SUM(H18:H20))+SUM(H21:$J23) -> 91.184681 | I26: =I25 -> #REF! | J26: =J25 -> #REF! | K26: =K25 -> #REF!
C28: Unadjusted EPS | D28: =D14/D25*1000 -> 4264.8261 | E28: =E14/E25*1000 -> 605.36847 | F28: =F14/F25*1000 -> 1298.856 | G28: =G14/G25*1000 -> 900.79737 | H28: =H14/H25*1000 -> 1260.1845 | I28: =I14/I25*1000 -> #REF! | J28: =J14/J25*1000 -> #REF! | K28: =K14/K25*1000 -> #REF!
C29: Adjusted EPS | D29: =D14/D26*1000 -> 1451.235 | E29: =E14/E26*1000 -> 312.47616 | F29: =F14/F26*1000 -> 765.69945 | G29: =G14/G26*1000 -> 663.79069 | H29: =H14/H26*1000 -> 1037.0585 | I29: =I14/I26*1000 -> #REF! | J29: =J14/J26*1000 -> #REF! | K29: =K14/K26*1000 -> #REF! | M29: Going forward, C200 requires adjustment for employee bonus, we will start applying this treatment now
C31: EPS growth | E31: =E28/D28-1 -> -0.85805553 | F31: =F28/E28-1 -> 1.1455627 | G31: =G28/F28-1 -> -0.30646862 | H31: =H28/G28-1 -> 0.3989656 | I31: =I28/H28-1 -> #REF! | J31: =J28/I28-1 -> #REF! | K31: =K28/J28-1 -> #REF!
C32: Adj EPS growth | E32: =E29/D29-1 -> -0.78468259 | F32: =F29/E29-1 -> 1.4504252 | G32: =G29/F29-1 -> -0.13309239 | H32: =H29/G29-1 -> 0.56232754 | I32: =I29/H29-1 -> #REF! | J32: =J29/I29-1 -> #REF! | K32: =K29/J29-1 -> #REF!
C33: NPAT growth | E33: =E14/D14-1 -> -0.71611106 | F33: =F14/E14-1 -> 1.8882574 | G33: =G14/F14-1 -> -0.13309239 | H33: =H14/G14-1 -> 0.9995949 | I33: =I14/H14-1 -> -0.99738484 | J33: =J14/I14-1 -> 0.69265038 | K33: =K14/J14-1 -> 0.53448144
C35: P/E | E35: =$D$7/E29 -> #REF! | F35: =$D$7/F29 -> #REF! | G35: =D6/G29 -> #REF! | H35: =D6/H29 -> #REF! | I35: =D6/I29 -> #REF! | J35: =D7/J29 -> #REF! | K35: =$D$7/K29 -> #REF!
C37: Total Equity | D37: 288.99152 | E37: 457.17548 | F37: 579.59414 | G37: 663.61479 | H37: =#REF! -> #REF! | I37: =#REF! -> #REF! | J37: =#REF! -> #REF! | K37: =#REF! -> #REF!
C38: Minority interest | D38: 45.393554 | E38: 55.78551 | F38: 23.858045 | G38: 30.481793 | H38: =#REF! -> #REF! | I38: =#REF! -> #REF! | J38: =#REF! -> #REF! | K38: =#REF! -> #REF!
C39: Book value per share | D39: =(D37-D38)/D26*10^3 -> 5313.5586 | E39: =(E37-E38)/E26*10^3 -> 6640.6257 | F39: =(F37-F38)/F26*10^3 -> 7800.3961 | G39: =(G37-G38)/G26*10^3 -> 8886.7506 | H39: =(H37-H38)/H26*10^3 -> #REF! | I39: =(I37-I38)/I26*10^3 -> #REF! | J39: =(J37-J38)/J26*10^3 -> #REF! | K39: =(K37-K38)/K26*10^3 -> #REF!
C40: P/B | D40: =$D$6/D39 -> #REF! | E40: =$D$6/E39 -> #REF! | F40: =$D$6/F39 -> #REF! | G40: =$D$6/G39 -> #REF! | H40: =$D$6/H39 -> #REF! | I40: =$D$6/I39 -> #REF! | J40: =$D$7/J39 -> #REF! | K40: =$D$7/K39 -> #REF!
C42: NPAT less MI, reported | D42: ='P&L'!C30 -> 72.079287 | E42: ='P&L'!D30 -> 24.591496 | F42: ='P&L'!E30 -> 57.859951 | G42: ='P&L'!F30 -> 82.763994 | H42: ='P&L'!G30 -> 167.83449 | I42: ='P&L'!H30 -> 0.337 | J42: ='P&L'!I30 -> 0.50305051 | K42: ='P&L'!J30 -> 0.73327004
C43: Adjusted share count (basic)
C44: EPS basic reported | D44: =D42/D26*1000 -> 1572.2525 | E44: =E42/E26*1000 -> 406.84356 | F44: =F42/F26*1000 -> 812.13104 | G44: =G42/G26*1000 -> 1161.688 | H44: =H42/H26*1000 -> 1840.5996 | I44: =I42/I26*1000 -> #REF! | J44: =J42/J26*1000 -> #REF! | K44: =K42/K26*1000 -> #REF!
C45: EPS basic adjusted | D45: =D29 -> 1451.235 | E45: =E29 -> 312.47616 | F45: =F29 -> 765.69945 | G45: =G29 -> 663.79069 | H45: =H29 -> 1037.0585 | I45: =I29 -> #REF! | J45: =J29 -> #REF! | K45: =K29 -> #REF!
C46: Fully diluted shares | D46: =D26+10.56 -> 56.4046 | E46: =E26+10.56 -> 71.0046 | F46: =F26+10.56 -> 81.8046 | G46: =G26+10.56 -> 81.8046 | H46: =H26+10.56 -> 101.74468 | I46: =I26 -> #REF! | J46: =J26 -> #REF! | K46: =K26 -> #REF!
C47: EPS fully diluted | D47: =D14/D46*1000 -> 1179.5365 | E47: =E14/E46*1000 -> 266.00384 | F47: =F14/F46*1000 -> 666.85677 | G47: =G14/G46*1000 -> 578.10321 | H47: =H14/H46*1000 -> 929.42299 | I47: =I14/I46*1000 -> #REF! | J47: =J14/J46*1000 -> #REF! | K47: =K14/K46*1000 -> #REF!

Sheet Bloomberg
A3: =ticker -> DXG VN EQUITY | B3: ="CY"&year-12 -> CY2013
A4: Date | B4: =_xll.BDH($A$3,$A$5:$A$64,B3,"","Dir=H","Dts=S","Sort=A","Quote=C","QtTyp=Y","Days=A","Per=cy","DtFmt=D","Fill=0","UseDPDF=Y","cols=12;rows=61") -> #NAME? | C4: 37986 | D4: 38352 | E4: 38716 | F4: 39080 | G4: 39444 | H4: 39813 | I4: 40178 | J4: 40543 | K4: 40907 | L4: 41274 | M4: 41639 | N4: 42004
A5: SALES_REV_TURN | B5: 0 | C5: 0 | D5: 0 | E5: 0 | F5: 0 | G5: 28607.371 | H5: 28610.677 | I5: 84909.411 | J5: 374255.04 | K5: 286386.26 | L5: 403502.98 | M5: 342591.14 | N5: 506180.66
A6: IS_COGS_TO_FE_AND_PP_AND_G | B6: 0 | C6: 0 | D6: 0 | E6: 0 | F6: 0 | G6: 3518.2214 | H6: 4046.6697 | I6: 6118.7114 | J6: 204977.95 | K6: 80303.295 | L6: 210618.2 | M6: 136660.21 | N6: 204365.45
A7: ARD_SALES_MKT_ADVERTISING_EXP | B7: 0 | C7: 0 | D7: 0 | E7: 0 | F7: 0 | G7: 5283.724 | H7: 7905.5888 | I7: 18678.028 | J7: 35836.083 | K7: 45220.325 | L7: 44045.725 | M7: 62493.81 | N7: 54302.47 | P7: =L7+L8 -> 122716.96 | Q7: =M7+M8 -> 143739.85 | R7: =N7+N8 -> 136630.05
A8: ARD_GENERAL_ADMINISTRATIVE_EXP | B8: 0 | C8: 0 | D8: 0 | E8: 0 | F8: 0 | G8: 4482.1224 | H8: 8711.7508 | I8: 23742.199 | J8: 54237.319 | K8: 83735.938 | L8: 78671.24 | M8: 81246.045 | N8: 82327.577
A9: IS_OPER_INC | B9: 0 | C9: 0 | D9: 0 | E9: 0 | F9: 0 | G9: 15323.304 | H9: 7946.6674 | I9: 36370.473 | J9: 79203.69 | K9: 77126.706 | L9: 70167.824 | M9: 62191.073 | N9: 165185.16
A10: IS_FOREIGN_EXCH_LOSS | B10: 0 | C10: 0 | D10: 0 | E10: 0 | F10: 0 | G10: 0 | H10: 0 | I10: 0 | J10: 0 | K10: 0 | L10: -42.025 | M10: 0 | N10: 0
A11: IS_NET_NON_OPER_LOSS | B11: 0 | C11: 0 | D11: 0 | E11: 0 | F11: 0 | G11: -238.6071 | H11: -1524.915 | I11: -10921.238 | J11: -32021.182 | K11: -16821.034 | L11: -15520.407 | M11: -58637.8 | N11: -101263.15
A12: IS_INT_EXPENSE | B12: 0 | C12: 0 | D12: 0 | E12: 0 | F12: 0 | G12: 56.1367 | H12: 0 | I12: 5.3629 | J12: 1033.1689 | K12: 38554.054 | L12: 6616.4557 | M12: 342.829 | N12: 79.2907
A13: IS_INC_TAX_EXP | B13: 0 | C13: 0 | D13: 0 | E13: 0 | F13: 0 | G13: 4341.6167 | H13: 2638.9703 | I13: 9269.2797 | J13: 32336.92 | K13: 22333.479 | L13: 20018.952 | M13: 30756.144 | N13: 53321.005
A14: MIN_NONCONTROL_INTEREST_CREDITS | B14: 0 | C14: 0 | D14: 0 | E14: 0 | F14: 0 | G14: 0 | H14: 0 | I14: -124.1939 | J14: 5775.4965 | K14: 8468.7108 | L14: 1234.897 | M14: 6965.9064 | N14: 45213.531
A15: EBITDA | B15: 0 | C15: 0 | D15: 0 | E15: 0 | F15: 0 | G15: 15479.646 | H15: 8384.3383 | I15: 37359.175 | J15: 81273.525 | K15: 80987.137 | L15: 74063.457 | M15: 65730.594 | N15: 168474.61
A16: IS_DEPR_EXP | B16: 0 | C16: 0 | D16: 0 | E16: 0 | F16: 0 | G16: 156.3425 | H16: 437.671 | I16: 916.076 | J16: 1995.131 | K16: 2917.0359 | L16: 2959.1801 | M16: 2192.354 | N16: 2297.6035
A17: BS_CASH_NEAR_CASH_ITEM | B17: 0 | C17: 0 | D17: 0 | E17: 0 | F17: 0 | G17: 31559.074 | H17: 39657.925 | I17: 78033.22 | J17: 161564.46 | K17: 107361.8 | L17: 136052.65 | M17: 72886.29 | N17: 776338.99
A18: BS_MKT_SEC_OTHER_ST_INVEST | B18: 0 | C18: 0 | D18: 0 | E18: 0 | F18: 0 | G18: 0 | H18: 0 | I18: 0 | J18: 0 | K18: 0 | L18: 0 | M18: 0 | N18: 0
A19: BS_ACCT_NOTE_RCV | B19: 0 | C19: 0 | D19: 0 | E19: 0 | F19: 0 | G19: 0 | H19: 3332.833 | I19: 1684.5235 | J19: 51946.89 | K19: 137804.63 | L19: 125808.68 | M19: 131245.3 | N19: 119201.13
... A64: DVD_PAYOUT_RATIO | B64: 0 | C64: 0 | D64: 0 | E64: 0 | F64: 0 | G64: 0 | H64: 0 | I64: 73.4113 | J64: 59.2181 | K64: 0 | L64: 0 | M64: 0 | N64: 0
B66: ="CQ4"&year-3 -> CQ42022 | C66: ="CQ4"&year -> CQ42025
B67: =_xll.BDH(ticker,$A$68:$A$125,B66,C66,"Dir=H","Dts=S","Sort=A","Quote=C","QtTyp=Y","Days=A","Per=cq","DtFmt=D","Fill=0","UseDPDF=Y","cols=12;rows=59") -> #NAME? | C67: 40998 | D67: 41089 | E67: 41180 | F67: 41274 | G67: 41362 | H67: 41453 | I67: 41547 | J67: 41639 | K67: 41729 | L67: 41820 | M67: 41912 | N67: 42004 | O67: 42094
A68: SALES_REV_TURN | B68: 45976.524 | C68: 34725.55 | D68: 94877.759 | E68: 152942.42 | F68: 120957.26 | G68: 48773.071 | H68: 139055.14 | I68: 31324.253 | J68: 123438.67 | K68: 92389.558 | L68: 117633.06 | M68: 57464.837 | N68: 238693.2 | O68: 171599.67
A69: IS_COGS_TO_FE_AND_PP_AND_G | B69: 4822.3274 | C69: 3821.4099 | D69: 46378.936 | E69: 89321.595 | F69: 71096.255 | G69: 19581.237 | H69: 65363.035 | I69: 5599.4087 | J69: 46116.532 | K69: 42966.623 | L69: 34341.225 | M69: 20105.175 | N69: 106952.43 | O69: 71341.777
A70: ARD_SALES_MKT_ADVERTISING_EXP | B70: 15881.564 | C70: 6718.8995 | D70: 13199.601 | E70: 11821.989 | F70: 12305.236 | G70: 11643.514 | H70: 26212.991 | I70: 10077.196 | J70: 14560.108 | K70: 6828.6185 | L70: 12496.487 | M70: 10398.006 | N70: 24579.358 | O70: 14572.18
A71: ARD_GENERAL_ADMINISTRATIVE_EXP | B71: 29180.805 | C71: 19319.28 | D71: 19337.477 | E71: 18828.244 | F71: 21186.238 | G71: 17635.771 | H71: 18224.652 | I71: 20001.84 | J71: 25383.783 | K71: 15070.207 | L71: 19021.671 | M71: 17674.513 | N71: 30561.187 | O71: 24895.741
A72: IS_OPER_INC | B72: -3908.1724 | C72: 4865.9608 | D72: 15961.745 | E72: 32970.587 | F72: 16369.531 | G72: -87.4506 | H72: 29254.465 | I72: -4354.1914 | J72: 37378.25 | K72: 27524.11 | L72: 51773.681 | M72: 9287.1427 | N72: 76600.228 | O72: 60789.973
A73: IS_FOREIGN_EXCH_LOSS | B73: 0 | C73: 0 | D73: 0 | E73: 0 | F73: 0 | G73: 0 | H73: 0 | I73: 0 | J73: 0 | K73: 0 | L73: 0 | M73: 0 | N73: 0 | O73: 0
A74: IS_NET_NON_OPER_LOSS | B74: -1800.6132 | C74: -1554.492 | D74: 397.8238 | E74: -2357.5704 | F74: -12048.193 | G74: -1982.2024 | H74: -1484.1765 | I74: -43705.19 | J74: -11466.231 | K74: -1336.4533 | L74: -5666.0597 | M74: -5999.0715 | N74: -88261.57 | O74: -10696.592
A75: IS_INT_EXPENSE | B75: 14047.063 | C75: 3709.756 | D75: 1776.8341 | E75: 1073.3554 | F75: 56.5102 | G75: 45.5231 | H75: 55.1752 | I75: 32.2711 | J75: 209.8597 | K75: 33.6088 | L75: 11.0954 | M75: 9.8985 | N75: 24.6881 | O75: 25.3813
A76: IS_INC_TAX_EXP | B76: 1196.5996 | C76: 4032.2641 | D76: 4465.5487 | E76: 7039.2748 | F76: 4481.864 | G76: 1939.814 | H76: 10032.337 | I76: 9490.7923 | J76: 9293.2007 | K76: 6650.3025 | L76: 12662.513 | M76: 4485.0403 | N76: 29523.15 | O76: 12201.29
A77: MIN_NONCONTROL_INTEREST_CREDITS | B77: 413.2477 | C77: -3875.888 | D77: 3633.6453 | E77: 1722.1895 | F77: -245.0498 | G77: -1495.3463 | H77: 576.1958 | I77: -251.3511 | J77: 8136.408 | K77: 859.7138 | L77: 13436 | M77: 9823.3077 | N77: 21094.509 | O77: 22664.508
A78: EBITDA | B78: -3302.6433 | C78: 5825.668 | D78: 16666.082 | E78: 33755.945 | F78: 18034.842 | G78: 927.5444 | H78: 30202.27 | I78: -3472.8279 | J78: 38073.607 | K78: 28342.567 | L78: 52592.414 | M78: 10101.104 | N78: 77438.521 | O78: 61546.401
A79: IS_DEPR_EXP | B79: 597.1047 | C79: 725.5938 | D79: 689.3034 | E79: 770.3237 | F79: 773.9593 | G79: 780.5484 | H79: 713.3222 | I79: 648.1406 | J79: 50.3428 | K79: 577.3177 | L79: 577.593 | M79: 566.8921 | N79: 575.8007 | O79: 643.0904
... A125: PX LAST | B125: 5407.72 | C125: 6643.77 | D125: 7339.04 | E125: 5871.24 | F125: 8343.33 | G125: 8806.85 | H125: 9149.86 | I125: 8565.82 | J125: 12500 | K125: 16300 | L125: 12659.3 | M125: 13084.11 | N125: 11894.65 | O125: 15454.55

Sheet FS Year
C1: Currrent Price | D1: 15900
D2: ='Valuation summary'!P47 -> 14309.04 | L2: =32*1.25 -> 40 | M2: =42*1.25 -> 52.5 | N2: =52.8*1.25 -> 66 | O2: 75 | P2: 75 | Q2: 125 | R2: 125 | T2: 17400
L3: 25000 | M3: 58000 | N3: 83000 | P3: =135*1000 -> 135000 | Q3: =Q24*1000 -> 337 | R3: =R24*1000 -> 503.05051 | T3: =$T$2/M142 -> 1.6437658 | U3: =$T$2/N142 -> 1.8138369 | V3: =$T$2/P142 -> #DIV/0! | W3: =$T$2/Q142 -> #DIV/0! | X3: =$T$2/R142 -> #DIV/0!
L4: =L3/L2 -> 625 | M4: =M3/M2 -> 1104.7619 | N4: =N3/N2 -> 1257.5758 | P4: =P3/P2 -> 1800 | Q4: =Q3/Q2 -> 2.696 | R4: =R3/R2 -> 4.0244041
L5: =$D$1/L4 -> 25.44 | M5: =$D$1/M4 -> 14.392241 | N5: =$D$1/N4 -> 12.643373 | P5: =$D$2/P4 -> 7.9494667 | Q5: =$D$2/Q4 -> 5307.5074 | R5: =$D$2/R4 -> 3555.5674
N6: =(N4-M4)/M4 -> 0.13832288 | P6: =(P4-N4)/N4 -> 0.4313253 | Q6: =(Q4-P4)/P4 -> -0.99850222 | R6: =(R4-Q4)/Q4 -> 0.49273148
B7: =ticker -> DXG VN EQUITY | N7: 1.25 | R7: =((R4/P4)^(1/3))-1 -> -0.86923956
B8: 1000
B9: INCOME STATEMENT | D9: =year-12 -> 2013 | E9: =D9+1 -> 2014 | F9: =E9+1 -> 2015 | G9: =F9+1 -> 2016 | H9: =G9+1 -> 2017 | I9: =H9+1 -> 2018 | J9: =I9+1 -> 2019 | K9: =J9+1 -> 2020 | L9: =K9+1 -> 2021 | ... N9: =M9+1 -> 2023 | O9: 2014A | P9: =N9+1 -> 2024 | Q9: =P9+1 -> 2025 | R9: =Q9+1 -> 2026 | S9: =R9+1 -> 2027 | T9: =S9+1 -> 2028 | U9: =T9+1 -> 2029 | V9: =U9+1 -> 2030 | W9: =V9+1 -> 2031 | X9: =W9+1 -> 2032 | Y9: =X9+1 -> 2033
B10: Revenue | D10: =Bloomberg!C5/unit -> 0 | E10: =Bloomberg!D5/unit -> 0 | F10: =Bloomberg!E5/unit -> 0 | G10: =Bloomberg!F5/unit -> 0 | H10: =Bloomberg!G5/unit -> 28.607371 | I10: =Bloomberg!H5/unit -> 28.610677 | J10: =Bloomberg!I5/unit -> 84.909411 | K10: =Bloomberg!J5/unit -> 374.25504 | ... O10: =Bloomberg!N5/unit -> 506.18066 | P10: ='P&L'!#REF! -> #REF! | Q10: ='P&L'!H10 -> 1.395 | R10: ='P&L'!I10 -> 2.5065169 | S10: ='P&L'!J10 -> 2.8792414 | T10: ='P&L'!K10 -> 4.6453186 | U10: ='P&L'!L10 -> 5.8135777 | V10: ='P&L'!M10 -> 0 | W10: ='P&L'!N10 -> 0 | X10: ='P&L'!O10 -> 0 | Y10: ='P&L'!P10 -> 0
B11: - Cost of goods sold | D11: =-Bloomberg!C6/unit -> 0 | E11: =-Bloomberg!D6/unit -> 0 | F11: =-Bloomberg!E6/unit -> 0 | G11: =-Bloomberg!F6/unit -> 0 | H11: =-Bloomberg!G6/unit -> -3.5182214 | I11: =-Bloomberg!H6/unit -> -4.0466697 | J11: =-Bloomberg!I6/unit -> -6.1187114 | K11: =-Bloomberg!J6/unit -> -204.97795 | ... O11: =-Bloomberg!N6/unit -> -204.36545 | P11: ='P&L'!#REF! -> #REF! | Q11: ='P&L'!H11 -> -0.735 | R11: ='P&L'!I11 -> -1.4548796 | S11: ='P&L'!J11 -> -1.14944 | T11: ='P&L'!K11 -> -2.0305444 | U11: ='P&L'!L11 -> -2.7299755 | V11: ='P&L'!M11 -> 0 | W11: ='P&L'!N11 -> 0 | X11: ='P&L'!O11 -> 0 | Y11: ='P&L'!P11 -> 0
B12: Gross profit | D12: =SUM(D10:D11) -> 0 | E12: =SUM(E10:E11) -> 0 | F12: =SUM(F10:F11) -> 0 | G12: =SUM(G10:G11) -> 0 | H12: =SUM(H10:H11) -> 25.08915 | I12: =SUM(I10:I11) -> 24.564007 | J12: =SUM(J10:J11) -> 78.790699 | K12: =SUM(K10:K11) -> 169.27709 | ... O12: =SUM(O10:O11) -> 301.81521 | P12: ='P&L'!#REF! -> #REF! | Q12: ='P&L'!H12 -> 0.66 | R12: ='P&L'!I12 -> 1.0516373 | S12: ='P&L'!J12 -> 1.7298014 | T12: ='P&L'!K12 -> 2.6147742 | U12: ='P&L'!L12 -> 3.0836022 | V12: ='P&L'!M12 -> 0 | W12: ='P&L'!N12 -> 0 | X12: ='P&L'!O12 -> 0 | Y12: ='P&L'!P12 -> 0
B13: - Sales and marketing exp | D13: =-Bloomberg!C7/unit -> 0 | E13: =-Bloomberg!D7/unit -> 0 | F13: =-Bloomberg!E7/unit -> 0 | G13: =-Bloomberg!F7/unit -> 0 | H13: =-Bloomberg!G7/unit -> -5.283724 | I13: =-Bloomberg!H7/unit -> -7.9055888 | J13: =-Bloomberg!I7/unit -> -18.678028 | K13: =-Bloomberg!J7/unit -> -35.836083 | ... O13: =-Bloomberg!N7/unit -> -54.30247 | P13: ='P&L'!#REF! -> #REF! | Q13: ='P&L'!H14 -> -0.162 | R13: ='P&L'!I14 -> -0.25330222 | S13: ='P&L'!J14 -> -0.34785493 | T13: ='P&L'!K14 -> -0.5146234 | U13: ='P&L'!L14 -> -0.66952142 | V13: ='P&L'!M14 -> 0 | W13: ='P&L'!N14 -> 0 | X13: ='P&L'!O14 -> 0 | Y13: ='P&L'!P14 -> 0
B14: - General and administrative exp | D14: =-Bloomberg!C8/unit -> 0 | E14: =-Bloomberg!D8/unit -> 0 | F14: =-Bloomberg!E8/unit -> 0 | G14: =-Bloomberg!F8/unit -> 0 | H14: =-Bloomberg!G8/unit -> -4.4821224 | I14: =-Bloomberg!H8/unit -> -8.7117508 | J14: =-Bloomberg!I8/unit -> -23.742199 | K14: =-Bloomberg!J8/unit -> -54.237319 | ... O14: =-Bloomberg!N8/unit -> -82.327577 | P14: ='P&L'!#REF! -> #REF! | Q14: ='P&L'!H16 -> -0.108 | R14: ='P&L'!I16 -> -0.15524975 | S14: ='P&L'!J16 -> -0.1956684 | T14: ='P&L'!K16 -> -0.26510903 | U14: ='P&L'!L16 -> -0.3150689 | V14: ='P&L'!M16 -> 0 | W14: ='P&L'!N16 -> 0 | X14: ='P&L'!O16 -> 0 | Y14: ='P&L'!P16 -> 0
B15: Operating profit | D15: =SUM(D12:D14) -> 0 | E15: =SUM(E12:E14) -> 0 | F15: =SUM(F12:F14) -> 0 | G15: =SUM(G12:G14) -> 0 | H15: =SUM(H12:H14) -> 15.323303 | I15: =SUM(I12:I14) -> 7.9466674 | J15: =SUM(J12:J14) -> 36.370473 | K15: =SUM(K12:K14) -> 79.20369 | ... O15: =SUM(O12:O14) -> 165.18516 | P15: =P12+P13+P14 -> #REF! | Q15: =Q12+Q13+Q14 -> 0.39 | R15: =R12+R13+R14 -> 0.6430853 | S15: =S12+S13+S14 -> 1.186278 | T15: =T12+T13+T14 -> 1.8350418 | U15: =U12+U13+U14 -> 2.0990119 | V15: =V12+V13+V14 -> 0 | W15: =W12+W13+W14 -> 0 | ... Y15: =Y12+Y13+Y14 -> 0
B16: - Forex (losses) / gains | D16: =-Bloomberg!C10/unit -> 0 | E16: =-Bloomberg!D10/unit -> 0 | F16: =-Bloomberg!E10/unit -> 0 | G16: =-Bloomberg!F10/unit -> 0 | H16: =-Bloomberg!G10/unit -> 0 | I16: =-Bloomberg!H10/unit -> 0 | J16: =-Bloomberg!I10/unit -> 0 | K16: =-Bloomberg!J10/unit -> 0 | ... O16: =-Bloomberg!N10/unit -> 0 | P16: ='P&L'!#REF! -> #REF! | Q16: ='P&L'!H21 -> 0.093 | R16: ='P&L'!I21 -> 0.10465975 | S16: ='P&L'!J21 -> 0.066074832 | T16: ='P&L'!K21 -> 0.20673132 | U16: ='P&L'!L21 -> 0.27047204 | V16: ='P&L'!M21 -> 0 | W16: ='P&L'!N21 -> 0 | X16: ='P&L'!O21 -> 0 | Y16: ='P&L'!P21 -> 0
B17: - Net non-operating (losses) / gains | D17: =-Bloomberg!C11/unit -> 0 | E17: =-Bloomberg!D11/unit -> 0 | F17: =-Bloomberg!E11/unit -> 0 | G17: =-Bloomberg!F11/unit -> 0 | H17: =-Bloomberg!G11/unit -> 0.2386071 | I17: =-Bloomberg!H11/unit -> 1.524915 | J17: =-Bloomberg!I11/unit -> 10.921238 | K17: =-Bloomberg!J11/unit -> 32.021182 | ... O17: =-Bloomberg!N11/unit -> 101.26315 | P17: ='P&L'!#REF! -> #REF! | Q17: ='P&L'!H22+'P&L'!H24+'P&L'!H25 -> 0.123 | R17: ='P&L'!I22+'P&L'!I24+'P&L'!I25 -> 0.10619569 | S17: ='P&L'!J22+'P&L'!J24+'P&L'!J25 -> 0.14563212 | T17: ='P&L'!K22+'P&L'!K24+'P&L'!K25 -> 0.25076595 | U17: ='P&L'!L22+'P&L'!L24+'P&L'!L25 -> 0.22806085 | V17: ='P&L'!M22+'P&L'!M24+'P&L'!M25 -> 0 | W17: ='P&L'!N22+'P&L'!N24+'P&L'!N25 -> 0 | X17: ='P&L'!O22+'P&L'!O24+'P&L'!O25 -> 0 | Y17: ='P&L'!P22+'P&L'!P24+'P&L'!P25 -> 0
B18: EBIT | D18: =SUM(D15:D17) -> 0 | E18: =SUM(E15:E17) -> 0 | F18: =SUM(F15:F17) -> 0 | G18: =SUM(G15:G17) -> 0 | H18: =SUM(H15:H17) -> 15.56191 | I18: =SUM(I15:I17) -> 9.4715824 | J18: =SUM(J15:J17) -> 47.291711 | K18: =SUM(K15:K17) -> 111.22487 | ... Y18: =SUM(Y15:Y17) -> 0
B19: - Interest exp | D19: =-Bloomberg!C12/unit -> 0 | E19: =-Bloomberg!D12/unit -> 0 | F19: =-Bloomberg!E12/unit -> 0 | G19: =-Bloomberg!F12/unit -> 0 | H19: =-Bloomberg!G12/unit -> -0.0561367 | I19: =-Bloomberg!H12/unit -> 0 | J19: =-Bloomberg!I12/unit -> -0.0053629 | K19: =-Bloomberg!J12/unit -> -1.0331689 | ... O19: =-Bloomberg!N12/unit -> -0.0792907 | P19: ='P&L'!#REF! -> #REF! | Q19: ='P&L'!H23 -> -0.009 | R19: ='P&L'!I23 -> -0.032702591 | S19: ='P&L'!J23 -> -0.062664889 | T19: ='P&L'!K23 -> -0.19075452 | U19: ='P&L'!L23 -> -0.20903103 | V19: ='P&L'!M23 -> 0 | W19: ='P&L'!N23 -> 0 | X19: ='P&L'!O23 -> 0 | Y19: ='P&L'!P23 -> 0
B20: EBT | D20: =SUM(D18:D19) -> 0 | E20: =SUM(E18:E19) -> 0 | F20: =SUM(F18:F19) -> 0 | G20: =SUM(G18:G19) -> 0 | H20: =SUM(H18:H19) -> 15.505774 | I20: =SUM(I18:I19) -> 9.4715824 | J20: =SUM(J18:J19) -> 47.286348 | K20: =SUM(K18:K19) -> 110.1917 | ... O20: =SUM(O18:O19) -> 266.36903 | P20: ='P&L'!#REF! -> #REF! | Q20: =SUM(Q18:Q19) -> 0.597 | R20: =SUM(R18:R19) -> 0.82123814 | S20: =SUM(S18:S19) -> 1.3353201 | T20: =SUM(T18:T19) -> 2.1017845 | U20: =SUM(U18:U19) -> 2.3885138 | V20: =SUM(V18:V19) -> 0 | W20: =SUM(W18:W19) -> 0 | X20: =SUM(X18:X19) -> 0 | Y20: =SUM(Y18:Y19) -> 0
B21: - Income tax exp | D21: =-Bloomberg!C13/unit -> 0 | E21: =-Bloomberg!D13/unit -> 0 | F21: =-Bloomberg!E13/unit -> 0 | G21: =-Bloomberg!F13/unit -> 0 | H21: =-Bloomberg!G13/unit -> -4.3416167 | I21: =-Bloomberg!H13/unit -> -2.6389703 | J21: =-Bloomberg!I13/unit -> -9.2692797 | K21: =-Bloomberg!J13/unit -> -32.33692 | ... O21: =-Bloomberg!N13/unit -> -53.321005 | P21: ='P&L'!#REF! -> #REF! | Q21: ='P&L'!H27 -> -0.095 | R21: ='P&L'!I27 -> -0.15681483 | S21: ='P&L'!J27 -> -0.24989984 | T21: ='P&L'!K27 -> -0.37898975 | U21: ='P&L'!L27 -> -0.5022951 | V21: ='P&L'!M27 -> 0 | W21: ='P&L'!N27 -> 0 | X21: ='P&L'!O27 -> 0 | Y21: ='P&L'!P27 -> 0
B22: Profit after tax | D22: =SUM(D20:D21) -> 0 | E22: =SUM(E20:E21) -> 0 | F22: =SUM(F20:F21) -> 0 | G22: =SUM(G20:G21) -> 0 | H22: =SUM(H20:H21) -> 11.164157 | I22: =SUM(I20:I21) -> 6.8326121 | J22: =SUM(J20:J21) -> 38.017069 | K22: =SUM(K20:K21) -> 77.854783 | ... O22: =SUM(O20:O21) -> 213.04802 | P22: ='P&L'!#REF! -> #REF! | Q22: ='P&L'!H28 -> 0.446 | R22: ='P&L'!I28 -> 0.63027029 | S22: ='P&L'!J28 -> 1.0677995 | T22: ='P&L'!K28 -> 1.7282958 | U22: ='P&L'!L28 -> 1.8074943 | V22: ='P&L'!M28 -> 0 | W22: ='P&L'!N28 -> 0 | X22: ='P&L'!O28 -> 0 | Y22: ='P&L'!P28 -> 0
B23: - Minority interests | D23: =-Bloomberg!C14/unit -> 0 | E23: =-Bloomberg!D14/unit -> 0 | F23: =-Bloomberg!E14/unit -> 0 | G23: =-Bloomberg!F14/unit -> 0 | H23: =-Bloomberg!G14/unit -> 0 | I23: =-Bloomberg!H14/unit -> 0 | J23: =-Bloomberg!I14/unit -> 0.1241939 | K23: =-Bloomberg!J14/unit -> -5.7754965 | ... O23: =-Bloomberg!N14/unit -> -45.213531 | P23: ='P&L'!#REF! -> #REF! | Q23: ='P&L'!H29 -> -0.109 | R23: ='P&L'!I29 -> -0.12721978 | S23: ='P&L'!J29 -> -0.33452951 | T23: ='P&L'!K29 -> -0.54436776 | U23: ='P&L'!L29 -> -0.6697039 | V23: ='P&L'!M29 -> 0 | W23: ='P&L'!N29 -> 0 | X23: ='P&L'!O29 -> 0 | Y23: ='P&L'!P29 -> 0
B24: Net income to shareholders | D24: =SUM(D22:D23) -> 0 | E24: =SUM(E22:E23) -> 0 | F24: =SUM(F22:F23) -> 0 | G24: =SUM(G22:G23) -> 0 | H24: =SUM(H22:H23) -> 11.164157 | I24: =SUM(I22:I23) -> 6.8326121 | J24: =SUM(J22:J23) -> 38.141262 | K24: =SUM(K22:K23) -> 72.079287 | ... O24: =SUM(O22:O23) -> 167.83449 | P24: ='P&L'!#REF! -> #REF! | Q24: ='P&L'!H30 -> 0.337 | R24: ='P&L'!I30 -> 0.50305051 | S24: ='P&L'!J30 -> 0.73327004 | T24: ='P&L'!K30 -> 1.183928 | U24: ='P&L'!L30 -> 1.1377904 | V24: ='P&L'!M30 -> 0 | W24: ='P&L'!N30 -> 0 | X24: ='P&L'!O30 -> 0 | Y24: ='P&L'!P30 -> 0
B25: Earnings per share (basic) | D25: =D24/D29*10^3 -> #DIV/0! | E25: =E24/E29*10^3 -> #DIV/0! | F25: =F24/F29*10^3 -> #DIV/0! | G25: =G24/G29*10^3 -> #DIV/0! | H25: =H24/H29*10^3 -> 14885.543 | I25: =I24/I29*10^3 -> 1438.4447 | J25: =J24/J29*10^3 -> 4767.6578 | K25: =K24/K29*10^3 -> 6006.6072 | ... Y25: =Y24/Y29*10^3 -> #REF!
B26: Earnings per share (adjusted) | K26: =K24/K30*10^3 -> 6006.6072 | L26: =L24/L30*10^3 -> 1024.6457 | M26: =M24/M30*10^3 -> 1377.6179 | N26: =N24/N30*10^3 -> 1567.5093 | O26: =O24/O30*10^3 -> 2237.7932 | P26: =P4 -> 1800 | Q26: =Q4 -> 2.696 | R26: =R24/R30*10^3 -> #REF! | S26: =S24/S30*10^3 -> #REF!
B27: EBITDA | D27: =D18-D28 -> 0 | E27: =E18-E28 -> 0 | F27: =F18-F28 -> 0 | G27: =G18-G28 -> 0 | H27: =H18-H28 -> 15.718253 | I27: =I18-I28 -> 9.9092534 | J27: =J18-J28 -> 48.207787 | K27: =K18-K28 -> 113.22 | ... O27: =O18-O28 -> 268.74592 | P27: ='P&L'!#REF! -> #REF! | Q27: ='P&L'!H33 -> 0.3953 | R27: ='P&L'!I33 -> 0.6469853 | S27: ='P&L'!J33 -> 1.191123 | T27: ='P&L'!K33 -> 1.8408318 | U27: ='P&L'!L33 -> 2.1057469 | V27: ='P&L'!M33 -> 0 | W27: ='P&L'!N33 -> #REF! | X27: ='P&L'!O33 -> #REF! | Y27: ='P&L'!P33 -> #REF!
B28: Depreciation expense | D28: =-Bloomberg!C16/unit -> 0 | E28: =-Bloomberg!D16/unit -> 0 | F28: =-Bloomberg!E16/unit -> 0 | G28: =-Bloomberg!F16/unit -> 0 | H28: =-Bloomberg!G16/unit -> -0.1563425 | I28: =-Bloomberg!H16/unit -> -0.437671 | J28: =-Bloomberg!I16/unit -> -0.916076 | K28: =-Bloomberg!J16/unit -> -1.995131 | ... O28: =-Bloomberg!N16/unit -> -2.2976035 | P28: ='P&L'!#REF! -> #REF! | Q28: ='P&L'!H34 -> -0.0053 | R28: ='P&L'!I34 -> -0.0039 | S28: ='P&L'!J34 -> -0.004845 | T28: ='P&L'!K34 -> -0.00579 | U28: ='P&L'!L34 -> -0.006735 | V28: ='P&L'!M34 -> 0 | W28: ='P&L'!N34 -> #REF! | X28: ='P&L'!O34 -> #REF! | Y28: ='P&L'!P34 -> #REF!
B29: Outstanding shares | D29: =(C58+D58)/2/10 -> 0 | E29: =(D58+E58)/2/10 -> 0 | F29: =(E58+F58)/2/10 -> 0 | G29: =(F58+G58)/2/10 -> 0 | H29: =(G58+H58)/2/10 -> 0.75 | I29: =(H58+I58)/2/10 -> 4.75 | J29: =(I58+J58)/2/10 -> 8 | K29: =(J58+K58)/2/10 -> 12 | L29: =((K58+L58)/2/10)*1.25 -> 30 | M29: =((L58+M58)/2/10)*1.25 -> 46.25 | N29: =((M58+N58)/2/10)*1.25 -> 59.249801 | O29: =((N58+O58)/2/10)*1.25 -> 79.874801 | P29: =(N58+P58)/2/10 -> #REF! | Q29: =(O58+Q58)/2/10 -> #REF! | R29: =(Q58+R58)/2/10 -> #REF! | S29: =(R58+S58)/2/10 -> #REF! | T29: =(S58+T58)/2/10 -> #REF! | U29: =(T58+U58)/2/10 -> #REF! | V29: =(U58+V58)/2/10 -> #REF! | W29: =(V58+W58)/2/10 -> #REF! | X29: =(W58+X58)/2/10 -> #REF! | Y29: =(X58+Y58)/2/10 -> #REF!
B30: Outstanding shares (adjusted) | K30: 12 | L30: 24 | M30: =M58/10 -> 42 | N30: =N58/10 -> 52.799681 | O30: =O58/10 -> 75 | P30: =P58/10 -> #REF! | Q30: =Q58/10 -> #REF! | R30: =R58/10 -> #REF! | S30: =S58/10 -> #REF! | T30: =T58/10 -> #REF! | ... V30: =V58/10 -> #REF! | W30: =V30 -> #REF! | X30: =W30 -> #REF! | Y30: =X30 -> #REF!
B31: BALANCE SHEET
B32: Assets
B33: + Cash & equivalents | D33: =Bloomberg!C17/unit -> 0 | E33: =Bloomberg!D17/unit -> 0 | F33: =Bloomberg!E17/unit -> 0 | G33: =Bloomberg!F17/unit -> 0 | H33: =Bloomberg!G17/unit -> 31.559074 | I33: =Bloomberg!H17/unit -> 39.657925 | J33: =Bloomberg!I17/unit -> 78.03322 | K33: =Bloomberg!J17/unit -> 161.56446 | ... O33: =Bloomberg!N17/unit -> 776.33899 | P33: =#REF! -> #REF! | Q33: =#REF! -> #REF! | R33: =#REF! -> #REF! | S33: =#REF! -> #REF! | T33: =#REF! -> #REF! | U33: =#REF! -> #REF! | V33: =#REF! -> #REF! | W33: =#REF! -> #REF! | ... Y33: =#REF! -> #REF!
B34: + Short-term investments | D34: =Bloomberg!C18/unit -> 0 | E34: =Bloomberg!D18/unit -> 0 | F34: =Bloomberg!E18/unit -> 0 | G34: =Bloomberg!F18/unit -> 0 | H34: =Bloomberg!G18/unit -> 0 | I34: =Bloomberg!H18/unit -> 0 | J34: =Bloomberg!I18/unit -> 0 | K34: =Bloomberg!J18/unit -> 0 | ... O34: =Bloomberg!N18/unit -> 0 | P34: =#REF! -> #REF! | Q34: =#REF! -> #REF! | R34: =#REF! -> #REF! | S34: =#REF! -> #REF! | T34: =#REF! -> #REF! | U34: =#REF! -> #REF! | V34: =#REF! -> #REF! | W34: =#REF! -> #REF! | ... Y34: =#REF! -> #REF!
B35: + Accounts & notes receivables | D35: =Bloomberg!C19/unit -> 0 | E35: =Bloomberg!D19/unit -> 0 | F35: =Bloomberg!E19/unit -> 0 | G35: =Bloomberg!F19/unit -> 0 | H35: =Bloomberg!G19/unit -> 0 | I35: =Bloomberg!H19/unit -> 3.332833 | J35: =Bloomberg!I19/unit -> 1.6845235 | K35: =Bloomberg!J19/unit -> 51.94689 | ... O35: =Bloomberg!N19/unit -> 119.20113 | P35: =#REF! -> #REF! | Q35: =#REF! -> #REF! | R35: =#REF! -> #REF! | S35: =#REF! -> #REF! | T35: =#REF! -> #REF! | U35: =#REF! -> #REF! | V35: =#REF! -> #REF! | W35: =#REF! -> #REF! | ... Y35: =#REF! -> #REF!
B36: + Inventories | D36: =Bloomberg!C20/unit -> 0 | E36: =Bloomberg!D20/unit -> 0 | F36: =Bloomberg!E20/unit -> 0 | G36: =Bloomberg!F20/unit -> 0 | H36: =Bloomberg!G20/unit -> 11.029091 | I36: =Bloomberg!H20/unit -> 47.387504 | J36: =Bloomberg!I20/unit -> 167.4791 | K36: =Bloomberg!J20/unit -> 249.43949 | ... O36: =Bloomberg!N20/unit -> 499.21431 | P36: =#REF! -> #REF! | Q36: =#REF! -> #REF! | R36: =#REF! -> #REF! | S36: =#REF! -> #REF! | T36: =#REF! -> #REF! | U36: =#REF! -> #REF! | V36: =#REF! -> #REF! | W36: =#REF! -> #REF! | ... Y36: =#REF! -> #REF!
B37: + Other current assets | D37: =Bloomberg!C21/unit -> 0 | E37: =Bloomberg!D21/unit -> 0 | F37: =Bloomberg!E21/unit -> 0 | G37: =Bloomberg!F21/unit -> 0 | H37: =Bloomberg!G21/unit -> 19.645768 | I37: =Bloomberg!H21/unit -> 178.41997 | J37: =Bloomberg!I21/unit -> 205.53053 | K37: =Bloomberg!J21/unit -> 77.914041 | ... O37: =Bloomberg!N21/unit -> 284.11639 | P37: =#REF! -> #REF! | Q37: =#REF! -> #REF! | R37: =#REF! -> #REF! | S37: =#REF! -> #REF! | T37: =#REF! -> #REF! | U37: =#REF! -> #REF! | V37: =#REF! -> #REF! | W37: =#REF! -> #REF! | ... Y37: =#REF! -> #REF!
B38: Total current assets | D38: =Bloomberg!C22/unit -> 0 | E38: =Bloomberg!D22/unit -> 0 | F38: =Bloomberg!E22/unit -> 0 | G38: =Bloomberg!F22/unit -> 0 | H38: =Bloomberg!G22/unit -> 62.233934 | I38: =Bloomberg!H22/unit -> 268.79823 | J38: =Bloomberg!I22/unit -> 452.72738 | K38: =Bloomberg!J22/unit -> 540.86489 | ... O38: =Bloomberg!N22/unit -> 1678.8708 | P38: =#REF! -> #REF! | Q38: =#REF! -> #REF! | R38: =#REF! -> #REF! | S38: =#REF! -> #REF! | T38: =#REF! -> #REF! | U38: =#REF! -> #REF! | V38: =#REF! -> #REF! | W38: =#REF! -> #REF! | ... Y38: =#REF! -> #REF!
B39: + Gross fixed assets | D39: =Bloomberg!C23/unit -> 0 | E39: =Bloomberg!D23/unit -> 0 | F39: =Bloomberg!E23/unit -> 0 | G39: =Bloomberg!F23/unit -> 0 | H39: =Bloomberg!G23/unit -> 1.368667 | I39: =Bloomberg!H23/unit -> 2.9289248 | J39: =Bloomberg!I23/unit -> 11.021873 | K39: =Bloomberg!J23/unit -> 17.300869 | ... O39: =Bloomberg!N23/unit -> 42.124221 | P39: =#REF! -> #REF! | Q39: =#REF! -> #REF! | R39: =#REF! -> #REF! | S39: =#REF! -> #REF! | T39: =#REF! -> #REF! | U39: =#REF! -> #REF! | V39: =#REF! -> #REF! | W39: =#REF! -> #REF! | ... Y39: =#REF! -> #REF!
B40: - Accumulated depreciation | D40: =-Bloomberg!C24/unit -> 0 | E40: =-Bloomberg!D24/unit -> 0 | F40: =-Bloomberg!E24/unit -> 0 | G40: =-Bloomberg!F24/unit -> 0 | H40: =-Bloomberg!G24/unit -> -0.2351129 | I40: =-Bloomberg!H24/unit -> -0.6448353 | J40: =-Bloomberg!I24/unit -> -1.560911 | K40: =-Bloomberg!J24/unit -> -3.548641 | ... O40: =-Bloomberg!N24/unit -> -9.8412946 | P40: =#REF! -> #REF! | Q40: =#REF! -> #REF! | R40: =#REF! -> #REF! | S40: =#REF! -> #REF! | T40: =#REF! -> #REF! | U40: =#REF! -> #REF! | V40: =#REF! -> #REF! | W40: =#REF! -> #REF! | ... Y40: =#REF! -> #REF!
B41: + Net fixed assets | D41: =Bloomberg!C25/unit -> 0 | E41: =Bloomberg!D25/unit -> 0 | F41: =Bloomberg!E25/unit -> 0 | G41: =Bloomberg!F25/unit -> 0 | H41: =Bloomberg!G25/unit -> 1.1335542 | I41: =Bloomberg!H25/unit -> 2.2840895 | J41: =Bloomberg!I25/unit -> 9.4609625 | K41: =Bloomberg!J25/unit -> 13.752228 | ... O41: =Bloomberg!N25/unit -> 32.282926 | P41: =#REF! -> #REF! | Q41: =#REF! -> #REF! | R41: =#REF! -> #REF! | S41: =#REF! -> #REF! | T41: =#REF! -> #REF! | U41: =#REF! -> #REF! | V41: =#REF! -> #REF! | W41: =#REF! -> #REF! | ... Y41: =#REF! -> #REF!
B42: + Long-term investments | D42: =Bloomberg!C26/unit -> 0 | E42: =Bloomberg!D26/unit -> 0 | F42: =Bloomberg!E26/unit -> 0 | G42: =Bloomberg!F26/unit -> 0 | H42: =Bloomberg!G26/unit -> 0 | I42: =Bloomberg!H26/unit -> 0 | J42: =Bloomberg!I26/unit -> 0 | K42: =Bloomberg!J26/unit -> 0 | ... O42: =Bloomberg!N26/unit -> 0 | P42: =#REF! -> #REF! | Q42: =#REF! -> #REF! | R42: =#REF! -> #REF! | S42: =#REF! -> #REF! | T42: =#REF! -> #REF! | U42: =#REF! -> #REF! | V42: =#REF! -> #REF! | W42: =#REF! -> #REF! | ... Y42: =#REF! -> #REF!
B43: + Other Long-term assets | D43: =Bloomberg!C27/unit -> 0 | E43: =Bloomberg!D27/unit -> 0 | F43: =Bloomberg!E27/unit -> 0 | G43: =Bloomberg!F27/unit -> 0 | H43: =Bloomberg!G27/unit -> 0.3362563 | I43: =Bloomberg!H27/unit -> 34.157266 | J43: =Bloomberg!I27/unit -> 85.354977 | K43: =Bloomberg!J27/unit -> 133.1415 | ... O43: =Bloomberg!N27/unit -> 449.29909 | P43: =#REF! -> #REF! | Q43: =#REF! -> #REF! | R43: =#REF! -> #REF! | S43: =#REF! -> #REF! | T43: =#REF! -> #REF! | U43: =#REF! -> #REF! | V43: =#REF! -> #REF! | W43: =#REF! -> #REF! | ... Y43: =#REF! -> #REF!
B44: Total Long-term assets | D44: =Bloomberg!C28/unit -> 0 | E44: =Bloomberg!D28/unit -> 0 | F44: =Bloomberg!E28/unit -> 0 | G44: =Bloomberg!F28/unit -> 0 | H44: =Bloomberg!G28/unit -> 1.4698105 | I44: =Bloomberg!H28/unit -> 36.441355 | J44: =Bloomberg!I28/unit -> 94.81594 | K44: =Bloomberg!J28/unit -> 146.89373 | ... O44: =Bloomberg!N28/unit -> 481.58202 | P44: =#REF! -> #REF! | Q44: =#REF! -> #REF! | R44: =#REF! -> #REF! | S44: =#REF! -> #REF! | T44: =#REF! -> #REF! | U44: =#REF! -> #REF! | V44: =#REF! -> #REF! | W44: =#REF! -> #REF! | ... Y44: =#REF! -> #REF!
B45: Total assets | D45: =Bloomberg!C29/unit -> 0 | E45: =Bloomberg!D29/unit -> 0 | F45: =Bloomberg!E29/unit -> 0 | G45: =Bloomberg!F29/unit -> 0 | H45: =Bloomberg!G29/unit -> 63.703742 | I45: =Bloomberg!H29/unit -> 305.23959 | J45: =Bloomberg!I29/unit -> 547.54332 | K45: =Bloomberg!J29/unit -> 687.75862 | ... O45: =Bloomberg!N29/unit -> 2160.4528 | P45: =#REF! -> #REF! | Q45: =#REF! -> #REF! | R45: =#REF! -> #REF! | S45: =#REF! -> #REF! | T45: =#REF! -> #REF! | U45: =#REF! -> #REF! | V45: =#REF! -> #REF! | W45: =#REF! -> #REF! | ... Y45: =#REF! -> #REF!
P46: =#REF! -> #REF! | Q46: =#REF! -> #REF! | R46: =#REF! -> #REF! | S46: =#REF! -> #REF! | T46: =#REF! -> #REF! | U46: =#REF! -> #REF! | V46: =#REF! -> #REF! | W46: =#REF! -> #REF! | ... Y46: =#REF! -> #REF!
B47: Liabilities & stockholders' equity | P47: =#REF! -> #REF! | Q47: =#REF! -> #REF! | R47: =#REF! -> #REF! | S47: =#REF! -> #REF! | T47: =#REF! -> #REF! | U47: =#REF! -> #REF! | V47: =#REF! -> #REF! | W47: =#REF! -> #REF! | ... Y47: =#REF! -> #REF!
B48: + Accounts payable | D48: =Bloomberg!C30/unit -> 0 | E48: =Bloomberg!D30/unit -> 0 | F48: =Bloomberg!E30/unit -> 0 | G48: =Bloomberg!F30/unit -> 0 | H48: =Bloomberg!G30/unit -> 0 | I48: =Bloomberg!H30/unit -> 9.9969011 | J48: =Bloomberg!I30/unit -> 0.8834598 | K48: =Bloomberg!J30/unit -> 1.433143 | ... O48: =Bloomberg!N30/unit -> 55.022482 | P48: =#REF! -> #REF! | Q48: =#REF! -> #REF! | R48: =#REF! -> #REF! | S48: =#REF! -> #REF! | T48: =#REF! -> #REF! | U48: =#REF! -> #REF! | V48: =#REF! -> #REF! | W48: =#REF! -> #REF! | ... Y48: =#REF! -> #REF!
B49: + Short-term borrowings | D49: =Bloomberg!C31/unit -> 0 | E49: =Bloomberg!D31/unit -> 0 | F49: =Bloomberg!E31/unit -> 0 | G49: =Bloomberg!F31/unit -> 0 | H49: =Bloomberg!G31/unit -> 0 | I49: =Bloomberg!H31/unit -> 16 | J49: =Bloomberg!I31/unit -> 120.2056 | K49: =Bloomberg!J31/unit -> 179.7224 | ... O49: =Bloomberg!N31/unit -> 1 | P49: =#REF! -> #REF! | Q49: =#REF! -> #REF! | R49: =#REF! -> #REF! | S49: =#REF! -> #REF! | T49: =#REF! -> #REF! | U49: =#REF! -> #REF! | V49: =#REF! -> #REF! | W49: =#REF! -> #REF! | ... Y49: =#REF! -> #REF!
B50: + Other short-term liabilities | D50: =Bloomberg!C32/unit -> 0 | E50: =Bloomberg!D32/unit -> 0 | F50: =Bloomberg!E32/unit -> 0 | G50: =Bloomberg!F32/unit -> 0 | H50: =Bloomberg!G32/unit -> 37.192941 | I50: =Bloomberg!H32/unit -> 160.54634 | J50: =Bloomberg!I32/unit -> 265.79222 | K50: =Bloomberg!J32/unit -> 199.78062 | ... O50: =Bloomberg!N32/unit -> 909.34067 | P50: =#REF! -> #REF! | Q50: =#REF! -> #REF! | R50: =#REF! -> #REF! | S50: =#REF! -> #REF! | T50: =#REF! -> #REF! | U50: =#REF! -> #REF! | V50: =#REF! -> #REF! | W50: =#REF! -> #REF! | ... Y50: =#REF! -> #REF!
B51: Total current liabilities | D51: =Bloomberg!C33/unit -> 0 | E51: =Bloomberg!D33/unit -> 0 | F51: =Bloomberg!E33/unit -> 0 | G51: =Bloomberg!F33/unit -> 0 | H51: =Bloomberg!G33/unit -> 37.192941 | I51: =Bloomberg!H33/unit -> 186.54324 | J51: =Bloomberg!I33/unit -> 386.88128 | K51: =Bloomberg!J33/unit -> 380.93616 | ... O51: =Bloomberg!N33/unit -> 965.36315 | P51: =#REF! -> #REF! | Q51: =#REF! -> #REF! | R51: =#REF! -> #REF! | S51: =#REF! -> #REF! | T51: =#REF! -> #REF! | U51: =#REF! -> #REF! | V51: =#REF! -> #REF! | W51: =#REF! -> #REF! | ... Y51: =#REF! -> #REF!
B52: + Long-term debt | D52: =Bloomberg!C34/unit -> 0 | E52: =Bloomberg!D34/unit -> 0 | F52: =Bloomberg!E34/unit -> 0 | G52: =Bloomberg!F34/unit -> 0 | H52: =Bloomberg!G34/unit -> 0 | I52: =Bloomberg!H34/unit -> 0.06 | J52: =Bloomberg!I34/unit -> 7.2066 | K52: =Bloomberg!J34/unit -> 12.662196 | ... O52: =Bloomberg!N34/unit -> 119.10941 | P52: =#REF! -> #REF! | Q52: =#REF! -> #REF! | R52: =#REF! -> #REF! | S52: =#REF! -> #REF! | T52: =#REF! -> #REF! | U52: =#REF! -> #REF! | V52: =#REF! -> #REF! | W52: =#REF! -> #REF! | ... Y52: =#REF! -> #REF!
B53: + Other long-term liabilities | D53: =Bloomberg!C35/unit -> 0 | E53: =Bloomberg!D35/unit -> 0 | F53: =Bloomberg!E35/unit -> 0 | G53: =Bloomberg!F35/unit -> 0 | H53: =Bloomberg!G35/unit -> 0.24595 | I53: =Bloomberg!H35/unit -> 3 | J53: =Bloomberg!I35/unit -> 3.0806748 | K53: =Bloomberg!J35/unit -> 5.1687368 | ... O53: =Bloomberg!N35/unit -> 3.752779 | P53: =#REF! -> #REF! | Q53: =#REF! -> #REF! | R53: =#REF! -> #REF! | S53: =#REF! -> #REF! | T53: =#REF! -> #REF! | U53: =#REF! -> #REF! | V53: =#REF! -> #REF! | W53: =#REF! -> #REF! | ... Y53: =#REF! -> #REF!
B54: Total long-term liabilities | D54: =Bloomberg!C36/unit -> 0 | E54: =Bloomberg!D36/unit -> 0 | F54: =Bloomberg!E36/unit -> 0 | G54: =Bloomberg!F36/unit -> 0 | H54: =Bloomberg!G36/unit -> 0.24595 | I54: =Bloomberg!H36/unit -> 3.06 | J54: =Bloomberg!I36/unit -> 10.287275 | K54: =Bloomberg!J36/unit -> 17.830933 | ... O54: =Bloomberg!N36/unit -> 122.86219 | P54: =#REF! -> #REF! | Q54: =#REF! -> #REF! | R54: =#REF! -> #REF! | S54: =#REF! -> #REF! | T54: =#REF! -> #REF! | U54: =#REF! -> #REF! | V54: =#REF! -> #REF! | W54: =#REF! -> #REF! | ... Y54: =#REF! -> #REF!
B55: Total liabilities | D55: =Bloomberg!C37/unit -> 0 | E55: =Bloomberg!D37/unit -> 0 | F55: =Bloomberg!E37/unit -> 0 | G55: =Bloomberg!F37/unit -> 0 | H55: =Bloomberg!G37/unit -> 37.438891 | I55: =Bloomberg!H37/unit -> 189.60324 | J55: =Bloomberg!I37/unit -> 397.16855 | K55: =Bloomberg!J37/unit -> 398.76709 | ... O55: =Bloomberg!N37/unit -> 1088.2253 | P55: =#REF! -> #REF! | Q55: =#REF! -> #REF! | R55: =#REF! -> #REF! | S55: =#REF! -> #REF! | T55: =#REF! -> #REF! | U55: =#REF! -> #REF! | V55: =#REF! -> #REF! | W55: =#REF! -> #REF! | ... Y55: =#REF! -> #REF!
B56: + Total preferred equity | D56: =Bloomberg!C38/unit -> 0 | E56: =Bloomberg!D38/unit -> 0 | F56: =Bloomberg!E38/unit -> 0 | G56: =Bloomberg!F38/unit -> 0 | H56: =Bloomberg!G38/unit -> 0 | I56: =Bloomberg!H38/unit -> 0 | J56: =Bloomberg!I38/unit -> 0 | K56: =Bloomberg!J38/unit -> 0 | ... O56: =Bloomberg!N38/unit -> 0 | P56: =#REF! -> #REF! | Q56: =#REF! -> #REF! | R56: =#REF! -> #REF! | S56: =#REF! -> #REF! | T56: =#REF! -> #REF! | U56: =#REF! -> #REF! | V56: =#REF! -> #REF! | W56: =#REF! -> #REF! | ... Y56: =#REF! -> #REF!
B57: + Additional paid in capital | D57: =Bloomberg!C39/unit -> 0 | E57: =Bloomberg!D39/unit -> 0 | F57: =Bloomberg!E39/unit -> 0 | G57: =Bloomberg!F39/unit -> 0 | H57: =Bloomberg!G39/unit -> 0 | I57: =Bloomberg!H39/unit -> 3.42 | J57: =Bloomberg!I39/unit -> 3.42 | K57: =Bloomberg!J39/unit -> 5.28 | ... O57: =Bloomberg!N39/unit -> 10.867981 | P57: =#REF! -> #REF! | Q57: =#REF! -> #REF! | R57: =#REF! -> #REF! | S57: =#REF! -> #REF! | T57: =#REF! -> #REF! | U57: =#REF! -> #REF! | V57: =#REF! -> #REF! | W57: =#REF! -> #REF! | ... Y57: =#REF! -> #REF!
B58: + Share capital | D58: =Bloomberg!C40/unit -> 0 | E58: =Bloomberg!D40/unit -> 0 | F58: =Bloomberg!E40/unit -> 0 | G58: =Bloomberg!F40/unit -> 0 | H58: =Bloomberg!G40/unit -> 15 | I58: =Bloomberg!H40/unit -> 80 | J58: =Bloomberg!I40/unit -> 80 | K58: =Bloomberg!J40/unit -> 160 | ... O58: =Bloomberg!N40/unit -> 750 | P58: =#REF! -> #REF! | Q58: =#REF! -> #REF! | R58: =#REF! -> #REF! | S58: =#REF! -> #REF! | T58: =#REF! -> #REF! | U58: =#REF! -> #REF! | V58: =#REF! -> #REF! | W58: =#REF! -> #REF! | ... Y58: =#REF! -> #REF!
B59: + Retained earnings & other equity | D59: =Bloomberg!C41/unit -> 0 | E59: =Bloomberg!D41/unit -> 0 | F59: =Bloomberg!E41/unit -> 0 | G59: =Bloomberg!F41/unit -> 0 | H59: =Bloomberg!G41/unit -> 11.264853 | I59: =Bloomberg!H41/unit -> 7.2230935 | J59: =Bloomberg!I41/unit -> 39.786704 | K59: =Bloomberg!J41/unit -> 78.31797 | ... O59: =Bloomberg!N41/unit -> 241.89213 | P59: =#REF! -> #REF! | Q59: =#REF! -> #REF! | R59: =#REF! -> #REF! | S59: =#REF! -> #REF! | T59: =#REF! -> #REF! | U59: =#REF! -> #REF! | V59: =#REF! -> #REF! | W59: =#REF! -> #REF! | ... Y59: =#REF! -> #REF!
... B62: Total liabilities & equity | D62: =Bloomberg!C44/unit -> 0 | E62: =Bloomberg!D44/unit -> 0 | F62: =Bloomberg!E44/unit -> 0 | G62: =Bloomberg!F44/unit -> 0 | H62: =Bloomberg!G44/unit -> 63.703744 | I62: =Bloomberg!H44/unit -> 305.23959 | J62: =Bloomberg!I44/unit -> 547.54332 | K62: =Bloomberg!J44/unit -> 687.75862 | ... O62: =Bloomberg!N44/unit -> 2160.4528 | P62: =#REF! -> #REF! | Q62: =#REF! -> #REF! | R62: =#REF! -> #REF! | S62: =#REF! -> #REF! | T62: =#REF! -> #REF! | U62: =#REF! -> #REF! | V62: =#REF! -> #REF! | W62: =#REF! -> #REF! | ... Y62: =#REF! -> #REF!
B63: Check | D63: =D45-D62 -> 0 | E63: =E45-E62 -> 0 | F63: =F45-F62 -> 0 | G63: =G45-G62 -> 0 | H63: =H45-H62 -> -1.7e-06 | I63: =I45-I62 -> 0 | J63: =J45-J62 -> 0 | K63: =K45-K62 -> 0 | ... Y63: =Y45-Y62 -> #REF!
B65: CASH FLOW STATEMENT
B66: Beginning cash | D66: =C33 -> 0 | E66: =D33 -> 0 | F66: =E33 -> 0 | G66: =F33 -> 0 | H66: =G33 -> 0 | I66: =H33 -> 31.559074 | J66: =I33 -> 39.657925 | K66: =J33 -> 78.03322 | ... O66: =N33 -> 72.88629 | P66: =#REF! -> #REF! | Q66: =#REF! -> #REF! | R66: =#REF! -> #REF! | S66: =#REF! -> #REF! | T66: =#REF! -> #REF! | U66: =#REF! -> #REF! | V66: =#REF! -> #REF! | W66: =#REF! -> #REF! | ... Y66: =#REF! -> #REF!
B67: + Net Income | D67: =Bloomberg!C45/unit -> 0 | E67: =Bloomberg!D45/unit -> 0 | F67: =Bloomberg!E45/unit -> 0 | G67: =Bloomberg!F45/unit -> 0 | H67: =Bloomberg!G45/unit -> 11.164157 | I67: =Bloomberg!H45/unit -> 6.8326122 | J67: =Bloomberg!I45/unit -> 38.141262 | K67: =Bloomberg!J45/unit -> 72.079287 | ... O67: =Bloomberg!N45/unit -> 167.83449 | P67: =#REF! -> #REF! | Q67: =#REF! -> #REF! | R67: =#REF! -> #REF! | S67: =#REF! -> #REF! | T67: =#REF! -> #REF! | U67: =#REF! -> #REF! | V67: =#REF! -> #REF! | W67: =#REF! -> #REF! | ... Y67: =#REF! -> #REF!
B68: + Depreciation & Amortization | D68: =Bloomberg!C46/unit -> 0 | E68: =Bloomberg!D46/unit -> 0 | F68: =Bloomberg!E46/unit -> 0 | G68: =Bloomberg!F46/unit -> 0 | H68: =Bloomberg!G46/unit -> 0.1563425 | I68: =Bloomberg!H46/unit -> 0.437671 | J68: =Bloomberg!I46/unit -> 0.9887019 | K68: =Bloomberg!J46/unit -> 2.0698347 | ... O68: =Bloomberg!N46/unit -> 3.2894437 | P68: =#REF! -> #REF! | Q68: =#REF! -> #REF! | R68: =#REF! -> #REF! | S68: =#REF! -> #REF! | T68: =#REF! -> #REF! | U68: =#REF! -> #REF! | V68: =#REF! -> #REF! | W68: =#REF! -> #REF! | ... Y68: =#REF! -> #REF!
B69: + Other Non-Cash Adjustments | D69: =Bloomberg!C47/unit -> 0 | E69: =Bloomberg!D47/unit -> 0 | F69: =Bloomberg!E47/unit -> 0 | G69: =Bloomberg!F47/unit -> 0 | H69: =Bloomberg!G47/unit -> 2.2107297 | I69: =Bloomberg!H47/unit -> -10.123744 | J69: =Bloomberg!I47/unit -> -81.320281 | K69: =Bloomberg!J47/unit -> 51.006002 | ... O69: =Bloomberg!N47/unit -> -312.16898 | P69: =#REF! -> #REF! | Q69: =#REF! -> #REF! | R69: =#REF! -> #REF! | S69: =#REF! -> #REF! | T69: =#REF! -> #REF! | U69: =#REF! -> #REF! | V69: =#REF! -> #REF! | W69: =#REF! -> #REF! | ... Y69: =#REF! -> #REF!
B70: + Changes in Non-Cash Capital | D70: =Bloomberg!C48/unit -> 0 | E70: =Bloomberg!D48/unit -> 0 | F70: =Bloomberg!E48/unit -> 0 | G70: =Bloomberg!F48/unit -> 0 | H70: =Bloomberg!G48/unit -> 4.0546045 | I70: =Bloomberg!H48/unit -> -53.044005 | J70: =Bloomberg!I48/unit -> 9.7517795 | K70: =Bloomberg!J48/unit -> -125.75755 | ... O70: =Bloomberg!N48/unit -> 473.60412 | P70: =#REF! -> #REF! | Q70: =#REF! -> #REF! | R70: =#REF! -> #REF! | S70: =#REF! -> #REF! | T70: =#REF! -> #REF! | U70: =#REF! -> #REF! | V70: =#REF! -> #REF! | W70: =#REF! -> #REF! | ... Y70: =#REF! -> #REF!
B71: Cash From Operating Activities | D71: =Bloomberg!C49/unit -> 0 | E71: =Bloomberg!D49/unit -> 0 | F71: =Bloomberg!E49/unit -> 0 | G71: =Bloomberg!F49/unit -> 0 | H71: =Bloomberg!G49/unit -> 17.585834 | I71: =Bloomberg!H49/unit -> -55.897466 | J71: =Bloomberg!I49/unit -> -32.438538 | K71: =Bloomberg!J49/unit -> -0.6024232 | ... O71: =Bloomberg!N49/unit -> 332.55908 | P71: =#REF! -> #REF! | Q71: =#REF! -> #REF! | R71: =#REF! -> #REF! | S71: =#REF! -> #REF! | T71: =#REF! -> #REF! | U71: =#REF! -> #REF! | V71: =#REF! -> #REF! | W71: =#REF! -> #REF! | ... Y71: =#REF! -> #REF!
B72: + Disposal of Fixed Assets | D72: =Bloomberg!C50/unit -> 0 | E72: =Bloomberg!D50/unit -> 0 | F72: =Bloomberg!E50/unit -> 0 | G72: =Bloomberg!F50/unit -> 0 | H72: =Bloomberg!G50/unit -> 0 | I72: =Bloomberg!H50/unit -> 0 | J72: =Bloomberg!I50/unit -> 0 | K72: =Bloomberg!J50/unit -> 0 | ... O72: =Bloomberg!N50/unit -> 1.5 | P72: =#REF! -> #REF! | Q72: =#REF! -> #REF! | R72: =#REF! -> #REF! | S72: =#REF! -> #REF! | T72: =#REF! -> #REF! | U72: =#REF! -> #REF! | V72: =#REF! -> #REF! | W72: =#REF! -> #REF! | ... Y72: =#REF! -> #REF!
B73: + Capital Expenditures | D73: =Bloomberg!C51/unit -> 0 | E73: =Bloomberg!D51/unit -> 0 | F73: =Bloomberg!E51/unit -> 0 | G73: =Bloomberg!F51/unit -> 0 | H73: =Bloomberg!G51/unit -> -0.8435311 | I73: =Bloomberg!H51/unit -> -1.7838461 | J73: =Bloomberg!I51/unit -> -8.0822487 | K73: =Bloomberg!J51/unit -> -6.3242338 | ... O73: =Bloomberg!N51/unit -> -3.0833069 | P73: =#REF! -> #REF! | Q73: =#REF! -> #REF! | R73: =#REF! -> #REF! | S73: =#REF! -> #REF! | T73: =#REF! -> #REF! | U73: =#REF! -> #REF! | V73: =#REF! -> #REF! | W73: =#REF! -> #REF! | ... Y73: =#REF! -> #REF!
B74: + Increase in Investments | D74: =Bloomberg!C52/unit -> 0 | E74: =Bloomberg!D52/unit -> 0 | F74: =Bloomberg!E52/unit -> 0 | G74: =Bloomberg!F52/unit -> 0 | H74: =Bloomberg!G52/unit -> 0 | I74: =Bloomberg!H52/unit -> 0 | J74: =Bloomberg!I52/unit -> 0 | K74: =Bloomberg!J52/unit -> 0 | ... O74: =Bloomberg!N52/unit -> 0
B75: + Decrease in Investments | D75: =Bloomberg!C53/unit -> 0 | E75: =Bloomberg!D53/unit -> 0 | F75: =Bloomberg!E53/unit -> 0 | G75: =Bloomberg!F53/unit -> 0 | H75: =Bloomberg!G53/unit -> 0 | I75: =Bloomberg!H53/unit -> 0 | J75: =Bloomberg!I53/unit -> 0 | K75: =Bloomberg!J53/unit -> 0 | ... O75: =Bloomberg!N53/unit -> 0
B76: + Other Investing Activities | D76: =Bloomberg!C54/unit -> 0 | E76: =Bloomberg!D54/unit -> 0 | F76: =Bloomberg!E54/unit -> 0 | G76: =Bloomberg!F54/unit -> 0 | H76: =Bloomberg!G54/unit -> 0 | I76: =Bloomberg!H54/unit -> -58.51 | J76: =Bloomberg!I54/unit -> -25.7968 | K76: =Bloomberg!J54/unit -> -40.761251 | ... O76: =Bloomberg!N54/unit -> 102.19816 | P76: =#REF! -> #REF! | Q76: =#REF! -> #REF! | R76: =#REF! -> #REF! | S76: =#REF! -> #REF! | T76: =#REF! -> #REF! | U76: =#REF! -> #REF! | V76: =#REF! -> #REF! | W76: =#REF! -> #REF! | ... Y76: =#REF! -> #REF!
B77: Cash From Investing Activities | D77: =Bloomberg!C55/unit -> 0 | E77: =Bloomberg!D55/unit -> 0 | F77: =Bloomberg!E55/unit -> 0 | G77: =Bloomberg!F55/unit -> 0 | H77: =Bloomberg!G55/unit -> -0.8435311 | I77: =Bloomberg!H55/unit -> -60.293846 | J77: =Bloomberg!I55/unit -> -33.879049 | K77: =Bloomberg!J55/unit -> -47.085485 | ... O77: =Bloomberg!N55/unit -> 100.61485 | P77: =#REF! -> #REF! | Q77: =#REF! -> #REF! | R77: =#REF! -> #REF! | S77: =#REF! -> #REF! | T77: =#REF! -> #REF! | U77: =#REF! -> #REF! | V77: =#REF! -> #REF! | W77: =#REF! -> #REF! | ... Y77: =#REF! -> #REF!
B78: + Dividends Paid | D78: =Bloomberg!C56/unit -> 0 | E78: =Bloomberg!D56/unit -> 0 | F78: =Bloomberg!E56/unit -> 0 | G78: =Bloomberg!F56/unit -> 0 | H78: =Bloomberg!G56/unit -> 0 | I78: =Bloomberg!H56/unit -> -9.9438855 | J78: =Bloomberg!I56/unit -> -4.699319 | K78: =Bloomberg!J56/unit -> -28.005857 | ... O78: =Bloomberg!N56/unit -> -15.779832 | P78: =#REF! -> #REF! | Q78: =#REF! -> #REF! | R78: =#REF! -> #REF! | S78: =#REF! -> #REF! | T78: =#REF! -> #REF! | U78: =#REF! -> #REF! | V78: =#REF! -> #REF! | W78: =#REF! -> #REF! | ... Y78: =#REF! -> #REF!
B79: + Increase in Capital Stocks | D79: =Bloomberg!C57/unit -> 0 | E79: =Bloomberg!D57/unit -> 0 | F79: =Bloomberg!E57/unit -> 0 | G79: =Bloomberg!F57/unit -> 0 | H79: =Bloomberg!G57/unit -> 9.2 | I79: =Bloomberg!H57/unit -> 134.42 | J79: =Bloomberg!I57/unit -> 2.04 | K79: =Bloomberg!J57/unit -> 94.25261 | ... O79: =Bloomberg!N57/unit -> 235.66319
B80: + Decrease in Capital Stocks | D80: =Bloomberg!C58/unit -> 0 | E80: =Bloomberg!D58/unit -> 0 | F80: =Bloomberg!E58/unit -> 0 | G80: =Bloomberg!F58/unit -> 0 | H80: =Bloomberg!G58/unit -> 0 | I80: =Bloomberg!H58/unit -> -0.18595 | J80: =Bloomberg!I58/unit -> 0 | K80: =Bloomberg!J58/unit -> 0 | ... O80: =Bloomberg!N58/unit -> 0
B81: Cash available / (required before debt) | D81: =D66+D71+D77+SUM(D78:D80) -> 0 | E81: =E66+E71+E77+SUM(E78:E80) -> 0 | F81: =F66+F71+F77+SUM(F78:F80) -> 0 | G81: =G66+G71+G77+SUM(G78:G80) -> 0 | H81: =H66+H71+H77+SUM(H78:H80) -> 25.942303 | I81: =I66+I71+I77+SUM(I78:I80) -> 39.657926 | J81: =J66+J71+J77+SUM(J78:J80) -> -29.31898 | K81: =K66+K71+K77+SUM(K78:K80) -> 96.592065 | ... Y81: =Y66+Y71+Y77+SUM(Y78:Y80) -> #REF!
B82: + Change in short-term debt | D82: =D49-C49 -> 0 | E82: =E49-D49 -> 0 | F82: =F49-E49 -> 0 | G82: =G49-F49 -> 0 | H82: =H49-G49 -> 0 | I82: =I49-H49 -> 16 | J82: =J49-I49 -> 104.2056 | K82: =K49-J49 -> 59.5168 | ... O82: =O49-N49 -> 1 | P82: =#REF! -> #REF! | Q82: =#REF! -> #REF! | R82: =#REF! -> #REF! | S82: =#REF! -> #REF! | T82: =#REF! -> #REF! | U82: =#REF! -> #REF! | V82: =#REF! -> #REF! | W82: =#REF! -> #REF! | ... Y82: =#REF! -> #REF!
B83: + Change in long-term debt | D83: =D52-C52 -> 0 | E83: =E52-D52 -> 0 | F83: =F52-E52 -> 0 | G83: =G52-F52 -> 0 | H83: =H52-G52 -> 0 | I83: =I52-H52 -> 0.06 | J83: =J52-I52 -> 7.1466 | K83: =K52-J52 -> 5.455596 | ... O83: =O52-N52 -> 49.395413
B84: + Other Financing Activities | D84: =Bloomberg!C59/unit -> 0 | E84: =Bloomberg!D59/unit -> 0 | F84: =Bloomberg!E59/unit -> 0 | G84: =Bloomberg!F59/unit -> 0 | H84: =Bloomberg!G59/unit -> 0 | I84: =Bloomberg!H59/unit -> 0 | J84: =Bloomberg!I59/unit -> 0 | K84: =Bloomberg!J59/unit -> 0 | ... O84: =Bloomberg!N59/unit -> 0 | P84: =#REF! -> #REF! | Q84: =#REF! -> #REF! | R84: =#REF! -> #REF! | S84: =#REF! -> #REF! | T84: =#REF! -> #REF! | U84: =#REF! -> #REF! | V84: =#REF! -> #REF! | W84: =#REF! -> #REF! | ... Y84: =#REF! -> #REF!
B85: Cash from Financing Activities | D85: =Bloomberg!C60/unit -> 0 | E85: =Bloomberg!D60/unit -> 0 | F85: =Bloomberg!E60/unit -> 0 | G85: =Bloomberg!F60/unit -> 0 | H85: =Bloomberg!G60/unit -> 9.2665996 | I85: =Bloomberg!H60/unit -> 124.29016 | J85: =Bloomberg!I60/unit -> 104.69288 | K85: =Bloomberg!J60/unit -> 131.21915 | ... O85: =Bloomberg!N60/unit -> 270.27877 | P85: =#REF! -> #REF! | Q85: =#REF! -> #REF! | R85: =#REF! -> #REF! | S85: =#REF! -> #REF! | T85: =#REF! -> #REF! | U85: =#REF! -> #REF! | V85: =#REF! -> #REF! | W85: =#REF! -> #REF! | ... Y85: =#REF! -> #REF!
B86: Net Changes in Cash | D86: =Bloomberg!C61/unit -> 0 | E86: =Bloomberg!D61/unit -> 0 | F86: =Bloomberg!E61/unit -> 0 | G86: =Bloomberg!F61/unit -> 0 | H86: =Bloomberg!G61/unit -> 26.008902 | I86: =Bloomberg!H61/unit -> 8.0988521 | J86: =Bloomberg!I61/unit -> 38.375295 | K86: =Bloomberg!J61/unit -> 83.531241 | ... O86: =Bloomberg!N61/unit -> 703.4527 | P86: =#REF! -> #REF! | Q86: =#REF! -> #REF! | R86: =#REF! -> #REF! | S86: =#REF! -> #REF! | T86: =#REF! -> #REF! | U86: =#REF! -> #REF! | V86: =#REF! -> #REF! | W86: =#REF! -> #REF! | ... Y86: =#REF! -> #REF!
B87: Ending cash | D87: =D66+D86 -> 0 | E87: =E66+E86 -> 0 | F87: =F66+F86 -> 0 | G87: =G66+G86 -> 0 | H87: =H66+H86 -> 26.008902 | I87: =I66+I86 -> 39.657926 | J87: =J66+J86 -> 78.03322 | K87: =K66+K86 -> 161.56446 | ... O87: =O66+O86 -> 776.33899 | P87: =#REF! -> #REF! | Q87: =#REF! -> #REF! | R87: =#REF! -> #REF! | S87: =#REF! -> #REF! | T87: =#REF! -> #REF! | U87: =#REF! -> #REF! | V87: =#REF! -> #REF! | W87: =#REF! -> #REF! | ... Y87: =#REF! -> #REF!
B88: Check | D88: 0 | E88: 0 | F88: 0 | G88: 0 | H88: 0 | I88: 0 | J88: 0 | K88: 0 | L88: 0 | M88: 0 | N88: 0 | O88: 0 | P88: =P87-P33 -> #REF! | Q88: =Q87-Q33 -> #REF! | R88: =R87-R33 -> #REF! | S88: =S87-S33 -> #REF! | T88: =T87-T33 -> #REF! | U88: =U87-U33 -> #REF! | V88: =V87-V33 -> #REF! | W88: =W87-W33 -> #REF! | ... Y88: =Y87-Y33 -> #REF!
B90: Share price at yearend | D90: =Bloomberg!C62 -> 0 | E90: =Bloomberg!D62 -> 0 | F90: =Bloomberg!E62 -> 0 | G90: =Bloomberg!F62 -> 0 | H90: =Bloomberg!G62 -> 0 | I90: =Bloomberg!H62 -> 0 | J90: =Bloomberg!I62 -> 22016.95 | K90: =Bloomberg!J62 -> 15895.93 | ... O90: =Bloomberg!N62 -> 11894.65 | P90: =VCSC!F15 -> #REF! | Q90: =P90 -> #REF! | R90: =Q90 -> #REF! | S90: =R90 -> #REF! | T90: =S90 -> #REF! | U90: =T90 -> #REF! | V90: =U90 -> #REF! | W90: =V90 -> #REF! | X90: =W90 -> #REF! | Y90: =X90 -> #REF!
B91: Dividend per share paid | D91: =-D78/D29*10^3 -> #DIV/0! | E91: =-E78/E29*10^3 -> #DIV/0! | F91: =-F78/F29*10^3 -> #DIV/0! | G91: =-G78/G29*10^3 -> #DIV/0! | H91: =-H78/H29*10^3 -> 0 | I91: =-I78/I29*10^3 -> 2093.4496 | J91: =-J78/J29*10^3 -> 587.41488 | K91: =-K78/K29*10^3 -> 2333.8214 | ... Y91: =-Y78/Y29*10^3 -> #REF!
B92: Dividend yield | D92: =D91/D90 -> #DIV/0! | E92: =E91/E90 -> #DIV/0! | F92: =F91/F90 -> #DIV/0! | G92: =G91/G90 -> #DIV/0! | H92: =H91/H90 -> #DIV/0! | I92: =I91/I90 -> #DIV/0! | J92: =J91/J90 -> 0.02668012 | K92: =K91/K90 -> 0.1468188 | ... Y92: =Y91/Y90 -> #REF!
B94: FINANCIAL RATIO ANALYSIS
B95: Market cap year end | D95: =IFERROR(D29*D90/10^3,0) -> 0 | E95: =IFERROR(E29*E90/10^3,0) -> 0 | F95: =IFERROR(F29*F90/10^3,0) -> 0 | G95: =IFERROR(G29*G90/10^3,0) -> 0 | H95: =IFERROR(H29*H90/10^3,0) -> 0 | I95: =IFERROR(I29*I90/10^3,0) -> 0 | J95: =IFERROR(J29*J90/10^3,0) -> 176.1356 | K95: =IFERROR(K29*K90/10^3,0) -> 190.75116 | ... Y95: =IFERROR(Y29*Y90/10^3,0) -> 0
B96: Market cap @ current px | K96: =K30*$D$1/10^3 -> 190.8 | L96: =L30*$D$1/10^3 -> 381.6 | M96: =M30*$D$1/10^3 -> 667.8 | N96: =N30*$D$1/10^3 -> 839.51493 | O96: =O30*$D$1/10^3 -> 1192.5 | P96: =P30*$D$1/10^3 -> #REF! | Q96: =Q30*$D$2/10^3 -> #REF! | R96: =R30*$D$1/10^3 -> #REF! | S96: =S30*$D$1/10^3 -> #REF! | T96: =T30*$D$1/10^3 -> #REF! | U96: =U30*$D$1/10^3 -> #REF! | V96: =V30*$D$1/10^3 -> #REF! | W96: =W30*$D$1/10^3 -> #REF! | X96: =X30*$D$1/10^3 -> #REF! | Y96: =Y30*$D$1/10^3 -> #REF!
L97: =L96/L29 -> 12.72 | M97: =M96/M29 -> 14.438919 | N97: =N96/N29 -> 14.169076 | O97: =O96/O29 -> 14.929615
L98: =L97/L26*1000 -> 12.414047 | M98: =M97/M26*1000 -> 10.481077 | N98: =N97/N26*1000 -> 9.039229 | O98: =O97/O26*1000 -> 6.6715793
B99: Enterprise value EV (ST&LT debt + market cap + minority) | D99: =IFERROR((D49+D52+D60+D96-D33)/(D96/D96),0) -> 0 | E99: =IFERROR((E49+E52+E60+E96-E33)/(E96/E96),0) -> 0 | F99: =IFERROR((F49+F52+F60+F96-F33)/(F96/F96),0) -> 0 | G99: =IFERROR((G49+G52+G60+G96-G33)/(G96/G96),0) -> 0 | H99: =IFERROR((H49+H52+H60+H96-H33)/(H96/H96),0) -> 0 | I99: =IFERROR((I49+I52+I60+I96-I33)/(I96/I96),0) -> 0 | J99: =IFERROR((J49+J52+J60+J96-J33)/(J96/J96),0) -> 0 | K99: =IFERROR((K49+K52+K60+K96-K33)/(K96/K96),0) -> 267.01369 | ... Y99: =IFERROR((Y49+Y52+Y60+Y96-Y33)/(Y96/Y96),0) -> 0
B100: Total short- and long-term debt | D100: =D49+D52 -> 0 | E100: =E49+E52 -> 0 | F100: =F49+F52 -> 0 | G100: =G49+G52 -> 0 | H100: =H49+H52 -> 0 | I100: =I49+I52 -> 16.06 | J100: =J49+J52 -> 127.4122 | K100: =K49+K52 -> 192.3846 | ... Y100: =Y49+Y52 -> #REF!
B101: Total average short- and long-term debt | D101: =IF(C100<1,D100,AVERAGE(C100:D100)) -> 0 | E101: =IF(D100<1,E100,AVERAGE(D100:E100)) -> 0 | F101: =IF(E100<1,F100,AVERAGE(E100:F100)) -> 0 | G101: =IF(F100<1,G100,AVERAGE(F100:G100)) -> 0 | H101: =IF(G100<1,H100,AVERAGE(G100:H100)) -> 0 | I101: =IF(H100<1,I100,AVERAGE(H100:I100)) -> 16.06 | J101: =IF(I100<1,J100,AVERAGE(I100:J100)) -> 71.7361 | K101: =IF(J100<1,K100,AVERAGE(J100:K100)) -> 159.8984 | ... O101: =IF(N100<1,O100,AVERAGE(N100:O100)) -> 94.911707 | P101: =IF(N100<1,P100,AVERAGE(N100:P100)) -> #REF! | Q101: =IF(O100<1,Q100,AVERAGE(O100,O100)) -> 120.10941 | R101: =IF(Q100<1,R100,AVERAGE(Q100:R100)) -> #REF! | S101: =IF(R100<1,S100,AVERAGE(R100:S100)) -> #REF! | T101: =IF(S100<1,T100,AVERAGE(S100:T100)) -> #REF! | U101: =IF(T100<1,U100,AVERAGE(T100:U100)) -> #REF! | V101: =IF(U100<1,V100,AVERAGE(U100:V100)) -> #REF! | W101: =IF(V100<1,W100,AVERAGE(V100:W100)) -> #REF! | X101: =IF(W100<1,X100,AVERAGE(W100:X100)) -> #REF! | Y101: =IF(X100<1,Y100,AVERAGE(X100:Y100)) -> #REF!
B102: Total invested capital (ST& LT debt + equity) | D102: =D49+D52+D61 -> 0 | E102: =E49+E52+E61 -> 0 | F102: =F49+F52+F61 -> 0 | G102: =G49+G52+G61 -> 0 | H102: =H49+H52+H61 -> 26.264852 | I102: =I49+I52+I61 -> 131.69634 | J102: =J49+J52+J61 -> 277.78696 | K102: =K49+K52+K61 -> 481.37612 | ... Y102: =Y49+Y52+Y61 -> #REF!
B103: Total average invested capital | D103: =IF(C102<1,D102,AVERAGE(C102:D102)) -> 0 | E103: =IF(D102<1,E102,AVERAGE(D102:E102)) -> 0 | F103: =IF(E102<1,F102,AVERAGE(E102:F102)) -> 0 | G103: =IF(F102<1,G102,AVERAGE(F102:G102)) -> 0 | H103: =IF(G102<1,H102,AVERAGE(G102:H102)) -> 26.264852 | I103: =IF(H102<1,I102,AVERAGE(H102:I102)) -> 78.980597 | J103: =IF(I102<1,J102,AVERAGE(I102:J102)) -> 204.74165 | K103: =IF(J102<1,K102,AVERAGE(J102:K102)) -> 379.58154 | ... O103: =IF(N102<1,O102,AVERAGE(N102:O102)) -> 962.83285 | P103: =IF(N102<1,P102,AVERAGE(N102:P102)) -> #REF! | Q103: =IF(O102<1,Q102,AVERAGE(O102,Q102)) -> #REF! | R103: =IF(Q102<1,R102,AVERAGE(Q102:R102)) -> #REF! | S103: =IF(R102<1,S102,AVERAGE(R102:S102)) -> #REF! | T103: =IF(S102<1,T102,AVERAGE(S102:T102)) -> #REF! | U103: =IF(T102<1,U102,AVERAGE(T102:U102)) -> #REF! | V103: =IF(U102<1,V102,AVERAGE(U102:V102)) -> #REF! | W103: =IF(V102<1,W102,AVERAGE(V102:W102)) -> #REF! | X103: =IF(W102<1,X102,AVERAGE(W102:X102)) -> #REF! | Y103: =IF(X102<1,Y102,AVERAGE(X102:Y102)) -> #REF!
B104: Total average assets | D104: =IFERROR(IF(C45<1,D45,AVERAGE(C45:D45)),0) -> 0 | E104: =IFERROR(IF(D45<1,E45,AVERAGE(D45:E45)),0) -> 0 | F104: =IFERROR(IF(E45<1,F45,AVERAGE(E45:F45)),0) -> 0 | G104: =IFERROR(IF(F45<1,G45,AVERAGE(F45:G45)),0) -> 0 | H104: =IFERROR(IF(G45<1,H45,AVERAGE(G45:H45)),0) -> 63.703742 | I104: =IFERROR(IF(H45<1,I45,AVERAGE(H45:I45)),0) -> 184.47166 | J104: =IFERROR(IF(I45<1,J45,AVERAGE(I45:J45)),0) -> 426.39145 | K104: =IFERROR(IF(J45<1,K45,AVERAGE(J45:K45)),0) -> 617.65097 | ... O104: =IFERROR(IF(N45<1,O45,AVERAGE(N45:O45)),0) -> 1714.3339 | P104: =IFERROR(IF(N45<1,P45,AVERAGE(N45:P45)),0) -> 0 | Q104: =IFERROR(IF(P45<1,Q45,AVERAGE(P45:Q45)),0) -> 0 | R104: =IFERROR(IF(Q45<1,R45,AVERAGE(Q45:R45)),0) -> 0 | S104: =IFERROR(IF(R45<1,S45,AVERAGE(R45:S45)),0) -> 0 | T104: =IFERROR(IF(S45<1,T45,AVERAGE(S45:T45)),0) -> 0 | U104: =IFERROR(IF(T45<1,U45,AVERAGE(T45:U45)),0) -> 0 | V104: =IFERROR(IF(U45<1,V45,AVERAGE(U45:V45)),0) -> 0 | W104: =IFERROR(IF(V45<1,W45,AVERAGE(V45:W45)),0) -> 0 | X104: =IFERROR(IF(W45<1,X45,AVERAGE(W45:X45)),0) -> 0 | Y104: =IFERROR(IF(X45<1,Y45,AVERAGE(X45:Y45)),0) -> 0
B105: Total average equity | D105: =IFERROR(IF(C61<1,D61,AVERAGE(C61:D61)),0) -> 0 | E105: =IFERROR(IF(D61<1,E61,AVERAGE(D61:E61)),0) -> 0 | F105: =IFERROR(IF(E61<1,F61,AVERAGE(E61:F61)),0) -> 0 | G105: =IFERROR(IF(F61<1,G61,AVERAGE(F61:G61)),0) -> 0 | H105: =IFERROR(IF(G61<1,H61,AVERAGE(G61:H61)),0) -> 26.264852 | I105: =IFERROR(IF(H61<1,I61,AVERAGE(H61:I61)),0) -> 70.950597 | J105: =IFERROR(IF(I61<1,J61,AVERAGE(I61:J61)),0) -> 133.00555 | K105: =IFERROR(IF(J61<1,K61,AVERAGE(J61:K61)),0) -> 219.68314 | ... O105: =IFERROR(IF(N61<1,O61,AVERAGE(N61:O61)),0) -> 867.92114 | P105: =IFERROR(IF(N61<1,P61,AVERAGE(N61:P61)),0) -> 0 | Q105: =IFERROR(IF(P61<1,Q61,AVERAGE(P61:Q61)),0) -> 0 | R105: =IFERROR(IF(Q61<1,R61,AVERAGE(Q61:R61)),0) -> 0 | S105: =IFERROR(IF(R61<1,S61,AVERAGE(R61:S61)),0) -> 0 | T105: =IFERROR(IF(S61<1,T61,AVERAGE(S61:T61)),0) -> 0 | U105: =IFERROR(IF(T61<1,U61,AVERAGE(T61:U61)),0) -> 0 | V105: =IFERROR(IF(U61<1,V61,AVERAGE(U61:V61)),0) -> 0 | W105: =IFERROR(IF(V61<1,W61,AVERAGE(V61:W61)),0) -> 0 | X105: =IFERROR(IF(W61<1,X61,AVERAGE(W61:X61)),0) -> 0 | Y105: =IFERROR(IF(X61<1,Y61,AVERAGE(X61:Y61)),0) -> 0
...

Sheet VCSC
C7: DXG | F7: Settings
C8: =C7&" VN EQUITY" -> DXG VN EQUITY | F8: English
C9: Ho Chi Minh | E9: =IF(F9="VND million",1,1000) -> 1000 | F9: VND Billion
A10: =IF(C9="Ho Chi Minh","VNIndex", "HNIndex") -> VNIndex | C10: =YEAR(TODAY()) -> 2025 | E10: VND | F10: 21000
A11: =year+9 -> 2034 | C11: =TODAY() -> 45874
C13: =IF(F16>VCSC!C64,VCSC!D64,IF(F16>VCSC!C65,VCSC!D65,IF(F16>VCSC!C66,VCSC!D66,IF(F16>VCSC!C67,VCSC!D67,"Sell")))) -> HOLD | J13: =VCSC!F8 -> English
J14: =IF($J$13="English",Y14,Z14) -> Income statement | K14: ='FS Year'!M9 -> 2022 | L14: ='FS Year'!N9 -> 2023 | M14: ='FS Year'!P9 -> 2024 | N14: ='FS Year'!Q9 -> 2025 | O14: ='FS Year'!R9 -> 2026 | Q14: =IF($J$13="english",AA14,AB14) -> Balance sheet | R14: =K14 -> 2022 | S14: =L14 -> 2023 | T14: =M14 -> 2024 | U14: =N14 -> 2025 | V14: =O14 -> 2026 | Y14: Income statement | Z14: CĐKT | AA14: Balance sheet | AB14: CĐKT
C15: Target price | F15: =ROUNDDOWN('Valuation summary'!T25/1000,1)*1000 -> #REF! | J15: =IF($J$13="english",Y15,Z15) -> Revenue | K15: ='FS Year'!M10 -> 403.50298 | L15: ='FS Year'!N10 -> 342.59114 | M15: ='FS Year'!O10 -> 506.18066 | N15: ='FS Year'!Q10 -> 1.395 | O15: ='FS Year'!R10 -> 2.5065169 | Q15: =IF($J$13="english",AA15,AB15) -> Assets | Y15: Revenue | Z15: Doanh thu thuần | AA15: Assets | AB15: Tài sản
C16: Upside/Downside | F16: =IFERROR(F15/F21-1,0)*100 -> 0 | J16: =IF($J$13="english",Y16,Z16) -> - Cost of goods sold | K16: ='FS Year'!M11 -> -210.6182 | L16: ='FS Year'!N11 -> -136.66021 | M16: ='FS Year'!O11 -> -204.36545 | N16: ='FS Year'!Q11 -> -0.735 | O16: ='FS Year'!R11 -> -1.4548796 | Q16: =IF($J$13="english",AA16,AB16) -> + Cash & equivalent | R16: ='FS Year'!M33 -> 136.05265 | S16: ='FS Year'!N33 -> 72.88629 | T16: ='FS Year'!O33 -> 776.33899 | U16: ='FS Year'!Q33 -> #REF! | V16: ='FS Year'!R33 -> #REF! | Y16: - Cost of goods sold | Z16: - Giá vốn hàng bán | AA16: + Cash & equivalent | AB16: + Tiền và tương đương
J17: =IF($J$13="english",Y17,Z17) -> Gross profit | K17: ='FS Year'!M12 -> 192.88479 | L17: ='FS Year'!N12 -> 205.93093 | M17: ='FS Year'!O12 -> 301.81521 | N17: ='FS Year'!Q12 -> 0.66 | O17: ='FS Year'!R12 -> 1.0516373 | Q17: =IF($J$13="english",AA17,AB17) -> + Short-term investments | R17: ='FS Year'!M34 -> 0 | S17: ='FS Year'!N34 -> 0 | T17: ='FS Year'!O34 -> 0 | U17: ='FS Year'!Q34 -> #REF! | V17: ='FS Year'!R34 -> #REF! | Y17: Gross profit | Z17: Lợi nhuận gộp | AA17: + Short-term investments | AB17: + Đầu tư TC ngắn hạn
C18: Sector | J18: =IF($J$13="english",Y18,Z18) -> - Sales & marketing | K18: ='FS Year'!M13 -> -44.045725 | L18: ='FS Year'!N13 -> -62.49381 | M18: ='FS Year'!O13 -> -54.30247 | N18: ='FS Year'!Q13 -> -0.162 | O18: ='FS Year'!R13 -> -0.25330222 | Q18: =IF($J$13="english",AA18,AB18) -> + Accounts receivable | R18: ='FS Year'!M35 -> 125.80868 | S18: ='FS Year'!N35 -> 131.2453 | T18: ='FS Year'!O35 -> 119.20113 | U18: ='FS Year'!Q35 -> #REF! | V18: ='FS Year'!R35 -> #REF! | Y18: - Sales & marketing | Z18: - Chi phí bán hàng | AA18: + Accounts receivable | AB18: + Các khoản phải thu
J19: =IF($J$13="english",Y19,Z19) -> - General & admin | K19: ='FS Year'!M14 -> -78.67124 | L19: ='FS Year'!N14 -> -81.246045 | M19: ='FS Year'!O14 -> -82.327577 | N19: ='FS Year'!Q14 -> -0.108 | O19: ='FS Year'!R14 -> -0.15524975 | Q19: =IF($J$13="english",AA19,AB19) -> + Inventories | R19: ='FS Year'!M36 -> 129.20743 | S19: ='FS Year'!N36 -> 432.78726 | T19: ='FS Year'!O36 -> 499.21431 | U19: ='FS Year'!Q36 -> #REF! | V19: ='FS Year'!R36 -> #REF! | Y19: - General & admin | Z19: - Chi phí quản lí DN | AA19: + Inventories | AB19: + Hàng tồn kho
C20: Key indicators | J20: =IF($J$13="english",Y20,Z20) -> Operating profit | K20: ='FS Year'!M15 -> 70.167824 | L20: ='FS Year'!N15 -> 62.191073 | M20: ='FS Year'!O15 -> 165.18516 | N20: ='FS Year'!Q15 -> 0.39 | O20: ='FS Year'!R15 -> 0.6430853 | Q20: =IF($J$13="english",AA20,AB20) -> + Other current assets | R20: ='FS Year'!M37 -> 189.55619 | S20: ='FS Year'!N37 -> 297.11363 | T20: ='FS Year'!O37 -> 284.11639 | U20: ='FS Year'!Q37 -> #REF! | V20: ='FS Year'!R37 -> #REF! | Y20: Operating profit | Z20: Lợi nhuận thuần HĐKD | AA20: + Other current assets | AB20: + Tài sản ngắn hạn khác
C21: Current price | F21: =Price!C382 -> 15700 | J21: =IF($J$13="english",Y21,Z21) -> - Forex gains/(losses) | K21: ='FS Year'!M16 -> 0.042025 | L21: ='FS Year'!N16 -> 0 | M21: ='FS Year'!O16 -> 0 | N21: ='FS Year'!Q16 -> 0.093 | O21: ='FS Year'!R16 -> 0.10465975 | Q21: =IF($J$13="english",AA21,AB21) -> Total current assets | R21: ='FS Year'!M38 -> 580.62496 | S21: ='FS Year'!N38 -> 934.03248 | T21: ='FS Year'!O38 -> 1678.8708 | U21: ='FS Year'!Q38 -> #REF! | V21: ='FS Year'!R38 -> #REF! | Y21: - Forex gains/(losses) | Z21: - (Lỗ) / lại tỷ giá | AA21: Total current assets | AB21: Tổng tài sản ngắn hạn
J22: =IF($J$13="english",Y22,Z22) -> - Net non-op gains | K22: ='FS Year'!M17 -> 15.520407 | L22: ='FS Year'!N17 -> 58.6378 | M22: ='FS Year'!O17 -> 101.26315 | N22: ='FS Year'!Q17 -> 0.123 | O22: ='FS Year'!R17 -> 0.10619569 | Q22: =IF($J$13="english",AA22,AB22) -> + Gross fixed assets | R22: ='FS Year'!M39 -> 46.413282 | S22: ='FS Year'!N39 -> 44.852805 | T22: ='FS Year'!O39 -> 42.124221 | U22: ='FS Year'!Q39 -> #REF! | V22: ='FS Year'!R39 -> #REF! | Y22: - Net non-op gains | Z22: - Lợi nhuận khác | AA22: + Gross fixed assets | AB22: + Tài sản dài hạn
C23: 52-week low | F23: =MIN(Price!C17:C382) -> 7592.43 | J23: =IF($J$13="english",Y23,Z23) -> EBIT | K23: ='FS Year'!M18 -> 85.730256 | L23: ='FS Year'!N18 -> 120.82887 | M23: ='FS Year'!O18 -> 266.44832 | N23: ='FS Year'!Q18 -> 0.606 | O23: ='FS Year'!R18 -> 0.85394073 | Q23: =IF($J$13="english",AA23,AB23) -> - Accum. depreciation | R23: ='FS Year'!M40 -> -8.9248649 | S23: ='FS Year'!N40 -> -9.2843747 | T23: ='FS Year'!O40 -> -9.8412946 | U23: ='FS Year'!Q40 -> #REF! | V23: ='FS Year'!R40 -> #REF! | Y23: EBIT | Z23: Lợi nhuận khác | AA23: - Accum. depreciation | AB23: + Khấu hao lũy kế
C24: 52-week high | F24: =MAX(Price!C17:C382) -> 17500 | J24: =IF($J$13="english",Y24,Z24) -> - Interest expense | K24: ='FS Year'!M19 -> -6.6164557 | L24: ='FS Year'!N19 -> -0.342829 | M24: ='FS Year'!O19 -> -0.0792907 | N24: ='FS Year'!Q19 -> -0.009 | O24: ='FS Year'!R19 -> -0.032702591 | Q24: =IF($J$13="english",AA24,AB24) -> + Net fixed assets | R24: ='FS Year'!M41 -> 37.488417 | S24: ='FS Year'!N41 -> 35.56843 | T24: ='FS Year'!O41 -> 32.282926 | U24: ='FS Year'!Q41 -> #REF! | V24: ='FS Year'!R41 -> #REF! | Y24: - Interest expense | Z24: - Chi phí lãi vay | AA24: + Net fixed assets | AB24: + Tài sản dài hạn
C25: Avg 30-day trading vol | F25: =AVERAGE(Price!L17:L46) -> 530328.67 | J25: =IF($J$13="english",Y25,Z25) -> EBT | K25: ='FS Year'!M20 -> 79.1138 | L25: ='FS Year'!N20 -> 120.48604 | M25: ='FS Year'!O20 -> 266.36903 | N25: ='FS Year'!Q20 -> 0.597 | O25: ='FS Year'!R20 -> 0.82123814 | Q25: =IF($J$13="english",AA25,AB25) -> + Long-term investments | R25: ='FS Year'!M42 -> 110.14465 | S25: ='FS Year'!N42 -> 110.14465 | T25: ='FS Year'!O42 -> 0 | U25: ='FS Year'!Q42 -> #REF! | V25: ='FS Year'!R42 -> #REF! | Y25: EBT | Z25: Lợi nhuận trước thuế | AA25: + Long-term investments | AB25: + Đầu tư tài chính dài hạn
C26: Outstanding shares (mn) | E26: =_xll.BDH(ticker,"EQY_SH_OUT",C11-1,C11,"Dir=H","Dts=H","Sort=A","Quote=C","QtTyp=Y","Days=A","Per=cd","DtFmt=D","Fill=P","cols=2;rows=1") -> #NAME? | F26: 75 | J26: =IF($J$13="english",Y26,Z26) -> - Income tax expense | K26: ='FS Year'!M21 -> -20.018952 | L26: ='FS Year'!N21 -> -30.756144 | M26: ='FS Year'!O21 -> -53.321005 | N26: ='FS Year'!Q21 -> -0.095 | O26: ='FS Year'!R21 -> -0.15681483 | Q26: =IF($J$13="english",AA26,AB26) -> + Other long-term assets | R26: ='FS Year'!M43 -> 88.194154 | S26: ='FS Year'!N43 -> 188.4695 | T26: ='FS Year'!O43 -> 449.29909 | U26: ='FS Year'!Q43 -> #REF! | V26: ='FS Year'!R43 -> #REF! | Y26: - Income tax expense | Z26: - Thuế TNDN | AA26: + Other long-term assets | AB26: + Tài sản dài hạn khác
C27: Market cap (VND billion) | F27: =price*shares/unit -> 1177.5 | J27: =IF($J$13="english",Y27,Z27) -> Profit after tax | K27: ='FS Year'!M22 -> 59.094848 | L27: ='FS Year'!N22 -> 89.7299 | M27: ='FS Year'!O22 -> 213.04802 | N27: ='FS Year'!Q22 -> 0.446 | O27: ='FS Year'!R22 -> 0.63027029 | Q27: =IF($J$13="english",AA27,AB27) -> Total long-term assets | R27: ='FS Year'!M44 -> 235.82722 | S27: ='FS Year'!N44 -> 334.18258 | T27: ='FS Year'!O44 -> 481.58202 | U27: ='FS Year'!Q44 -> #REF! | V27: ='FS Year'!R44 -> #REF! | Y27: Profit after tax | Z27: LNST | AA27: Total long-term assets | AB27: Tổng tài sản dài hạn
C28: Market cap (USD million) | F28: =F27/F10*10^3 -> 56.071429 | J28: =IF($J$13="english",Y28,Z28) -> - Minority interests | K28: ='FS Year'!M23 -> -1.234897 | L28: ='FS Year'!N23 -> -6.9659064 | M28: ='FS Year'!O23 -> -45.213531 | N28: ='FS Year'!Q23 -> -0.109 | O28: ='FS Year'!R23 -> -0.12721978 | Q28: =IF($J$13="english",AA28,AB28) -> Total Assets | R28: ='FS Year'!M45 -> 816.45218 | S28: ='FS Year'!N45 -> 1268.2151 | T28: ='FS Year'!O45 -> 2160.4528 | U28: ='FS Year'!Q45 -> #REF! | V28: ='FS Year'!R45 -> #REF! | Y28: - Minority interests | Z28: - Lợi ích cổ đông thiểu số | AA28: Total Assets | AB28: Tổng Tài sản
C29: Foreign ownership % | E29: =_xll.BDH(ticker,"TOTAL_FOREIGN_PER_SHR_TOT",C11-1,C11,"Dir=H","Dts=H","Sort=A","Quote=C","QtTyp=Y","Days=A","Per=cd","DtFmt=D","Fill=P","cols=2;rows=1")/100 -> #NAME? | F29: 24.81 | J29: =IF($J$13="english",Y29,Z29) -> Net Income to common | K29: ='FS Year'!M24 -> 57.859951 | L29: ='FS Year'!N24 -> 82.763994 | M29: ='FS Year'!O24 -> 167.83449 | N29: ='FS Year'!Q24 -> 0.337 | O29: ='FS Year'!R24 -> 0.50305051 | Y29: Net Income to common | Z29: LNST của cổ đông CT Mẹ
J30: =IF($J$13="english",Y30,Z30) -> EPS | K30: ='FS Year'!M25 -> 1251.026 | L30: ='FS Year'!N25 -> 1396.8654 | M30: ='FS Year'!O25 -> 2101.2195 | N30: ='FS Year'!Q25 -> #REF! | O30: ='FS Year'!R25 -> #REF! | Q30: =IF($J$13="english",AA30,AB30) -> Liabilities & Equity | Y30: EPS | Z30: EPS (đ) | AA30: Liabilities & Equity | AB30: Nợ & Vốn chủ sở hữu
D31: =L14 -> 2023 | E31: =M14 -> 2024 | F31: =N14&"F" -> 2025F | J31: =IF($J$13="english",Y31,Z31) -> EBITDA | K31: ='FS Year'!M27 -> 88.689436 | L31: ='FS Year'!N27 -> 123.02123 | M31: ='FS Year'!O27 -> 268.74592 | N31: ='FS Year'!Q27 -> 0.3953 | O31: ='FS Year'!R27 -> 0.6469853 | Q31: =IF($J$13="english",AA31,AB31) -> + Accounts payable | R31: ='FS Year'!M48 -> 35.76286 | S31: ='FS Year'!N48 -> 21.303074 | T31: ='FS Year'!O48 -> 55.022482 | U31: ='FS Year'!Q48 -> #REF! | V31: ='FS Year'!R48 -> #REF! | Y31: EBITDA | Z31: EBITDA | AA31: + Accounts payable | AB31: + Phải trả ngắn hạn
C32: EPS (basic) | D32: ='FS Year'!N25 -> 1396.8654 | E32: ='FS Year'!O25 -> 2101.2195 | F32: ='FS Year'!Q25 -> #REF! | J32: =IF($J$13="english",Y32,Z32) -> Depreciation | K32: ='FS Year'!M28 -> -2.9591801 | L32: ='FS Year'!N28 -> -2.192354 | M32: ='FS Year'!O28 -> -2.2976035 | N32: ='FS Year'!Q28 -> -0.0053 | O32: ='FS Year'!R28 -> -0.0039 | Q32: =IF($J$13="english",AA32,AB32) -> + Short-term borrowings | R32: ='FS Year'!M49 -> 0.45 | S32: ='FS Year'!N49 -> 0 | T32: ='FS Year'!O49 -> 1 | U32: ='FS Year'!Q49 -> #REF! | V32: ='FS Year'!R49 -> #REF! | Y32: Depreciation | Z32: Khấu hao | AA32: + Short-term borrowings | AB32: + Vay và nợ ngắn hạn
C33: EPS growth % | D33: ='FS Year'!N188*100 -> 11.657582 | E33: ='FS Year'!P188*100 -> 0 | F33: ='FS Year'!Q188*100 -> 0 | J33: =IF($J$13="english",Y33,Z33) -> Revenue growth % | K33: ='FS Year'!M173 -> 0.40894671 | L33: ='FS Year'!N173 -> -0.1509576 | M33: ='FS Year'!O173 -> 0.47750656 | N33: ='FS Year'!Q173 -> -0.99724407 | O33: ='FS Year'!R173 -> 0.79678628 | Q33: =IF($J$13="english",AA33,AB33) -> + Other ST liabilities | R33: ='FS Year'!M50 -> 196.74578 | S33: ='FS Year'!N50 -> 509.92335 | T33: ='FS Year'!O50 -> 909.34067 | U33: ='FS Year'!Q50 -> #REF! | V33: ='FS Year'!R50 -> #REF! | Y33: Revenue growth % | Z33: Tăng trưởng doanh thu | AA33: + Other ST liabilities | AB33: + Phải trả ngắn hạn khác
C34: Dividend yield % | D34: ='FS Year'!N92*100 -> 0.28184399 | E34: ='FS Year'!O92*100 -> 1.6608902 | F34: ='FS Year'!Q92*100 -> #REF! | J34: =IF($J$13="english",Y34,Z34) -> Operating profit growth % | K34: ='FS Year'!M178 -> -0.090226628 | L34: ='FS Year'!N178 -> -0.11368104 | M34: ='FS Year'!O178 -> 1.6560912 | N34: ='FS Year'!Q178 -> -0.99763901 | O34: ='FS Year'!R178 -> 0.64893666 | Q34: =IF($J$13="english",AA34,AB34) -> Current liabilities | R34: ='FS Year'!M51 -> 232.95864 | S34: ='FS Year'!N51 -> 531.22642 | T34: ='FS Year'!O51 -> 965.36315 | U34: ='FS Year'!Q51 -> #REF! | V34: ='FS Year'!R51 -> #REF! | Y34: Operating profit growth % | Z34: Tăng trưởng LN HĐKD | AA34: Current liabilities | AB34: Nợ ngắn hạn
C35: P/E x (mkt. price) | D35: ='FS Year'!N138 -> 10.14348 | E35: ='FS Year'!P138 -> 0 | F35: ='FS Year'!Q138 -> 0 | J35: =IF($J$13="english",Y35,Z35) -> EBIT growth % | K35: ='FS Year'!M181 -> -0.087468678 | L35: ='FS Year'!N181 -> 0.40940759 | M35: ='FS Year'!O181 -> 1.2051709 | N35: ='FS Year'!Q181 -> -0.99772564 | O35: ='FS Year'!R181 -> 0.40914312 | Q35: =IF($J$13="english",AA35,AB35) -> + Long-term debt | R35: ='FS Year'!M52 -> 0.11576 | S35: ='FS Year'!N52 -> 69.714 | T35: ='FS Year'!O52 -> 119.10941 | U35: ='FS Year'!Q52 -> #REF! | V35: ='FS Year'!R52 -> #REF! | Y35: EBIT growth % | Z35: Tăng trưởng EBIT % | AA35: + Long-term debt | AB35: + Vay và nợ dài hạn
C36: P/B x (mkt. price) | D36: ='FS Year'!N139 -> 1.6574717 | E36: ='FS Year'!P139 -> 0 | F36: ='FS Year'!Q139 -> 0 | J36: =IF($J$13="english",Y36,Z36) -> EPS growth % | K36: ='FS Year'!M188 -> 0.526169 | L36: ='FS Year'!N188 -> 0.11657582 | M36: ='FS Year'!O188 -> 0.50423912 | N36: ='FS Year'!Q188 -> 0 | O36: ='FS Year'!R188 -> 0 | Q36: =IF($J$13="english",AA36,AB36) -> + Other LT liabilities | R36: ='FS Year'!M53 -> 3.7836345 | S36: ='FS Year'!N53 -> 3.6598596 | T36: ='FS Year'!O53 -> 3.752779 | U36: ='FS Year'!Q53 -> #REF! | V36: ='FS Year'!R53 -> #REF! | Y36: EPS growth % | Z36: Tăng trưởng EPS % | AA36: + Other LT liabilities | AB36: + Phải trả dài hạn
C37: EV / EBITDA x | D37: ='FS Year'!N140 -> 7.0461371 | E37: ='FS Year'!P140 -> 0 | F37: ='FS Year'!Q140 -> 0 | J37: =IF($J$13="english",Y37,Z37) -> Profitability ratios | K37: =K14 -> 2022 | L37: =L14 -> 2023 | M37: =M14 -> 2024 | N37: =N14 -> 2025 | O37: =O14 -> 2026 | Q37: =IF($J$13="english",AA37,AB37) -> Total LT liabilities | R37: ='FS Year'!M54 -> 3.8993945 | S37: ='FS Year'!N54 -> 73.37386 | T37: ='FS Year'!O54 -> 122.86219 | U37: ='FS Year'!Q54 -> #REF! | V37: ='FS Year'!R54 -> #REF! | Y37: Profitability ratios | Z37: Chỉ số khả năng sinh lợi | AA37: Total LT liabilities | AB37: Nợ dài hạn
C38: ROE % | D38: ='FS Year'!N112*100 -> 14.435208 | E38: ='FS Year'!P112*100 -> 0 | F38: ='FS Year'!Q112*100 -> 0 | J38: =IF($J$13="english",Y38,Z38) -> Gross margin | K38: ='FS Year'!M108 -> 0.47802568 | L38: ='FS Year'!N108 -> 0.60109823 | M38: ='FS Year'!O108 -> 0.59625986 | N38: ='FS Year'!Q108 -> 0.47311828 | O38: ='FS Year'!R108 -> 0.41956122 | Q38: =IF($J$13="english",AA38,AB38) -> Total Liabilities | R38: ='FS Year'!M55 -> 236.85803 | S38: ='FS Year'!N55 -> 604.60028 | T38: ='FS Year'!O55 -> 1088.2253 | U38: ='FS Year'!Q55 -> #REF! | V38: ='FS Year'!R55 -> #REF! | Y38: Gross margin | Z38: Tỷ suất lợi nhuận gộp | AA38: Total Liabilities | AB38: Tổng nợ
C39: ROA % | D39: ='FS Year'!N113*100 -> 8.6085585 | E39: ='FS Year'!P113*100 -> 0 | F39: ='FS Year'!Q113*100 -> 0 | J39: =IF($J$13="english",Y39,Z39) -> Profit after tax margin | K39: ='FS Year'!M111 -> 0.14645455 | L39: ='FS Year'!N111 -> 0.26191541 | M39: ='FS Year'!O111 -> 0.42089325 | N39: ='FS Year'!Q111 -> 0.31971326 | O39: ='FS Year'!R111 -> 0.25145264 | Q39: =IF($J$13="english",AA39,AB39) -> + Total preferred equity | R39: ='FS Year'!M56 -> 0 | S39: ='FS Year'!N56 -> 0 | T39: ='FS Year'!O56 -> 0 | U39: ='FS Year'!Q56 -> #REF! | V39: ='FS Year'!R56 -> #REF! | Y39: Profit after tax margin | Z39: Tỷ suất LNST | AA39: + Total preferred equity | AB39: + Cổ phiếu ưu đãi
C40: ROIC % | D40: ='FS Year'!N119*100 -> 13.662836 | E40: ='FS Year'!P119*100 -> 0 | F40: ='FS Year'!Q119*100 -> 0 | J40: =IF($J$13="english",Y40,Z40) -> ROE Dupont | K40: ='FS Year'!M112 -> 0.11399803 | L40: ='FS Year'!N112 -> 0.14435208 | M40: ='FS Year'!O112 -> 0.24546933 | N40: ='FS Year'!Q112 -> 0 | O40: ='FS Year'!R112 -> 0 | Q40: =IF($J$13="english",AA40,AB40) -> + Addt’l paid in capital | R40: ='FS Year'!M57 -> 31.980271 | S40: ='FS Year'!N57 -> 10.982381 | T40: ='FS Year'!O57 -> 10.867981 | U40: ='FS Year'!Q57 -> #REF! | V40: ='FS Year'!R57 -> #REF! | Y40: ROE Dupont | Z40: ROE DuPont | AA40: + Addt’l paid in capital | AB40: + Thặng dư
C41: Debt-to-equity % | D41: ='FS Year'!N133 -> 0.10505191 | E41: ='FS Year'!P133 -> 0 | F41: ='FS Year'!Q133 -> 0 | J41: =IF($J$13="english",Y41,Z41) -> ROA Dupont | K41: ='FS Year'!M113 -> 0.069413276 | L41: ='FS Year'!N113 -> 0.086085585 | M41: ='FS Year'!O113 -> 0.12427452 | N41: ='FS Year'!Q113 -> 0 | O41: ='FS Year'!R113 -> 0 | Q41: =IF($J$13="english",AA41,AB41) -> + Share capital | R41: ='FS Year'!M58 -> 420 | S41: ='FS Year'!N58 -> 527.99681 | T41: ='FS Year'!O58 -> 750 | U41: ='FS Year'!Q58 -> #REF! | V41: ='FS Year'!R58 -> #REF! | Y41: ROA Dupont | Z41: ROA DuPont | AA41: + Share capital | AB41: + Vốn điều lệ
J42: =IF($J$13="english",Y42,Z42) -> * EBIT Margin | K42: ='FS Year'!M114 -> 0.21246499 | L42: ='FS Year'!N114 -> 0.35269118 | M42: ='FS Year'!O114 -> 0.52638976 | N42: ='FS Year'!Q114 -> 0.4344086 | O42: ='FS Year'!R114 -> 0.34068821 | Q42: =IF($J$13="english",AA42,AB42) -> + Retained earnings | R42: ='FS Year'!M59 -> 103.75583 | S42: ='FS Year'!N59 -> 94.153804 | T42: ='FS Year'!O59 -> 241.89213 | U42: ='FS Year'!Q59 -> #REF! | V42: ='FS Year'!R59 -> #REF! | Y42: * EBIT Margin | Z42: Tỷ suất EBIT | AA42: + Retained earnings | AB42: + LN chưa phân phối
C43: Price performance % | D43: 3M | E43: 6M | F43: 12M | J43: =IF($J$13="english",Y43,Z43) -> * Tax burden | K43: ='FS Year'!M115 -> 0.74696005 | L43: ='FS Year'!N115 -> 0.74473273 | M43: ='FS Year'!O115 -> 0.7998228 | N43: ='FS Year'!Q115 -> 0.74706868 | O43: ='FS Year'!R115 -> 0.76746349 | Q43: =IF($J$13="english",AA43,AB43) -> + Minority interest | R43: ='FS Year'!M60 -> 23.858045 | S43: ='FS Year'!N60 -> 30.481793 | T43: ='FS Year'!O60 -> 69.467376 | U43: ='FS Year'!Q60 -> #REF! | V43: ='FS Year'!R60 -> #REF! | Y43: * Tax burden | Z43: LNTT / LNST | AA43: + Minority interest | AB43: + Lợi ích cổ đông thiểu số
C44: =C7 -> DXG | D44: =Price!G11*100 -> 5.3691275 | E44: =Price!H11*100 -> 21.705426 | F44: =Price!I11*100 -> 75.317526 | J44: =IF($J$13="english",Y44,Z44) -> * Interest burden | K44: ='FS Year'!M116 -> 0.9228224 | L44: ='FS Year'!N116 -> 0.99716269 | M44: ='FS Year'!O116 -> 0.99970242 | N44: ='FS Year'!Q116 -> 0.98514851 | O44: ='FS Year'!R116 -> 0.96170391 | Q44: =IF($J$13="english",AA44,AB44) -> Total equity | R44: ='FS Year'!M61 -> 579.59414 | S44: ='FS Year'!N61 -> 663.61479 | T44: ='FS Year'!O61 -> 1072.2275 | U44: ='FS Year'!Q61 -> #REF! | V44: ='FS Year'!R61 -> #REF! | Y44: * Interest burden | Z44: LNTT / EBIT | AA44: Total equity | AB44: Vốn chủ sở hữu
C45: Relative to Index | D45: =Price!G12*100 -> 1.8426968 | E45: =Price!H12*100 -> 9.6126945 | F45: =Price!I12*100 -> 56.077931 | J45: =IF($J$13="english",Y45,Z45) -> * Asset turnover | K45: ='FS Year'!M117 -> 0.4739578 | L45: ='FS Year'!N117 -> 0.32867705 | M45: ='FS Year'!O117 -> 0.29526374 | N45: ='FS Year'!Q117 -> 0 | O45: ='FS Year'!R117 -> 0 | Q45: =IF($J$13="english",AA45,AB45) -> Liabilities & equity | R45: ='FS Year'!M62 -> 816.45218 | S45: ='FS Year'!N62 -> 1268.2151 | T45: ='FS Year'!O62 -> 2160.4528 | U45: ='FS Year'!Q62 -> #REF! | V45: ='FS Year'!R62 -> #REF! | Y45: * Asset turnover | Z45: Vòng quay tổng tài sản | AA45: Liabilities & equity | AB45: Tổng cộng nguồn vốn
J46: =IF($J$13="english",Y46,Z46) -> Leverage ratio | K46: ='FS Year'!M118 -> 1.6423088 | L46: ='FS Year'!N118 -> 1.6768438 | M46: ='FS Year'!O118 -> 1.9752186 | N46: ='FS Year'!Q118 -> 0 | O46: ='FS Year'!R118 -> 0 | Y46: Leverage ratio | Z46: Đòn bẩy tài chính
J47: =IF($J$13="english",Y47,Z47) -> ROIC | K47: ='FS Year'!M119 -> 0.10203719 | L47: ='FS Year'!N119 -> 0.13662836 | M47: ='FS Year'!P119 -> 0 | N47: ='FS Year'!Q119 -> 0 | O47: ='FS Year'!R119 -> 0 | Y47: ROIC | Z47: ROIC
J48: =IF($J$13="english",Y48,Z48) -> Efficiency ratios | K48: =K37 -> 2022 | L48: =L37 -> 2023 | M48: =M37 -> 2024 | N48: =N37 -> 2025 | O48: =O37 -> 2026 | Q48: =IF($J$13="english",AA48,AB48) -> Cash flow | R48: =R14 -> 2022 | S48: =S14 -> 2023 | T48: =T14 -> 2024 | U48: =U14 -> 2025 | V48: =V14 -> 2026 | Y48: Efficiency ratios | Z48: Chỉ số hiệu quả vận hành | AA48: Cash flow | AB48: Lưu chuyển tiền tệ
J49: =IF($J$13="english",Y49,Z49) -> Days inventory on hand | K49: ='FS Year'!M121 -> 184.82913 | L49: ='FS Year'!N121 -> 750.50396 | M49: ='FS Year'!O121 -> 832.28495 | N49: ='FS Year'!Q121 -> 0 | O49: ='FS Year'!R121 -> 0 | Q49: =IF($J$13="english",AA49,AB49) -> Beginning cash | R49: ='FS Year'!M66 -> 107.3618 | S49: ='FS Year'!N66 -> 136.05265 | T49: ='FS Year'!O66 -> 72.88629 | U49: ='FS Year'!Q66 -> #REF! | V49: ='FS Year'!R66 -> #REF! | Y49: Days inventory on hand | Z49: Số ngày phải thu | AA49: Beginning cash | AB49: Tiền đầu năm
J50: =IF($J$13="english",Y50,Z50) -> Days AR outstanding | K50: ='FS Year'!M122 -> 119.22943 | L50: ='FS Year'!N122 -> 136.93393 | M50: ='FS Year'!O122 -> 90.29676 | N50: ='FS Year'!Q122 -> 0 | O50: ='FS Year'!R122 -> 0 | Q50: =IF($J$13="english",AA50,AB50) -> Net Income | R50: ='FS Year'!M67 -> 57.859951 | S50: ='FS Year'!N67 -> 82.763994 | T50: ='FS Year'!O67 -> 167.83449 | U50: ='FS Year'!Q67 -> #REF! | V50: ='FS Year'!R67 -> #REF! | Y50: Days AR outstanding | Z50: Số ngày tồn kho | AA50: Net Income | AB50: Lợi nhuận sau thuế
J51: =IF($J$13="english",Y51,Z51) -> Days AP outstanding | K51: ='FS Year'!M123 -> 34.706816 | L51: ='FS Year'!N123 -> 76.207499 | M51: ='FS Year'!O123 -> 68.159339 | N51: ='FS Year'!Q123 -> 0 | O51: ='FS Year'!R123 -> 0 | Q51: =IF($J$13="english",AA51,AB51) -> + Depreciation | R51: ='FS Year'!M68 -> 3.8956335 | S51: ='FS Year'!N68 -> 3.539521 | T51: ='FS Year'!O68 -> 3.2894437 | U51: ='FS Year'!Q68 -> #REF! | V51: ='FS Year'!R68 -> #REF! | Y51: Days AP outstanding | Z51: Số ngày phải trả | AA51: + Depreciation | AB51: + Khấu hao lũy kế
J52: =IF($J$13="english",Y52,Z52) -> Cash conversion cycle | K52: ='FS Year'!M124 -> 269.35174 | L52: ='FS Year'!N124 -> 811.23039 | M52: ='FS Year'!O124 -> 854.42237 | N52: ='FS Year'!Q124 -> 0 | O52: ='FS Year'!R124 -> 0 | Q52: =IF($J$13="english",AA52,AB52) -> + Other non-cash adjust. | R52: ='FS Year'!M69 -> -38.137384 | S52: ='FS Year'!N69 -> -41.166668 | T52: ='FS Year'!O69 -> -312.16898 | U52: ='FS Year'!Q69 -> #REF! | V52: ='FS Year'!R69 -> #REF! | Y52: Cash conversion cycle | Z52: Thời gian luân chuyển tiền | AA52: + Other non-cash adjust. | AB52: + Điều chỉnh
J53: =IF($J$13="english",Y53,Z53) -> Inventory turnover | K53: ='FS Year'!M125 -> 1.974797 | L53: ='FS Year'!N125 -> 0.48633987 | M53: ='FS Year'!O125 -> 0.43855172 | N53: ='FS Year'!Q125 -> 0 | O53: ='FS Year'!R125 -> 0 | Q53: =IF($J$13="english",AA53,AB53) -> + Changes in non-cash | R53: ='FS Year'!M70 -> 91.698899 | S53: ='FS Year'!N70 -> -126.03356 | T53: ='FS Year'!O70 -> 473.60412 | U53: ='FS Year'!Q70 -> #REF! | V53: ='FS Year'!R70 -> #REF! | Y53: Inventory turnover | Z53: COGS / Hàng tồn kho | AA53: + Changes in non-cash | AB53: + Thay đổi vốn lưu động
J54: =IF($J$13="english",Y54,Z54) -> Liquidity/Solvency | K54: =K14 -> 2022 | L54: =L14 -> 2023 | M54: =M14 -> 2024 | N54: =N14 -> 2025 | O54: =O14 -> 2026 | Q54: =IF($J$13="english",AA54,AB54) -> Cash from Operations | R54: ='FS Year'!M71 -> 115.3171 | S54: ='FS Year'!N71 -> -80.896718 | T54: ='FS Year'!O71 -> 332.55908 | U54: ='FS Year'!Q71 -> #REF! | V54: ='FS Year'!R71 -> #REF! | Y54: Liquidity/Solvency | Z54: Chỉ số TK/đòn bẩy TC | AA54: Cash from Operations | AB54: Tiền từ hoạt động KD
J55: =IF($J$13="english",Y55,Z55) -> Current ratio | K55: ='FS Year'!M127 -> 2.4923951 | L55: ='FS Year'!N127 -> 1.7582568 | M55: ='FS Year'!O127 -> 1.739108 | N55: ='FS Year'!Q127 -> 0 | O55: ='FS Year'!R127 -> 0 | Q55: =IF($J$13="english",AA55,AB55) -> + Disposal fixed assets | R55: ='FS Year'!M72 -> 0.0175455 | S55: ='FS Year'!N72 -> 0.6689728 | T55: ='FS Year'!O72 -> 1.5 | U55: ='FS Year'!Q72 -> #REF! | V55: ='FS Year'!R72 -> #REF! | Y55: Current ratio | Z55: CS thanh toán hiện hành | AA55: + Disposal fixed assets | AB55: + Thanh lý tài sản cố dinh‎
J56: =IF($J$13="english",Y56,Z56) -> Quick ratio | K56: ='FS Year'!M128 -> 1.9377583 | L56: ='FS Year'!N128 -> 0.94356229 | M56: ='FS Year'!O128 -> 1.2219821 | N56: ='FS Year'!Q128 -> 0 | O56: ='FS Year'!R128 -> 0 | Q56: =IF($J$13="english",AA56,AB56) -> + Capex | R56: ='FS Year'!M73 -> -2.7833428 | S56: ='FS Year'!N73 -> -2.4838598 | T56: ='FS Year'!O73 -> -3.0833069 | U56: ='FS Year'!Q73 -> #REF! | V56: ='FS Year'!R73 -> #REF! | Y56: Quick ratio | Z56: CS thanh toán nhanh | AA56: + Capex | AB56: + Chi mua sắm TSCĐ
J57: =IF($J$13="english",Y57,Z57) -> Cash ratio | K57: ='FS Year'!M129 -> 0.58402065 | L57: ='FS Year'!N129 -> 0.13720381 | M57: ='FS Year'!O129 -> 0.80419372 | N57: ='FS Year'!Q129 -> 0 | O57: ='FS Year'!R129 -> 0 | Q57: =IF($J$13="english",AA57,AB57) -> + Change in investments | R57: ='FS Year'!M74 -> 0 | S57: ='FS Year'!N74 -> 0 | T57: ='FS Year'!O74 -> 0 | U57: ='FS Year'!Q74 -> 0 | V57: ='FS Year'!R74 -> 0 | Y57: Cash ratio | Z57: CS thanh toán tiền mặt | AA57: + Change in investments | AB57: + Tăng (giảm) đầu tư
J58: =IF($J$13="english",Y58,Z58) -> Debt-to-assets (*) | K58: ='FS Year'!M131 -> 0.00069294934 | L58: ='FS Year'!N131 -> 0.054970172 | M58: ='FS Year'!O131 -> 0.055594555 | N58: ='FS Year'!Q131 -> 0 | O58: ='FS Year'!R131 -> 0 | Q58: =IF($J$13="english",AA58,AB58) -> + Other investments | R58: ='FS Year'!M76 -> -43.103909 | S58: ='FS Year'!N76 -> -165.64607 | T58: ='FS Year'!O76 -> 102.19816 | U58: ='FS Year'!Q76 -> #REF! | V58: ='FS Year'!R76 -> #REF! | Y58: Debt-to-assets (*) | Z58: Nợ / Tài sản | AA58: + Other investments | AB58: + Các hoạt động đầu tư khác
J59: =IF($J$13="english",Y59,Z59) -> Debt-to-capital (*) | K59: ='FS Year'!M132 -> 0.00097517942 | L59: ='FS Year'!N132 -> 0.095065135 | M59: ='FS Year'!O132 -> 0.10073446 | N59: ='FS Year'!Q132 -> 0 | O59: ='FS Year'!R132 -> 0 | Q59: =IF($J$13="english",AA59,AB59) -> Cash from Investing | R59: ='FS Year'!M77 -> -45.869706 | S59: ='FS Year'!N77 -> -167.46096 | T59: ='FS Year'!O77 -> 100.61485 | U59: ='FS Year'!Q77 -> #REF! | V59: ='FS Year'!R77 -> #REF! | Y59: Debt-to-capital (*) | Z59: Nợ / Vốn sử dụng | AA59: Cash from Investing | AB59: Tiền từ hoạt động đầu tư
J60: =IF($J$13="english",Y60,Z60) -> Debt-to-equity (*) | K60: ='FS Year'!M133 -> 0.00097613132 | L60: ='FS Year'!N133 -> 0.10505191 | M60: ='FS Year'!O133 -> 0.11201859 | N60: ='FS Year'!Q133 -> 0 | O60: ='FS Year'!R133 -> 0 | Q60: =IF($J$13="english",AA60,AB60) -> + Dividends paid | R60: ='FS Year'!M78 -> -5.2611494 | S60: ='FS Year'!N78 -> -2.0874 | T60: ='FS Year'!O78 -> -15.779832 | U60: ='FS Year'!Q78 -> #REF! | V60: ='FS Year'!R78 -> #REF! | Y60: Debt-to-equity (*) | Z60: Nợ / Vốn CSH | AA60: + Dividends paid | AB60: + Cổ tức đã trả
J61: =IF($J$13="english",Y61,Z61) -> Short-term debt to equity | K61: ='FS Year'!M134 -> 0.00055116517 | L61: ='FS Year'!N134 -> 0 | M61: ='FS Year'!O134 -> 0.00046286593 | N61: ='FS Year'!Q134 -> 0 | O61: ='FS Year'!R134 -> 0 | Q61: =IF($J$13="english",AA61,AB61) -> + Change in capital | R61: ='FS Year'!M79 -> 101.392 | S61: ='FS Year'!N79 -> 113.54205 | T61: ='FS Year'!O79 -> 235.66319 | U61: ='FS Year'!Q79 -> 0 | V61: ='FS Year'!R79 -> 0 | Y61: Short-term debt to equity | Z61: Nợ ngắn hạn / Vốn CSH | AA61: + Change in capital | AB61: + Tăng (giảm) vốn
J62: =IF($J$13="english",Y62,Z62) -> Long-term debt to equity | K62: ='FS Year'!M135 -> 0.00014178418 | L62: ='FS Year'!N135 -> 0.054970172 | M62: ='FS Year'!O135 -> 0.055131689 | N62: ='FS Year'!Q135 -> 0 | O62: ='FS Year'!R135 -> 0 | Q62: =IF($J$13="english",AA62,AB62) -> + Change in ST debt | R62: ='FS Year'!M82 -> -108.4 | S62: ='FS Year'!N82 -> -0.45 | T62: ='FS Year'!O82 -> 1 | U62: ='FS Year'!Q82 -> #REF! | V62: ='FS Year'!R82 -> #REF! | Y62: Long-term debt to equity | Z62: Nợ dài hạn / Vốn CSH | AA62: + Change in ST debt | AB62: + Thay đổi nợ ngắn hạn
C63: RATIING SCALE | J63: =IF($J$13="english",Y63,Z63) -> Interest coverage ratio | K63: ='FS Year'!M136 -> 12.957127 | L63: ='FS Year'!N136 -> 352.44648 | M63: =First_page!C73 -> 2083.3038 | N63: =First_page!D73 -> 43.333333 | O63: ='FS Year'!R136 -> 26.112327 | Q63: =IF($J$13="english",AA63,AB63) -> + Change in LT debt | R63: ='FS Year'!M83 -> -11.999056 | S63: ='FS Year'!N83 -> 69.59824 | T63: ='FS Year'!O83 -> 49.395413 | U63: ='FS Year'!Q83 -> 0 | V63: ='FS Year'!R83 -> 0 | Y63: Interest coverage ratio | Z63: Khả năng TT lãi vay | AA63: + Change in LT debt | AB63: + Thay đổi nợ dài hạn
C64: 0.2 | D64: BUY | J64: =IF($J$13="english",Y64,Z64) -> Valuation ratios | K64: =K48 -> 2022 | L64: =L48 -> 2023 | M64: =M48 -> 2024 | N64: =N48 -> 2025 | O64: =O48 -> 2026 | Q64: =IF($J$13="english",AA64,AB64) -> + Other financing act. | R64: ='FS Year'!M84 -> 0 | S64: ='FS Year'!N84 -> 0 | T64: ='FS Year'!O84 -> 0 | U64: ='FS Year'!Q84 -> #REF! | V64: ='FS Year'!R84 -> #REF! | Y64: Valuation ratios | Z64: Định giá | AA64: + Other financing act. | AB64: + Các hoạt động TC khác
C65: 0.1 | D65: ADD | J65: =IF($J$13="english",Y65,Z65) -> Price-to-earnings (P/E) | K65: =price/K30 -> 12.549699 | L65: =price/L30 -> 11.239451 | M65: =price/M30 -> 7.4718514 | N65: =price/N30 -> #REF! | O65: =price/O30 -> #REF! | Q65: =IF($J$13="english",AA65,AB65) -> Cash from Financing | R65: ='FS Year'!M85 -> -40.756539 | S65: ='FS Year'!N85 -> 185.19131 | T65: ='FS Year'!O85 -> 270.27877 | U65: ='FS Year'!Q85 -> #REF! | V65: ='FS Year'!R85 -> #REF! | Y65: Price-to-earnings (P/E) | Z65: P/E | AA65: Cash from Financing | AB65: Tiền từ hoạt động TC
C66: -0.1 | D66: HOLD | J66: =IF($J$13="english",Y66,Z66) -> Price-to-book value (P/B) | K66: =price/K68 -> 1.483168 | L66: =price/L68 -> 1.636623 | M66: =price/M68 -> 1.1742589 | N66: =price/N68 -> #DIV/0! | O66: =price/O68 -> #DIV/0! | Q66: =IF($J$13="english",AA66,AB66) -> Net changes in cash | R66: ='FS Year'!M86 -> 28.690855 | S66: ='FS Year'!N86 -> -63.166364 | T66: ='FS Year'!O86 -> 703.4527 | U66: ='FS Year'!Q86 -> #REF! | V66: ='FS Year'!R86 -> #REF! | Y66: Price-to-book value (P/B) | Z66: P/B | AA66: Net changes in cash | AB66: Tổng lưu chuyển tiền tệ
C67: -0.2 | D67: REDUCE | J67: =IF($J$13="english",Y67,Z67) -> EV / EBITDA | K67: ='FS Year'!M140 -> 6.2709966 | L67: ='FS Year'!N140 -> 7.0461371 | M67: ='FS Year'!O140 -> 2.2539423 | N67: ='FS Year'!Q140 -> 0 | O67: ='FS Year'!R140 -> 0 | Q67: =IF($J$13="english",AA67,AB67) -> Ending cash | R67: ='FS Year'!M87 -> 136.05265 | S67: ='FS Year'!N87 -> 72.88629 | T67: ='FS Year'!O87 -> 776.33899 | U67: ='FS Year'!Q87 -> #REF! | V67: ='FS Year'!R87 -> #REF! | Y67: EV / EBITDA | Z67: EV / EBITDA | AA67: Ending cash | AB67: Tiền cuối năm
J68: =IF($J$13="english",Y68,Z68) -> Book value per share | K68: ='FS Year'!M142 -> 10585.45 | L68: ='FS Year'!N142 -> 9592.9242 | M68: ='FS Year'!O142 -> 13370.135 | N68: ='FS Year'!Q142 -> 0 | O68: ='FS Year'!R142 -> 0 | Q68: =IF($J$13="english",AA68,AB68) -> Units in VND bn | Y68: Book value per share | AA68: Units in VND bn

Sheet FS QTR
B7: =ticker -> DXG VN EQUITY
B8: 1000
B9: INCOME STATEMENT | D9: =Bloomberg!C67 -> 40998 | E9: =Bloomberg!D67 -> 41089 | F9: =Bloomberg!E67 -> 41180 | G9: =Bloomberg!F67 -> 41274 | H9: =Bloomberg!G67 -> 41362 | I9: =Bloomberg!H67 -> 41453 | J9: =Bloomberg!I67 -> 41547 | K9: =Bloomberg!J67 -> 41639 | ... P9: =Bloomberg!O67 -> 42094 | Q9: 42185
B10: Revenue | D10: =Bloomberg!C68/unit -> 34.72555 | E10: =Bloomberg!D68/unit -> 94.877759 | F10: =Bloomberg!E68/unit -> 152.94242 | G10: =Bloomberg!F68/unit -> 120.95726 | H10: =Bloomberg!G68/unit -> 48.773071 | I10: =Bloomberg!H68/unit -> 139.05514 | J10: =Bloomberg!I68/unit -> 31.324253 | K10: =Bloomberg!J68/unit -> 123.43867 | ... P10: =Bloomberg!O68/unit -> 171.59967 | Q10: 212.3
B11: - Cost of goods sold | D11: =-Bloomberg!C69/unit -> -3.8214099 | E11: =-Bloomberg!D69/unit -> -46.378936 | F11: =-Bloomberg!E69/unit -> -89.321595 | G11: =-Bloomberg!F69/unit -> -71.096255 | H11: =-Bloomberg!G69/unit -> -19.581237 | I11: =-Bloomberg!H69/unit -> -65.363035 | J11: =-Bloomberg!I69/unit -> -5.5994087 | K11: =-Bloomberg!J69/unit -> -46.116532 | ... P11: =-Bloomberg!O69/unit -> -71.341777 | Q11: -70.6
B12: Gross profit | D12: =SUM(D10:D11) -> 30.904141 | E12: =SUM(E10:E11) -> 48.498823 | F12: =SUM(F10:F11) -> 63.620821 | G12: =SUM(G10:G11) -> 49.861004 | H12: =SUM(H10:H11) -> 29.191834 | I12: =SUM(I10:I11) -> 73.692108 | J12: =SUM(J10:J11) -> 25.724845 | K12: =SUM(K10:K11) -> 77.322141 | ... Q12: =SUM(Q10:Q11) -> 141.7
B13: - Sales and marketing exp | D13: =-Bloomberg!C70/unit -> -6.7188995 | E13: =-Bloomberg!D70/unit -> -13.199601 | F13: =-Bloomberg!E70/unit -> -11.821989 | G13: =-Bloomberg!F70/unit -> -12.305236 | H13: =-Bloomberg!G70/unit -> -11.643514 | I13: =-Bloomberg!H70/unit -> -26.212991 | J13: =-Bloomberg!I70/unit -> -10.077196 | K13: =-Bloomberg!J70/unit -> -14.560108 | ... P13: =-Bloomberg!O70/unit -> -14.57218 | Q13: -28.5
B14: - General and administrative exp | D14: =-Bloomberg!C71/unit -> -19.31928 | E14: =-Bloomberg!D71/unit -> -19.337477 | F14: =-Bloomberg!E71/unit -> -18.828244 | G14: =-Bloomberg!F71/unit -> -21.186238 | H14: =-Bloomberg!G71/unit -> -17.635771 | I14: =-Bloomberg!H71/unit -> -18.224652 | J14: =-Bloomberg!I71/unit -> -20.00184 | K14: =-Bloomberg!J71/unit -> -25.383783 | ... P14: =-Bloomberg!O71/unit -> -24.895741 | Q14: -30.1
B15: Operating profit | D15: =SUM(D12:D14) -> 4.8659608 | E15: =SUM(E12:E14) -> 15.961745 | F15: =SUM(F12:F14) -> 32.970587 | G15: =SUM(G12:G14) -> 16.36953 | H15: =SUM(H12:H14) -> -0.0874506 | I15: =SUM(I12:I14) -> 29.254465 | J15: =SUM(J12:J14) -> -4.3541914 | K15: =SUM(K12:K14) -> 37.37825 | ... Q15: =SUM(Q12:Q14) -> 83.1
B16: - Forex (losses) / gains | D16: =-Bloomberg!C73/unit -> 0 | E16: =-Bloomberg!D73/unit -> 0 | F16: =-Bloomberg!E73/unit -> 0 | G16: =-Bloomberg!F73/unit -> 0 | H16: =-Bloomberg!G73/unit -> 0 | I16: =-Bloomberg!H73/unit -> 0 | J16: =-Bloomberg!I73/unit -> 0 | K16: =-Bloomberg!J73/unit -> 0 | ... P16: =-Bloomberg!O73/unit -> 0 | Q16: 0
B17: - Net non-operating (losses) / gains | D17: =-Bloomberg!C74/unit -> 1.554492 | E17: =-Bloomberg!D74/unit -> -0.3978238 | F17: =-Bloomberg!E74/unit -> 2.3575704 | G17: =-Bloomberg!F74/unit -> 12.048193 | H17: =-Bloomberg!G74/unit -> 1.9822024 | I17: =-Bloomberg!H74/unit -> 1.4841765 | J17: =-Bloomberg!I74/unit -> 43.70519 | K17: =-Bloomberg!J74/unit -> 11.466231 | ... P17: =-Bloomberg!O74/unit -> 10.696592 | Q17: =9.6-3.6+20+55.4-0.1 -> 81.3
B18: EBIT | D18: =SUM(D15:D17) -> 6.4204528 | E18: =SUM(E15:E17) -> 15.563921 | F18: =SUM(F15:F17) -> 35.328158 | G18: =SUM(G15:G17) -> 28.417724 | H18: =SUM(H15:H17) -> 1.8947518 | I18: =SUM(I15:I17) -> 30.738641 | J18: =SUM(J15:J17) -> 39.350998 | K18: =SUM(K15:K17) -> 48.844482 | ... Q18: =SUM(Q15:Q17) -> 164.4
B19: - Interest exp | D19: =-Bloomberg!C75/unit -> -3.709756 | E19: =-Bloomberg!D75/unit -> -1.7768341 | F19: =-Bloomberg!E75/unit -> -1.0733554 | G19: =-Bloomberg!F75/unit -> -0.0565102 | H19: =-Bloomberg!G75/unit -> -0.0455231 | I19: =-Bloomberg!H75/unit -> -0.0551752 | J19: =-Bloomberg!I75/unit -> -0.0322711 | K19: =-Bloomberg!J75/unit -> -0.2098597 | ... P19: =-Bloomberg!O75/unit -> -0.0253813 | Q19: -0.086
B20: EBT | D20: =SUM(D18:D19) -> 2.7106968 | E20: =SUM(E18:E19) -> 13.787087 | F20: =SUM(F18:F19) -> 34.254802 | G20: =SUM(G18:G19) -> 28.361213 | H20: =SUM(H18:H19) -> 1.8492287 | I20: =SUM(I18:I19) -> 30.683466 | J20: =SUM(J18:J19) -> 39.318727 | K20: =SUM(K18:K19) -> 48.634622 | ... Q20: =SUM(Q18:Q19) -> 164.314
B21: - Income tax exp | D21: =-Bloomberg!C76/unit -> -4.0322641 | E21: =-Bloomberg!D76/unit -> -4.4655487 | F21: =-Bloomberg!E76/unit -> -7.0392748 | G21: =-Bloomberg!F76/unit -> -4.481864 | H21: =-Bloomberg!G76/unit -> -1.939814 | I21: =-Bloomberg!H76/unit -> -10.032337 | J21: =-Bloomberg!I76/unit -> -9.4907923 | K21: =-Bloomberg!J76/unit -> -9.2932007 | ... P21: =-Bloomberg!O76/unit -> -12.20129 | Q21: =-22.7+1.6 -> -21.1
B22: Profit after tax | D22: =SUM(D20:D21) -> -1.3215673 | E22: =SUM(E20:E21) -> 9.3215386 | F22: =SUM(F20:F21) -> 27.215528 | G22: =SUM(G20:G21) -> 23.879349 | H22: =SUM(H20:H21) -> -0.0905853 | I22: =SUM(I20:I21) -> 20.651129 | J22: =SUM(J20:J21) -> 29.827935 | K22: =SUM(K20:K21) -> 39.341421 | ... Q22: =SUM(Q20:Q21) -> 143.214
B23: - Minority interests | D23: =-Bloomberg!C77/unit -> 3.875888 | E23: =-Bloomberg!D77/unit -> -3.6336453 | F23: =-Bloomberg!E77/unit -> -1.7221895 | G23: =-Bloomberg!F77/unit -> 0.2450498 | H23: =-Bloomberg!G77/unit -> 1.4953463 | I23: =-Bloomberg!H77/unit -> -0.5761958 | J23: =-Bloomberg!I77/unit -> 0.2513511 | K23: =-Bloomberg!J77/unit -> -8.136408 | ... P23: =-Bloomberg!O77/unit -> -22.664508 | Q23: -26.6
B24: Net income to shareholders | D24: =SUM(D22:D23) -> 2.5543207 | E24: =SUM(E22:E23) -> 5.6878933 | F24: =SUM(F22:F23) -> 25.493338 | G24: =SUM(G22:G23) -> 24.124399 | H24: =SUM(H22:H23) -> 1.404761 | I24: =SUM(I22:I23) -> 20.074933 | J24: =SUM(J22:J23) -> 30.079286 | K24: =SUM(K22:K23) -> 31.205013 | ... Q24: =SUM(Q22:Q23) -> 116.614
B25: Earnings per share (basic) | D25: =D24/D28*10^3 -> 79.822522 | E25: =E24/E28*10^3 -> 177.74667 | F25: =F24/F28*10^3 -> 796.66681 | G25: =G24/G28*10^3 -> 652.01079 | H25: =H24/H28*10^3 -> 33.44669 | I25: =I24/I28*10^3 -> 424.86775 | J25: =J24/J28*10^3 -> 571.30994 | K25: =K24/K28*10^3 -> 591.00761 | ... Q25: =Q24/Q28*10^3 -> 1127.032
B26: EBITDA | D26: =D18-D27 -> 6.4204528 | E26: =E18-E27 -> 15.563921 | F26: =F18-F27 -> 35.328158 | G26: =G18-G27 -> 28.417724 | H26: =H18-H27 -> 2.0510943 | I26: =I18-I27 -> 31.176312 | J26: =J18-J27 -> 40.267074 | K26: =K18-K27 -> 50.839613 | ... Q26: =Q18-Q27 -> 165.084
B27: Depreciation expense | D27: =-Bloomberg!C16/unit -> 0 | E27: =-Bloomberg!D16/unit -> 0 | F27: =-Bloomberg!E16/unit -> 0 | G27: =-Bloomberg!F16/unit -> 0 | H27: =-Bloomberg!G16/unit -> -0.1563425 | I27: =-Bloomberg!H16/unit -> -0.437671 | J27: =-Bloomberg!I16/unit -> -0.916076 | K27: =-Bloomberg!J16/unit -> -1.995131 | ... P27: =-Bloomberg!O16/unit -> 0 | Q27: -0.684
B28: Outstanding shares | D28: =D56/10 -> 32 | E28: =(D56+E56)/2/10 -> 32 | F28: =(E56+F56)/2/10 -> 32 | G28: =(F56+G56)/2/10 -> 37 | H28: =(G56+H56)/2/10 -> 42 | I28: =(H56+I56)/2/10 -> 47.249841 | J28: =(I56+J56)/2/10 -> 52.649681 | K28: =(J56+K56)/2/10 -> 52.799681 | L28: =(K56+L56)/2/10 -> 63.899841 | ... Q28: =(P56+Q56)/2/10 -> 103.47
B29: BALANCE SHEET
B30: Assets
B31: + Cash & equivalents | D31: =Bloomberg!C80/unit -> 53.75065 | E31: =Bloomberg!D80/unit -> 55.688726 | F31: =Bloomberg!E80/unit -> 68.524952 | G31: =Bloomberg!F80/unit -> 136.05265 | H31: =Bloomberg!G80/unit -> 110.70893 | I31: =Bloomberg!H80/unit -> 120.15917 | J31: =Bloomberg!I80/unit -> 59.468312 | K31: =Bloomberg!J80/unit -> 72.88629 | ... P31: =Bloomberg!O80/unit -> 840.42562 | Q31: 662.4 | S31: Net Debt/Equity | T31: =Q47+Q50-Q31 -> -417.4
B32: + Short-term investments | D32: =Bloomberg!C81/unit -> 0 | E32: =Bloomberg!D81/unit -> 0 | F32: =Bloomberg!E81/unit -> 0 | G32: =Bloomberg!F81/unit -> 0 | H32: =Bloomberg!G81/unit -> 0 | I32: =Bloomberg!H81/unit -> 0 | J32: =Bloomberg!I81/unit -> 2.5 | K32: =Bloomberg!J81/unit -> 0 | ... P32: =Bloomberg!O81/unit -> 0 | Q32: 0 | T32: =T31/Q59 -> -0.27352556
B33: + Accounts & notes receivables | D33: =Bloomberg!C82/unit -> 65.074779 | E33: =Bloomberg!D82/unit -> 90.663914 | F33: =Bloomberg!E82/unit -> 110.7758 | G33: =Bloomberg!F82/unit -> 125.80868 | H33: =Bloomberg!G82/unit -> 95.291498 | I33: =Bloomberg!H82/unit -> 130.27006 | J33: =Bloomberg!I82/unit -> 111.40446 | K33: =Bloomberg!J82/unit -> 131.2453 | ... P33: =Bloomberg!O82/unit -> 161.16526 | Q33: =156.6-11.6 -> 145
B34: + Inventories | D34: =Bloomberg!C83/unit -> 96.877542 | E34: =Bloomberg!D83/unit -> 243.3597 | F34: =Bloomberg!E83/unit -> 168.31693 | G34: =Bloomberg!F83/unit -> 129.20743 | H34: =Bloomberg!G83/unit -> 327.79213 | I34: =Bloomberg!H83/unit -> 288.10147 | J34: =Bloomberg!I83/unit -> 296.15528 | K34: =Bloomberg!J83/unit -> 432.78726 | ... P34: =Bloomberg!O83/unit -> 535.17764 | Q34: 808.5
B35: + Other current assets | D35: =Bloomberg!C84/unit -> 276.79123 | E35: =Bloomberg!D84/unit -> 184.18461 | F35: =Bloomberg!E84/unit -> 190.94864 | G35: =Bloomberg!F84/unit -> 189.55619 | H35: =Bloomberg!G84/unit -> 236.16121 | I35: =Bloomberg!H84/unit -> 141.25336 | J35: =Bloomberg!I84/unit -> 322.65622 | K35: =Bloomberg!J84/unit -> 297.11363 | ... P35: =Bloomberg!O84/unit -> 511.05955 | Q35: =150+31.6+521.2+18.1 -> 720.9
B36: Total current assets | D36: =Bloomberg!C85/unit -> 492.49421 | E36: =Bloomberg!D85/unit -> 573.89695 | F36: =Bloomberg!E85/unit -> 538.56633 | G36: =Bloomberg!F85/unit -> 580.62496 | H36: =Bloomberg!G85/unit -> 769.95377 | I36: =Bloomberg!H85/unit -> 679.78406 | J36: =Bloomberg!I85/unit -> 792.18427 | K36: =Bloomberg!J85/unit -> 934.03248 | ... P36: =Bloomberg!O85/unit -> 2047.8281 | Q36: =SUM(Q31:Q35) -> 2336.8
B37: + Gross fixed assets | D37: =Bloomberg!C86/unit -> 45.365042 | E37: =Bloomberg!D86/unit -> 46.600329 | F37: =Bloomberg!E86/unit -> 46.602027 | G37: =Bloomberg!F86/unit -> 46.413282 | H37: =Bloomberg!G86/unit -> 46.368975 | I37: =Bloomberg!H86/unit -> 45.064213 | J37: =Bloomberg!I86/unit -> 46.540188 | K37: =Bloomberg!J86/unit -> 44.852805 | ... P37: =Bloomberg!O86/unit -> 45.642582 | Q37: =23.4+1.3 -> 24.7
B38: - Accumulated depreciation | D38: =Bloomberg!C87/unit -> 6.445137 | E38: =Bloomberg!D87/unit -> 7.4057501 | F38: =Bloomberg!E87/unit -> 8.1760738 | G38: =Bloomberg!F87/unit -> 8.9248649 | H38: =Bloomberg!G87/unit -> 9.7054133 | I38: =Bloomberg!H87/unit -> 9.6580492 | J38: =Bloomberg!I87/unit -> 10.63883 | K38: =Bloomberg!J87/unit -> 9.2843747 | ... P38: =Bloomberg!O87/unit -> 10.448956 | Q38: =11.1+0.58 -> 11.68
B39: + Net fixed assets | D39: =Bloomberg!C88/unit -> 38.919905 | E39: =Bloomberg!D88/unit -> 39.194579 | F39: =Bloomberg!E88/unit -> 38.425953 | G39: =Bloomberg!F88/unit -> 37.488417 | H39: =Bloomberg!G88/unit -> 36.663561 | I39: =Bloomberg!H88/unit -> 35.406164 | J39: =Bloomberg!I88/unit -> 35.901358 | K39: =Bloomberg!J88/unit -> 35.56843 | ... P39: =Bloomberg!O88/unit -> 35.193626 | Q39: =Q37-Q38 -> 13.02
B40: + Long-term investments | D40: =Bloomberg!C89/unit -> 180.27082 | E40: =Bloomberg!D89/unit -> 151.31676 | F40: =Bloomberg!E89/unit -> 179.72626 | G40: =Bloomberg!F89/unit -> 110.14465 | H40: =Bloomberg!G89/unit -> 110.14465 | I40: =Bloomberg!H89/unit -> 155.69259 | J40: =Bloomberg!I89/unit -> 110.25802 | K40: =Bloomberg!J89/unit -> 110.14465 | ... P40: =Bloomberg!O89/unit -> 0.7121685 | Q40: 350.5
B41: + Other Long-term assets | D41: =Bloomberg!C90/unit -> 82.844039 | E41: =Bloomberg!D90/unit -> 109.54275 | F41: =Bloomberg!E90/unit -> 87.667519 | G41: =Bloomberg!F90/unit -> 88.194154 | H41: =Bloomberg!G90/unit -> 87.027956 | I41: =Bloomberg!H90/unit -> 167.85271 | J41: =Bloomberg!I90/unit -> 176.44258 | K41: =Bloomberg!J90/unit -> 188.4695 | ... P41: =Bloomberg!O90/unit -> 425.55356 | Q41: =0.7+166.1+0.2+102.4 -> 269.4
B42: Total Long-term assets | D42: =Bloomberg!C91/unit -> 302.03477 | E42: =Bloomberg!D91/unit -> 300.0541 | F42: =Bloomberg!E91/unit -> 305.81974 | G42: =Bloomberg!F91/unit -> 235.82722 | H42: =Bloomberg!G91/unit -> 233.83617 | I42: =Bloomberg!H91/unit -> 358.95147 | J42: =Bloomberg!I91/unit -> 322.60196 | K42: =Bloomberg!J91/unit -> 334.18258 | ... P42: =Bloomberg!O91/unit -> 461.45936 | Q42: =SUM(Q39:Q41) -> 632.92
B43: Total assets | D43: =Bloomberg!C92/unit -> 794.52897 | E43: =Bloomberg!D92/unit -> 873.95104 | F43: =Bloomberg!E92/unit -> 844.38607 | G43: =Bloomberg!F92/unit -> 816.45218 | H43: =Bloomberg!G92/unit -> 1003.7899 | I43: =Bloomberg!H92/unit -> 1038.7355 | J43: =Bloomberg!I92/unit -> 1114.7862 | K43: =Bloomberg!J92/unit -> 1268.2151 | ... P43: =Bloomberg!O92/unit -> 2509.2874 | Q43: =Q42+Q36 -> 2969.72
B45: Liabilities & stockholders' equity
B46: + Accounts payable | D46: =Bloomberg!C93/unit -> 4.5999854 | E46: =Bloomberg!D93/unit -> 22.244769 | F46: =Bloomberg!E93/unit -> 27.617793 | G46: =Bloomberg!F93/unit -> 35.76286 | H46: =Bloomberg!G93/unit -> 26.918734 | I46: =Bloomberg!H93/unit -> 22.456059 | J46: =Bloomberg!I93/unit -> 15.647813 | K46: =Bloomberg!J93/unit -> 21.303074 | ... P46: =Bloomberg!O93/unit -> 44.978851 | Q46: 66.1
B47: + Short-term borrowings | D47: =Bloomberg!C94/unit -> 71.95 | E47: =Bloomberg!D94/unit -> 24.95 | F47: =Bloomberg!E94/unit -> 24.95 | G47: =Bloomberg!F94/unit -> 0.45 | H47: =Bloomberg!G94/unit -> 1.18 | I47: =Bloomberg!H94/unit -> 0.25 | J47: =Bloomberg!I94/unit -> 0.25 | K47: =Bloomberg!J94/unit -> 0 | ... P47: =Bloomberg!O94/unit -> 1.144 | Q47: 14.2
B48: + Other short-term liabilities | D48: =Bloomberg!C95/unit -> 251.82917 | E48: =Bloomberg!D95/unit -> 352.34944 | F48: =Bloomberg!E95/unit -> 290.1422 | G48: =Bloomberg!F95/unit -> 196.74578 | H48: =Bloomberg!G95/unit -> 395.07431 | I48: =Bloomberg!H95/unit -> 413.6619 | J48: =Bloomberg!I95/unit -> 464.62247 | K48: =Bloomberg!J95/unit -> 509.92335 | ... P48: =Bloomberg!O95/unit -> 869.29382 | Q48: =1105.8-Q46-Q47 -> 1025.5
B49: Total current liabilities | D49: =Bloomberg!C96/unit -> 328.37915 | E49: =Bloomberg!D96/unit -> 399.54421 | F49: =Bloomberg!E96/unit -> 342.70999 | G49: =Bloomberg!F96/unit -> 232.95864 | H49: =Bloomberg!G96/unit -> 423.17305 | I49: =Bloomberg!H96/unit -> 436.36796 | J49: =Bloomberg!I96/unit -> 480.52029 | K49: =Bloomberg!J96/unit -> 531.22642 | ... P49: =Bloomberg!O96/unit -> 915.41667 | Q49: =SUM(Q46:Q48) -> 1105.8
B50: + Long-term debt | D50: =Bloomberg!C97/unit -> 12.088176 | E50: =Bloomberg!D97/unit -> 12.061536 | F50: =Bloomberg!E97/unit -> 12.034896 | G50: =Bloomberg!F97/unit -> 0.11576 | H50: =Bloomberg!G97/unit -> 0.08912 | I50: =Bloomberg!H97/unit -> 0.06248 | J50: =Bloomberg!I97/unit -> 0.35 | K50: =Bloomberg!J97/unit -> 69.714 | ... P50: =Bloomberg!O97/unit -> 177.92314 | Q50: 230.8
B51: + Other long-term liabilities | D51: =Bloomberg!C98/unit -> 3.2471992 | E51: =Bloomberg!D98/unit -> 3.2308047 | F51: =Bloomberg!E98/unit -> 3.2621644 | G51: =Bloomberg!F98/unit -> 3.7836345 | H51: =Bloomberg!G98/unit -> 3.7951907 | I51: =Bloomberg!H98/unit -> 3.6967469 | J51: =Bloomberg!I98/unit -> 3.6783032 | K51: =Bloomberg!J98/unit -> 3.6598596 | ... P51: =Bloomberg!O98/unit -> 41.198765 | Q51: =337.9-Q50 -> 107.1
B52: Total long-term liabilities | D52: =Bloomberg!C99/unit -> 15.335375 | E52: =Bloomberg!D99/unit -> 15.292341 | F52: =Bloomberg!E99/unit -> 15.29706 | G52: =Bloomberg!F99/unit -> 3.8993945 | H52: =Bloomberg!G99/unit -> 3.8843107 | I52: =Bloomberg!H99/unit -> 3.7592269 | J52: =Bloomberg!I99/unit -> 4.0283032 | K52: =Bloomberg!J99/unit -> 73.37386 | ... P52: =Bloomberg!O99/unit -> 219.1219 | Q52: =SUM(Q50:Q51) -> 337.9
B53: Total liabilities | D53: =Bloomberg!C100/unit -> 343.71453 | E53: =Bloomberg!D100/unit -> 414.83655 | F53: =Bloomberg!E100/unit -> 358.00705 | G53: =Bloomberg!F100/unit -> 236.85803 | H53: =Bloomberg!G100/unit -> 427.05736 | I53: =Bloomberg!H100/unit -> 440.12719 | J53: =Bloomberg!I100/unit -> 484.54859 | K53: =Bloomberg!J100/unit -> 604.60028 | ... P53: =Bloomberg!O100/unit -> 1134.5386 | Q53: =Q52+Q49 -> 1443.7
B54: + Total preferred equity | D54: =Bloomberg!C101/unit -> 0 | E54: =Bloomberg!D101/unit -> 0 | F54: =Bloomberg!E101/unit -> 0 | G54: =Bloomberg!F101/unit -> 0 | H54: =Bloomberg!G101/unit -> 0 | I54: =Bloomberg!H101/unit -> 0 | J54: =Bloomberg!I101/unit -> 0 | K54: =Bloomberg!J101/unit -> 0 | ... P54: =Bloomberg!O101/unit -> 0 | Q54: 0
B55: + Additional paid in capital | D55: =Bloomberg!C102/unit -> 32.185271 | E55: =Bloomberg!D102/unit -> 32.185271 | F55: =Bloomberg!E102/unit -> 32.185271 | G55: =Bloomberg!F102/unit -> 31.980271 | H55: =Bloomberg!G102/unit -> 31.980271 | I55: =Bloomberg!H102/unit -> 10.982381 | J55: =Bloomberg!I102/unit -> 10.982381 | K55: =Bloomberg!J102/unit -> 10.982381 | ... P55: =Bloomberg!O102/unit -> 10.867981 | Q55: 10.3
B56: + Share capital | D56: =Bloomberg!C103/unit -> 320 | E56: =Bloomberg!D103/unit -> 320 | F56: =Bloomberg!E103/unit -> 320 | G56: =Bloomberg!F103/unit -> 420 | H56: =Bloomberg!G103/unit -> 420 | I56: =Bloomberg!H103/unit -> 524.99681 | J56: =Bloomberg!I103/unit -> 527.99681 | K56: =Bloomberg!J103/unit -> 527.99681 | ... P56: =Bloomberg!O103/unit -> 1007 | Q56: 1062.4
B57: + Retained earnings & other equity | D57: =Bloomberg!C104/unit -> 49.229183 | E57: =Bloomberg!D104/unit -> 54.917076 | F57: =Bloomberg!E104/unit -> 80.410414 | G57: =Bloomberg!F104/unit -> 103.75583 | H57: =Bloomberg!G104/unit -> 102.32484 | I57: =Bloomberg!H104/unit -> 38.400855 | J57: =Bloomberg!I104/unit -> 65.480141 | K57: =Bloomberg!J104/unit -> 94.153804 | ... P57: =Bloomberg!O104/unit -> 266.45693 | Q57: =307.4+17.5 -> 324.9
B58: + Minority interest | D58: =Bloomberg!C105/unit -> 49.399989 | E58: =Bloomberg!D105/unit -> 52.012147 | F58: =Bloomberg!E105/unit -> 53.783336 | G58: =Bloomberg!F105/unit -> 23.858045 | H58: =Bloomberg!G105/unit -> 22.427467 | I58: =Bloomberg!H105/unit -> 24.22829 | J58: =Bloomberg!I105/unit -> 25.778303 | K58: =Bloomberg!J105/unit -> 30.481793 | ... P58: =Bloomberg!O105/unit -> 90.423952 | Q58: 128.4
B59: Total shareholders' equity | D59: =Bloomberg!C106/unit -> 450.81444 | E59: =Bloomberg!D106/unit -> 459.11449 | F59: =Bloomberg!E106/unit -> 486.37902 | G59: =Bloomberg!F106/unit -> 579.59414 | H59: =Bloomberg!G106/unit -> 576.73258 | I59: =Bloomberg!H106/unit -> 598.60834 | J59: =Bloomberg!I106/unit -> 630.23763 | K59: =Bloomberg!J106/unit -> 663.61479 | ... P59: =Bloomberg!O106/unit -> 1374.7489 | Q59: =SUM(Q54:Q58) -> 1526
B60: Total liabilities & equity | D60: =Bloomberg!C107/unit -> 794.52897 | E60: =Bloomberg!D107/unit -> 873.95104 | F60: =Bloomberg!E107/unit -> 844.38607 | G60: =Bloomberg!F107/unit -> 816.45218 | H60: =Bloomberg!G107/unit -> 1003.7899 | I60: =Bloomberg!H107/unit -> 1038.7355 | J60: =Bloomberg!I107/unit -> 1114.7862 | K60: =Bloomberg!J107/unit -> 1268.2151 | ... P60: =Bloomberg!O107/unit -> 2509.2874 | Q60: =Q59+Q53 -> 2969.7
B61: Check | D61: =D43-D60 -> 0 | E61: =E43-E60 -> 0 | F61: =F43-F60 -> 0 | G61: =G43-G60 -> 0 | H61: =H43-H60 -> 0 | I61: =I43-I60 -> 0 | J61: =J43-J60 -> 0 | K61: =K43-K60 -> 0 | ... Q61: =Q43-Q60 -> 0.02
B63: CASH FLOW STATEMENT
B64: Beginning cash | D64: =C31 -> 0 | E64: =D31 -> 53.75065 | F64: =E31 -> 55.688726 | G64: =F31 -> 68.524952 | H64: =G31 -> 136.05265 | I64: =H31 -> 110.70893 | J64: =I31 -> 120.15917 | K64: =J31 -> 59.468312 | ... P64: =O31 -> 776.33899
B65: + Net Income | D65: =Bloomberg!C108/unit -> 2.5543208 | E65: =Bloomberg!D108/unit -> 5.6878931 | F65: =Bloomberg!E108/unit -> 25.493338 | G65: =Bloomberg!F108/unit -> 24.124399 | H65: =Bloomberg!G108/unit -> 1.4047609 | I65: =Bloomberg!H108/unit -> 20.074934 | J65: =Bloomberg!I108/unit -> 30.079286 | K65: =Bloomberg!J108/unit -> 31.205013 | ... P65: =Bloomberg!O108/unit -> 36.595386
B66: + Depreciation & Amortization | D66: =Bloomberg!C109/unit -> 0.9597071 | E66: =Bloomberg!D109/unit -> 0.7043371 | F66: =Bloomberg!E109/unit -> 0.7853574 | G66: =Bloomberg!F109/unit -> 1.6653115 | H66: =Bloomberg!G109/unit -> 1.0149951 | I66: =Bloomberg!H109/unit -> 0.9478054 | J66: =Bloomberg!I109/unit -> 0.8813634 | K66: =Bloomberg!J109/unit -> 0.6953571 | ... P66: =Bloomberg!O109/unit -> 0.7564283
B67: + Other Non-Cash Adjustments | D67: =Bloomberg!C110/unit -> -6.5866421 | E67: =Bloomberg!D110/unit -> 11.088254 | F67: =Bloomberg!E110/unit -> -38.79726 | G67: =Bloomberg!F110/unit -> -4.0608151 | H67: =Bloomberg!G110/unit -> -7.951832 | I67: =Bloomberg!H110/unit -> -0.4424351 | J67: =Bloomberg!I110/unit -> -133.43557 | K67: =Bloomberg!J110/unit -> 100.66317 | ... P67: =Bloomberg!O110/unit -> -8.4050313
B68: + Changes in Non-Cash Capital | D68: =Bloomberg!C111/unit -> -2.6137703 | E68: =Bloomberg!D111/unit -> 34.196132 | F68: =Bloomberg!E111/unit -> 26.203231 | G68: =Bloomberg!F111/unit -> 33.913307 | H68: =Bloomberg!G111/unit -> -20.369786 | I68: =Bloomberg!H111/unit -> 78.666343 | J68: =Bloomberg!I111/unit -> -78.86143 | K68: =Bloomberg!J111/unit -> -105.46869 | ... P68: =Bloomberg!O111/unit -> -15.954345
B69: Cash From Operating Activities | D69: =Bloomberg!C112/unit -> -5.6863844 | E69: =Bloomberg!D112/unit -> 51.676616 | F69: =Bloomberg!E112/unit -> 13.684666 | G69: =Bloomberg!F112/unit -> 55.642203 | H69: =Bloomberg!G112/unit -> -25.901862 | I69: =Bloomberg!H112/unit -> 99.246647 | J69: =Bloomberg!I112/unit -> -181.33636 | K69: =Bloomberg!J112/unit -> 27.094852 | ... P69: =Bloomberg!O112/unit -> 12.992437
B70: + Disposal of Fixed Assets | D70: =Bloomberg!C113/unit -> 0 | E70: =Bloomberg!D113/unit -> 0.0145455 | F70: =Bloomberg!E113/unit -> 0 | G70: =Bloomberg!F113/unit -> 0.003 | H70: =Bloomberg!G113/unit -> 0 | I70: =Bloomberg!H113/unit -> 0.1841546 | J70: =Bloomberg!I113/unit -> 0 | K70: =Bloomberg!J113/unit -> 0.4848182 | ... P70: =Bloomberg!O113/unit -> 0.4045455
B71: + Capital Expenditures | D71: =Bloomberg!C114/unit -> -0.0360727 | E71: =Bloomberg!D114/unit -> -1.4208486 | F71: =Bloomberg!E114/unit -> -0.1289487 | G71: =Bloomberg!F114/unit -> -1.1974727 | H71: =Bloomberg!G114/unit -> -0.1452265 | I71: =Bloomberg!H114/unit -> -0.581018 | J71: =Bloomberg!I114/unit -> -0.133 | K71: =Bloomberg!J114/unit -> -1.6246152 | ... P71: =Bloomberg!O114/unit -> -3.9985727
B72: + Increase in Investments | D72: =Bloomberg!C115/unit -> 0 | E72: =Bloomberg!D115/unit -> 0 | F72: =Bloomberg!E115/unit -> 0 | G72: =Bloomberg!F115/unit -> 0 | H72: =Bloomberg!G115/unit -> 0 | I72: =Bloomberg!H115/unit -> 0 | J72: =Bloomberg!I115/unit -> 0 | K72: =Bloomberg!J115/unit -> 0 | ... P72: =Bloomberg!O115/unit -> 0
B73: + Decrease in Investments | D73: =Bloomberg!C116/unit -> 0 | E73: =Bloomberg!D116/unit -> 0 | F73: =Bloomberg!E116/unit -> 0 | G73: =Bloomberg!F116/unit -> 0 | H73: =Bloomberg!G116/unit -> 0 | I73: =Bloomberg!H116/unit -> 0 | J73: =Bloomberg!I116/unit -> 0 | K73: =Bloomberg!J116/unit -> 0 | ... P73: =Bloomberg!O116/unit -> 0
B74: + Other Investing Activities | D74: =Bloomberg!C117/unit -> -6.3786455 | E74: =Bloomberg!D117/unit -> -0.178816 | F74: =Bloomberg!E117/unit -> -0.3282315 | G74: =Bloomberg!F117/unit -> -36.218216 | H74: =Bloomberg!G117/unit -> 0 | I74: =Bloomberg!H117/unit -> -92.682241 | J74: =Bloomberg!I117/unit -> 122.75136 | K74: =Bloomberg!J117/unit -> -195.71519 | ... P74: =Bloomberg!O117/unit -> -4
B75: Cash From Investing Activities | D75: =Bloomberg!C118/unit -> -6.4147182 | E75: =Bloomberg!D118/unit -> -1.5851191 | F75: =Bloomberg!E118/unit -> -0.4571802 | G75: =Bloomberg!F118/unit -> -37.412689 | H75: =Bloomberg!G118/unit -> -0.1452265 | I75: =Bloomberg!H118/unit -> -93.079104 | J75: =Bloomberg!I118/unit -> 122.61836 | K75: =Bloomberg!J118/unit -> -196.85498 | ... P75: =Bloomberg!O118/unit -> -7.5940273
B76: + Dividends Paid | D76: =Bloomberg!C119/unit -> -2.2814075 | E76: =Bloomberg!D119/unit -> -0.906334 | F76: =Bloomberg!E119/unit -> -0.4136194 | G76: =Bloomberg!F119/unit -> -1.6597886 | H76: =Bloomberg!G119/unit -> 0 | I76: =Bloomberg!H119/unit -> -1.2054 | J76: =Bloomberg!I119/unit -> -0.144 | K76: =Bloomberg!J119/unit -> -0.738 | ... P76: =Bloomberg!O119/unit -> -5.1695
... B78: + Decrease in Capital Stocks | D78: =Bloomberg!C121/unit -> 0 | E78: =Bloomberg!D121/unit -> 0 | F78: =Bloomberg!E121/unit -> 0 | G78: =Bloomberg!F121/unit -> -3.1017301 | H78: =Bloomberg!G121/unit -> 0 | I78: =Bloomberg!H121/unit -> 0 | J78: =Bloomberg!I121/unit -> 0 | K78: =Bloomberg!J121/unit -> 0 | ... P78: =Bloomberg!O121/unit -> 0
B79: Cash available / (required before debt) | D79: =D64+D69+D75+SUM(D76:D78) -> -14.12251 | E79: =E64+E69+E75+SUM(E76:E78) -> 103.30581 | F79: =F64+F69+F75+SUM(F76:F78) -> 68.551592 | G79: =G64+G69+G75+SUM(G76:G78) -> 182.70595 | H79: =H64+H69+H75+SUM(H76:H78) -> 110.00557 | I79: =I64+I69+I75+SUM(I76:I78) -> 115.67107 | J79: =J64+J69+J75+SUM(J76:J78) -> 61.397175 | K79: =K64+K69+K75+SUM(K76:K78) -> 2.4122276 | ... P79: =P64+P69+P75+SUM(P76:P78) -> 781.4679
B80: + Change in short-term debt | D80: =D47-C47 -> 71.95 | E80: =E47-D47 -> -47 | F80: =F47-E47 -> 0 | G80: =G47-F47 -> -24.5 | H80: =H47-G47 -> 0.73 | I80: =I47-H47 -> -0.93 | J80: =J47-I47 -> 0 | K80: =K47-J47 -> -0.25 | ... P80: =P47-O47 -> 0.144
B81: + Change in long-term debt | D81: =D50-C50 -> 12.088176 | E81: =E50-D50 -> -0.02664 | F81: =F50-E50 -> -0.02664 | G81: =G50-F50 -> -11.919136 | H81: =H50-G50 -> -0.02664 | I81: =I50-H50 -> -0.02664 | J81: =J50-I50 -> 0.28752 | K81: =K50-J50 -> 69.364 | ... P81: =P50-O50 -> 58.813725
B82: + Other Financing Activities | D82: =Bloomberg!C122/unit -> 0 | E82: =Bloomberg!D122/unit -> 0 | F82: =Bloomberg!E122/unit -> 0 | G82: =Bloomberg!F122/unit -> 0 | H82: =Bloomberg!G122/unit -> 0 | I82: =Bloomberg!H122/unit -> 0 | J82: =Bloomberg!I122/unit -> 0 | K82: =Bloomberg!J122/unit -> 0 | ... P82: =Bloomberg!O122/unit -> 0
B83: Cash from Financing Activities | D83: =Bloomberg!C123/unit -> -41.510047 | E83: =Bloomberg!D123/unit -> -48.15342 | F83: =Bloomberg!E123/unit -> -0.3912594 | G83: =Bloomberg!F123/unit -> 49.298188 | H83: =Bloomberg!G123/unit -> 0.70336 | I83: =Bloomberg!H123/unit -> 3.282706 | J83: =Bloomberg!I123/unit -> -5.692511 | K83: =Bloomberg!J123/unit -> 186.89776 | ... P83: =Bloomberg!O123/unit -> 58.688225
B84: Net Changes in Cash | D84: =Bloomberg!C124/unit -> -53.61115 | E84: =Bloomberg!D124/unit -> 1.9380765 | F84: =Bloomberg!E124/unit -> 12.836226 | G84: =Bloomberg!F124/unit -> 67.527702 | H84: =Bloomberg!G124/unit -> -25.343728 | I84: =Bloomberg!H124/unit -> 9.4502488 | J84: =Bloomberg!I124/unit -> -64.410511 | K84: =Bloomberg!J124/unit -> 17.137626 | ... P84: =Bloomberg!O124/unit -> 64.086635
B85: Ending cash | D85: =D64+D84 -> -53.61115 | E85: =E64+E84 -> 55.688726 | F85: =F64+F84 -> 68.524952 | G85: =G64+G84 -> 136.05265 | H85: =H64+H84 -> 110.70893 | I85: =I64+I84 -> 120.15917 | J85: =J64+J84 -> 55.748664 | K85: =K64+K84 -> 76.605938 | ... P85: =P64+P84 -> 840.42562
B86: Check | D86: 0 | E86: 0 | F86: 0 | G86: 0 | H86: 0 | I86: 0 | J86: 0 | K86: 0 | L86: 1 | M86: 2 | N86: 3 | O86: 4 | P86: 4
B88: Share price at yearend | D88: =Bloomberg!C125 -> 6643.77 | E88: =Bloomberg!D125 -> 7339.04 | F88: =Bloomberg!E125 -> 5871.24 | G88: =Bloomberg!F125 -> 8343.33 | H88: =Bloomberg!G125 -> 8806.85 | I88: =Bloomberg!H125 -> 9149.86 | J88: =Bloomberg!I125 -> 8565.82 | K88: =Bloomberg!J125 -> 12500 | ... P88: =Bloomberg!O125 -> 15454.55
B90: FINANCIAL RATIO ANALYSIS
B91: Market cap year end | D91: =IFERROR(D28*D88/10^3,0) -> 212.60064 | E91: =IFERROR(E28*E88/10^3,0) -> 234.84928 | F91: =IFERROR(F28*F88/10^3,0) -> 187.87968 | G91: =IFERROR(G28*G88/10^3,0) -> 308.70321 | H91: =IFERROR(H28*H88/10^3,0) -> 369.8877 | I91: =IFERROR(I28*I88/10^3,0) -> 432.32943 | J91: =IFERROR(J28*J88/10^3,0) -> 450.98769 | K91: =IFERROR(K28*K88/10^3,0) -> 659.99601 | ... Q91: =IFERROR(Q28*Q88/10^3,0) -> 0
B92: Enterprise value EV (ST&LT debt + market cap + minority) | D92: =IFERROR((D47+D50+D58+D91)/(D91/D91),0) -> 346.03881 | E92: =IFERROR((E47+E50+E58+E91)/(E91/E91),0) -> 323.87296 | F92: =IFERROR((F47+F50+F58+F91)/(F91/F91),0) -> 278.64791 | G92: =IFERROR((G47+G50+G58+G91)/(G91/G91),0) -> 333.12702 | H92: =IFERROR((H47+H50+H58+H91)/(H91/H91),0) -> 393.58429 | I92: =IFERROR((I47+I50+I58+I91)/(I91/I91),0) -> 456.8702 | J92: =IFERROR((J47+J50+J58+J91)/(J91/J91),0) -> 477.36599 | K92: =IFERROR((K47+K50+K58+K91)/(K91/K91),0) -> 760.19181 | ... Q92: =IFERROR((Q47+Q50+Q58+Q91)/(Q91/Q91),0) -> 0
B93: Total short- and long-term debt | D93: =D47+D50 -> 84.038176 | E93: =E47+E50 -> 37.011536 | F93: =F47+F50 -> 36.984896 | G93: =G47+G50 -> 0.56576 | H93: =H47+H50 -> 1.26912 | I93: =I47+I50 -> 0.31248 | J93: =J47+J50 -> 0.6 | K93: =K47+K50 -> 69.714 | ... Q93: =Q47+Q50 -> 245
B94: Total average short- and long-term debt | D94: =IF(C93<1,D93,AVERAGE(C93:D93)) -> 84.038176 | E94: =IF(D93<1,E93,AVERAGE(D93:E93)) -> 60.524856 | F94: =IF(E93<1,F93,AVERAGE(E93:F93)) -> 36.998216 | G94: =IF(F93<1,G93,AVERAGE(F93:G93)) -> 18.775328 | H94: =IF(G93<1,H93,AVERAGE(G93:H93)) -> 1.26912 | I94: =IF(H93<1,I93,AVERAGE(H93:I93)) -> 0.7908 | J94: =IF(I93<1,J93,AVERAGE(I93:J93)) -> 0.6 | K94: =IF(J93<1,K93,AVERAGE(J93:K93)) -> 69.714 | ... Q94: =IF(P93<1,Q93,AVERAGE(P93:Q93)) -> 212.03357
B95: Total invested capital (ST& LT debt + equity) | D95: =D47+D50+D59 -> 534.85262 | E95: =E47+E50+E59 -> 496.12603 | F95: =F47+F50+F59 -> 523.36392 | G95: =G47+G50+G59 -> 580.1599 | H95: =H47+H50+H59 -> 578.0017 | I95: =I47+I50+I59 -> 598.92082 | J95: =J47+J50+J59 -> 630.83763 | K95: =K47+K50+K59 -> 733.32879 | ... Q95: =Q47+Q50+Q59 -> 1771
B96: Total average invested capital | D96: =IF(C95<1,D95,AVERAGE(C95:D95)) -> 534.85262 | E96: =IF(D95<1,E95,AVERAGE(D95:E95)) -> 515.48932 | F96: =IF(E95<1,F95,AVERAGE(E95:F95)) -> 509.74497 | G96: =IF(F95<1,G95,AVERAGE(F95:G95)) -> 551.76191 | H96: =IF(G95<1,H95,AVERAGE(G95:H95)) -> 579.0808 | I96: =IF(H95<1,I95,AVERAGE(H95:I95)) -> 588.46126 | J96: =IF(I95<1,J95,AVERAGE(I95:J95)) -> 614.87923 | K96: =IF(J95<1,K95,AVERAGE(J95:K95)) -> 682.08321 | ... Q96: =IF(P95<1,Q95,AVERAGE(P95:Q95)) -> 1662.408
B97: Total average assets | D97: =IFERROR(IF(C43<1,D43,AVERAGE(C43:D43)),0) -> 794.52897 | E97: =IFERROR(IF(D43<1,E43,AVERAGE(D43:E43)),0) -> 834.24001 | F97: =IFERROR(IF(E43<1,F43,AVERAGE(E43:F43)),0) -> 859.16856 | G97: =IFERROR(IF(F43<1,G43,AVERAGE(F43:G43)),0) -> 830.41912 | H97: =IFERROR(IF(G43<1,H43,AVERAGE(G43:H43)),0) -> 910.12106 | I97: =IFERROR(IF(H43<1,I43,AVERAGE(H43:I43)),0) -> 1021.2627 | J97: =IFERROR(IF(I43<1,J43,AVERAGE(I43:J43)),0) -> 1076.7609 | K97: =IFERROR(IF(J43<1,K43,AVERAGE(J43:K43)),0) -> 1191.5006 | ... Q97: =IFERROR(IF(P43<1,Q43,AVERAGE(P43:Q43)),0) -> 2739.5037
B98: Total average equity | D98: =IFERROR(IF(C59<1,D59,AVERAGE(C59:D59)),0) -> 450.81444 | E98: =IFERROR(IF(D59<1,E59,AVERAGE(D59:E59)),0) -> 454.96447 | F98: =IFERROR(IF(E59<1,F59,AVERAGE(E59:F59)),0) -> 472.74676 | G98: =IFERROR(IF(F59<1,G59,AVERAGE(F59:G59)),0) -> 532.98658 | H98: =IFERROR(IF(G59<1,H59,AVERAGE(G59:H59)),0) -> 578.16336 | I98: =IFERROR(IF(H59<1,I59,AVERAGE(H59:I59)),0) -> 587.67046 | J98: =IFERROR(IF(I59<1,J59,AVERAGE(I59:J59)),0) -> 614.42299 | K98: =IFERROR(IF(J59<1,K59,AVERAGE(J59:K59)),0) -> 646.92621 | ... Q98: =IFERROR(IF(P59<1,Q59,AVERAGE(P59:Q59)),0) -> 1450.3744
B99: Total average inventory | D99: =IFERROR(IF(C34<1,D34,AVERAGE(C34:D34)),0) -> 96.877542 | E99: =IFERROR(IF(D34<1,E34,AVERAGE(D34:E34)),0) -> 170.11862 | F99: =IFERROR(IF(E34<1,F34,AVERAGE(E34:F34)),0) -> 205.83832 | G99: =IFERROR(IF(F34<1,G34,AVERAGE(F34:G34)),0) -> 148.76218 | H99: =IFERROR(IF(G34<1,H34,AVERAGE(G34:H34)),0) -> 228.49978 | I99: =IFERROR(IF(H34<1,I34,AVERAGE(H34:I34)),0) -> 307.9468 | J99: =IFERROR(IF(I34<1,J34,AVERAGE(I34:J34)),0) -> 292.12838 | K99: =IFERROR(IF(J34<1,K34,AVERAGE(J34:K34)),0) -> 364.47127 | ... Q99: =IFERROR(IF(P34<1,Q34,AVERAGE(P34:Q34)),0) -> 671.83882
B100: Profitability ratios
B101: Gross profit margin | D101: =IFERROR(D12/D10,0) -> 0.88995394 | E101: =IFERROR(E12/E10,0) -> 0.51117168 | F101: =IFERROR(F12/F10,0) -> 0.41597892 | G101: =IFERROR(G12/G10,0) -> 0.41222002 | H101: =IFERROR(H12/H10,0) -> 0.5985236 | I101: =IFERROR(I12/I10,0) -> 0.52994881 | J101: =IFERROR(J12/J10,0) -> 0.82124367 | K101: =IFERROR(K12/K10,0) -> 0.62640127 | ... Q101: =IFERROR(Q12/Q10,0) -> 0.66745172
B102: Operating profit margin | D102: =IFERROR(D15/D10,0) -> 0.14012624 | E102: =IFERROR(E15/E10,0) -> 0.16823485 | F102: =IFERROR(F15/F10,0) -> 0.21557517 | G102: =IFERROR(G15/G10,0) -> 0.13533318 | H102: =IFERROR(H15/H10,0) -> -0.0017930099 | I102: =IFERROR(I15/I10,0) -> 0.21038031 | J102: =IFERROR(J15/J10,0) -> -0.13900384 | K102: =IFERROR(K15/K10,0) -> 0.30280826 | ... Q102: =IFERROR(Q15/Q10,0) -> 0.39142723
B103: EBITDA margin | D103: =IFERROR(D26/D10,0) -> 0.18489132 | E103: =IFERROR(E26/E10,0) -> 0.16404183 | F103: =IFERROR(F26/F10,0) -> 0.23098993 | G103: =IFERROR(G26/G10,0) -> 0.23494021 | H103: =IFERROR(H26/H10,0) -> 0.042053827 | I103: =IFERROR(I26/I10,0) -> 0.22420107 | J103: =IFERROR(J26/J10,0) -> 1.2854919 | K103: =IFERROR(K26/K10,0) -> 0.4118613 | ... Q103: =IFERROR(Q26/Q10,0) -> 0.77759774
B104: Profit after tax margin | D104: =IFERROR(D22/D10,0) -> -0.03805749 | E104: =IFERROR(E22/E10,0) -> 0.098247879 | F104: =IFERROR(F22/F10,0) -> 0.17794624 | G104: =IFERROR(G22/G10,0) -> 0.19741973 | H104: =IFERROR(H22/H10,0) -> -0.001857281 | I104: =IFERROR(I22/I10,0) -> 0.14851036 | J104: =IFERROR(J22/J10,0) -> 0.95223131 | K104: =IFERROR(K22/K10,0) -> 0.31871228 | ... Q104: =IFERROR(Q22/Q10,0) -> 0.67458314
B105: ROE Dupont = ROA * leverage ratio | D105: =D106*D111 -> 0.0089443987 | E105: =E106*E111 -> 0.020488498 | F105: =F106*F111 -> 0.057568935 | G105: =G106*G111 -> 0.044802909 | H105: =H106*H111 -> -0.00015667769 | I105: =I106*I111 -> 0.035140662 | J105: =J106*J111 -> 0.048546255 | K105: =K106*K111 -> 0.060812842 | ... Q105: =Q106*Q111 -> 0.098742778
B106: ROA Dupont = EBIT margin * TB * IB * asset turnover | D106: =D107*D108*D109*D110 -> 0.0050750372 | E106: =E107*E108*E109*E110 -> 0.011173689 | F106: =F107*F108*F109*F110 -> 0.031676587 | G106: =G107*G108*G109*G110 -> 0.02875578 | H106: =H107*H108*H109*H110 -> -9.9531045e-05 | I106: =I107*I108*I109*I110 -> 0.020221172 | J106: =J107*J108*J109*J110 -> 0.02770154 | K106: =K107*K108*K109*K110 -> 0.03301838 | ... Q106: =Q107*Q108*Q109*Q110 -> 0.052277352
B107: * EBIT Margin (EBIT/Sales) | D107: =IFERROR(D18/D10,0) -> 0.18489132 | E107: =IFERROR(E18/E10,0) -> 0.16404183 | F107: =IFERROR(F18/F10,0) -> 0.23098993 | G107: =IFERROR(G18/G10,0) -> 0.23494021 | H107: =IFERROR(H18/H10,0) -> 0.038848319 | I107: =IFERROR(I18/I10,0) -> 0.22105361 | J107: =IFERROR(J18/J10,0) -> 1.256247 | K107: =IFERROR(K18/K10,0) -> 0.39569837 | ... Q107: =IFERROR(Q18/Q10,0) -> 0.77437588
B108: * Tax burden TB (profit after tax/EBT) | D108: =1-D139-1 -> 1.4875379 | E108: =IFERROR(E22/E20,0) -> 0.67610645 | F108: =IFERROR(F22/F20,0) -> 0.79450254 | G108: =IFERROR(G22/G20,0) -> 0.84197206 | H108: =IFERROR(H22/H20,0) -> -0.04898545 | I108: =IFERROR(I22/I20,0) -> 0.67303769 | J108: =IFERROR(J22/J20,0) -> 0.75861903 | K108: =IFERROR(K22/K20,0) -> 0.808918 | L108: =IFERROR(L22/L20,0) -> 0.76930263 | ... Q108: =IFERROR(Q22/Q20,0) -> 0.87158733
B109: * Interest burden IB (EBT/EBIT) | D109: =IFERROR(D20/D18,0) -> 0.42219714 | E109: =IFERROR(E20/E18,0) -> 0.88583635 | F109: =IFERROR(F20/F18,0) -> 0.96961757 | G109: =IFERROR(G20/G18,0) -> 0.99801145 | H109: =IFERROR(H20/H18,0) -> 0.97597411 | I109: =IFERROR(I20/I18,0) -> 0.99820502 | J109: =IFERROR(J20/J18,0) -> 0.99917992 | K109: =IFERROR(K20/K18,0) -> 0.99570351 | ... Q109: =IFERROR(Q20/Q18,0) -> 0.99947689
B110: * Asset turnover (Sales/assets) | D110: =IFERROR(D10/D97,0) -> 0.043705833 | E110: =IFERROR(E10/E97,0) -> 0.11372957 | F110: =IFERROR(F10/F97,0) -> 0.17801212 | G110: =IFERROR(G10/G97,0) -> 0.14565808 | H110: =IFERROR(H10/H97,0) -> 0.053589652 | I110: =IFERROR(I10/I97,0) -> 0.13616001 | J110: =IFERROR(J10/J97,0) -> 0.029091188 | K110: =IFERROR(K10/K97,0) -> 0.10359933 | ... Q110: =IFERROR(Q10/Q97,0) -> 0.077495788
B111: Leverage ratio (total assets/ total equity) | D111: =IFERROR(D97/D98,) -> 1.7624302 | E111: =IFERROR(E97/E98,) -> 1.8336377 | F111: =IFERROR(F97/F98,) -> 1.817397 | G111: =IFERROR(G97/G98,) -> 1.5580488 | H111: =IFERROR(H97/H98,) -> 1.574159 | I111: =IFERROR(I97/I98,) -> 1.7378153 | J111: =IFERROR(J97/J98,) -> 1.7524749 | K111: =IFERROR(K97/K98,) -> 1.8417876 | ... Q111: =IFERROR(Q97/Q98,) -> 1.8888252
...

Sheet QoQ
B7: =ticker -> DXG VN EQUITY
D8: =D16 -> 2023 | H8: =H16 -> 2024 | L8: =L16 -> 2025 | P8: =D8 -> 2023 | Q8: =H8 -> 2024 | R8: =L8 -> 2025 | S8: Reality Check | U8: Year over Year Performance
B9: MARGIN ANALYSIS | D9: Quarter 1 | E9: Quarter 2 | F9: Quarter 3 | G9: Quarter 4 | H9: Quarter 1 | I9: Quarter 2 | J9: Quarter 3 | K9: Quarter 4 | L9: Quarter 1 | M9: Quarter 2 | N9: Quarter 3 | O9: Quarter 4 | P9: FY | Q9: FY | R9: FY | S9: Forecast | T9: -/+ actual | U9: Quarter 1 | V9: Quarter 2 | W9: Quarter 3 | X9: Quarter 4
B10: Gross profit margin | D10: =IFERROR(D20/D18,0) -> 0.88995394 | E10: =IFERROR(E20/E18,0) -> 0.51117168 | F10: =IFERROR(F20/F18,0) -> 0.41597892 | G10: =IFERROR(G20/G18,0) -> 0.41222002 | H10: =IFERROR(H20/H18,0) -> 0.5985236 | I10: =IFERROR(I20/I18,0) -> 0.52994881 | J10: =IFERROR(J20/J18,0) -> 0.82124367 | K10: =IFERROR(K20/K18,0) -> 0.62640127 | ... O10: =IFERROR(O20/O18,0) -> 0.55192512 | P10: =P20/P18 -> 0.47802568 | Q10: =Q20/Q18 -> 0.60109823 | R10: =R20/R18 -> 0.59625986 | T10: =L10-S10 -> 0.5349407 | U10: =IFERROR(IF(L10<>0,L10/H10-1,0),0) -> -0.1062329 | V10: =IFERROR(IF(M10<>0,M10/I10-1,0),0) -> 0.33610047 | W10: =IFERROR(IF(N10<>0,N10/J10-1,0),0) -> -0.20835819 | X10: =IFERROR(IF(O10<>0,O10/K10-1,0),0) -> -0.11889526
B11: Operating profit margin | D11: =IFERROR(D23/D18,0) -> 0.14012624 | E11: =IFERROR(E23/E18,0) -> 0.16823485 | F11: =IFERROR(F23/F18,0) -> 0.21557517 | G11: =IFERROR(G23/G18,0) -> 0.13533318 | H11: =IFERROR(H23/H18,0) -> -0.0017930099 | I11: =IFERROR(I23/I18,0) -> 0.21038031 | J11: =IFERROR(J23/J18,0) -> -0.13900384 | K11: =IFERROR(K23/K18,0) -> 0.30280826 | ... O11: =IFERROR(O23/O18,0) -> 0.320915 | P11: =P23/P18 -> 0.17389667 | Q11: =Q23/Q18 -> 0.18153147 | R11: =R23/R18 -> 0.32633638 | T11: =L11-S11 -> 0.29791364 | U11: =IFERROR(IF(L11<>0,L11/H11-1,0),0) -> -167.15281 | V11: =IFERROR(IF(M11<>0,M11/I11-1,0),0) -> 1.0920619 | W11: =IFERROR(IF(N11<>0,N11/J11-1,0),0) -> -2.1626611 | X11: =IFERROR(IF(O11<>0,O11/K11-1,0),0) -> 0.059796052
B12: EBITDA | D12: =IFERROR(D34/D18,0) -> 0.18489132 | E12: =IFERROR(E34/E18,0) -> 0.16404183 | F12: =IFERROR(F34/F18,0) -> 0.23098993 | G12: =IFERROR(G34/G18,0) -> 0.23494021 | H12: =IFERROR(H34/H18,0) -> 0.042053827 | I12: =IFERROR(I34/I18,0) -> 0.22420107 | J12: =IFERROR(J34/J18,0) -> 1.2854919 | K12: =IFERROR(K34/K18,0) -> 0.4118613 | ... O12: =IFERROR(O34/O18,0) -> 0.7003107 | P12: =P34/P18 -> 0.21246499 | Q12: =Q34/Q18 -> 0.36292268 | R12: =R34/R18 -> 0.54686896 | T12: =L12-S12 -> 0.34395228 | U12: =IFERROR(IF(L12<>0,L12/H12-1,0),0) -> 7.178858 | V12: =IFERROR(IF(M12<>0,M12/I12-1,0),0) -> 1.2901403 | W12: =IFERROR(IF(N12<>0,N12/J12-1,0),0) -> -0.76338933 | X12: =IFERROR(IF(O12<>0,O12/K12-1,0),0) -> 0.70035567
B13: EBIT margin | D13: =IFERROR(D26/D18,0) -> 0.18489132 | E13: =IFERROR(E26/E18,0) -> 0.16404183 | F13: =IFERROR(F26/F18,0) -> 0.23098993 | G13: =IFERROR(G26/G18,0) -> 0.23494021 | H13: =IFERROR(H26/H18,0) -> 0.038848319 | I13: =IFERROR(I26/I18,0) -> 0.22105361 | J13: =IFERROR(J26/J18,0) -> 1.256247 | K13: =IFERROR(K26/K18,0) -> 0.39569837 | ... O13: =IFERROR(O26/O18,0) -> 0.69068494 | P13: =P26/P18 -> 0.21246499 | Q13: =Q26/Q18 -> 0.35269118 | R13: =R26/R18 -> 0.52638976 | T13: =L13-S13 -> 0.31237906 | U13: =IFERROR(IF(L13<>0,L13/H13-1,0),0) -> 7.040993 | V13: =IFERROR(IF(M13<>0,M13/I13-1,0),0) -> 1.2089478 | W13: =IFERROR(IF(N13<>0,N13/J13-1,0),0) -> -0.78825033 | X13: =IFERROR(IF(O13<>0,O13/K13-1,0),0) -> 0.74548342
B14: Net income profit margin | D14: =IFERROR(D32/D18,0) -> 0.073557385 | E14: =IFERROR(E32/E18,0) -> 0.059949701 | F14: =IFERROR(F32/F18,0) -> 0.16668586 | G14: =IFERROR(G32/G18,0) -> 0.19944565 | H14: =IFERROR(H32/H18,0) -> 0.02880198 | I14: =IFERROR(I32/I18,0) -> 0.14436671 | J14: =IFERROR(J32/J18,0) -> 0.96025548 | K14: =IFERROR(K32/K18,0) -> 0.25279771 | ... O14: =IFERROR(O32/O18,0) -> 0.47851992 | P14: =P32/P18 -> 0.14339411 | Q14: =Q32/Q18 -> 0.24158241 | R14: =R32/R18 -> 0.33157033 | T14: =L14-S14 -> 0.23072887 | U14: =IFERROR(IF(L14<>0,L14/H14-1,0),0) -> 7.0108684 | V14: =IFERROR(IF(M14<>0,M14/I14-1,0),0) -> 0.84487 | W14: =IFERROR(IF(N14<>0,N14/J14-1,0),0) -> -0.98245829 | X14: =IFERROR(IF(O14<>0,O14/K14-1,0),0) -> 0.89289662
B16: Units: Billion VND | D16: =year - 2 -> 2023 | H16: =year-1 -> 2024 | L16: =year -> 2025 | P16: =P8 -> 2023 | Q16: =Q8 -> 2024 | R16: =R8 -> 2025 | S16: Reality Check | U16: Year over Year Performance
B17: P & L (QUARTER) | D17: Quarter 1 | E17: Quarter 2 | F17: Quarter 3 | G17: Quarter 4 | H17: Quarter 1 | I17: Quarter 2 | J17: Quarter 3 | K17: Quarter 4 | L17: Quarter 1 | M17: Quarter 2 | N17: Quarter 3 | O17: Quarter 4 | S17: Forecast | T17: % Forecast | U17: Quarter 1 | V17: Quarter 2 | W17: Quarter 3 | X17: Quarter 4
B18: Revenue | D18: ='FS QTR'!D10 -> 34.72555 | E18: ='FS QTR'!E10 -> 94.877759 | F18: ='FS QTR'!F10 -> 152.94242 | G18: ='FS QTR'!G10 -> 120.95726 | H18: ='FS QTR'!H10 -> 48.773071 | I18: ='FS QTR'!I10 -> 139.05514 | J18: ='FS QTR'!J10 -> 31.324253 | K18: ='FS QTR'!K10 -> 123.43867 | ... O18: ='FS QTR'!O10 -> 238.6932 | P18: =SUM(D18:G18) -> 403.50298 | Q18: =SUM(H18:K18) -> 342.59114 | R18: =SUM(L18:O18) -> 506.18066 | S18: ='P&L'!#REF! -> #REF! | T18: =IFERROR(R18/S18,0) -> 0 | U18: =IF(L18<>0,L18/H18-1,0) -> 0.89427396 | V18: =IF(M18<>0,M18/I18-1,0) -> -0.15405456 | W18: =IF(N18<>0,N18/J18-1,0) -> 0.83451577 | X18: =IF(O18<>0,O18/K18-1,0) -> 0.93369867
B19: - Cost of Goods Sold | D19: ='FS QTR'!D11 -> -3.8214099 | E19: ='FS QTR'!E11 -> -46.378936 | F19: ='FS QTR'!F11 -> -89.321595 | G19: ='FS QTR'!G11 -> -71.096255 | H19: ='FS QTR'!H11 -> -19.581237 | I19: ='FS QTR'!I11 -> -65.363035 | J19: ='FS QTR'!J11 -> -5.5994087 | K19: ='FS QTR'!K11 -> -46.116532 | ... O19: ='FS QTR'!O11 -> -106.95243 | P19: =SUM(D19:G19) -> -210.6182 | Q19: =SUM(H19:K19) -> -136.66021 | R19: =SUM(L19:O19) -> -204.36545 | S19: ='P&L'!#REF! -> #REF! | T19: =IFERROR(R19/S19,0) -> 0 | U19: =IF(L19<>0,L19/H19-1,0) -> 1.1942752 | V19: =IF(M19<>0,M19/I19-1,0) -> -0.47460785 | W19: =IF(N19<>0,N19/J19-1,0) -> 2.590589 | X19: =IF(O19<>0,O19/K19-1,0) -> 1.3191775
B20: Gross profit | D20: ='FS QTR'!D12 -> 30.904141 | E20: ='FS QTR'!E12 -> 48.498823 | F20: ='FS QTR'!F12 -> 63.620821 | G20: ='FS QTR'!G12 -> 49.861004 | H20: ='FS QTR'!H12 -> 29.191834 | I20: ='FS QTR'!I12 -> 73.692108 | J20: ='FS QTR'!J12 -> 25.724845 | K20: ='FS QTR'!K12 -> 77.322141 | ... O20: ='FS QTR'!O12 -> 131.74077 | P20: =SUM(D20:G20) -> 192.88479 | Q20: =SUM(H20:K20) -> 205.93093 | R20: =SUM(L20:O20) -> 301.81521 | S20: ='P&L'!#REF! -> #REF! | T20: =IFERROR(R20/S20,0) -> 0 | U20: =IF(L20<>0,L20/H20-1,0) -> 0.69303975 | V20: =IF(M20<>0,M20/I20-1,0) -> 0.1302681 | W20: =IF(N20<>0,N20/J20-1,0) -> 0.45227938 | X20: =IF(O20<>0,O20/K20-1,0) -> 0.70379106
B21: - Sales/Marketing/Advertising Expenses | D21: ='FS QTR'!D13 -> -6.7188995 | E21: ='FS QTR'!E13 -> -13.199601 | F21: ='FS QTR'!F13 -> -11.821989 | G21: ='FS QTR'!G13 -> -12.305236 | H21: ='FS QTR'!H13 -> -11.643514 | I21: ='FS QTR'!I13 -> -26.212991 | J21: ='FS QTR'!J13 -> -10.077196 | K21: ='FS QTR'!K13 -> -14.560108 | ... O21: ='FS QTR'!O13 -> -24.579358 | P21: =SUM(D21:G21) -> -44.045725 | Q21: =SUM(H21:K21) -> -62.493809 | R21: =SUM(L21:O21) -> -54.30247 | S21: ='P&L'!#REF! -> #REF! | T21: =IFERROR(R21/S21,0) -> 0 | U21: =IF(L21<>0,L21/H21-1,0) -> -0.41352596 | V21: =IF(M21<>0,M21/I21-1,0) -> -0.52327122 | W21: =IF(N21<>0,N21/J21-1,0) -> 0.031835224 | X21: =IF(O21<>0,O21/K21-1,0) -> 0.68813016
B22: - General and Administrative Expenses | D22: ='FS QTR'!D14 -> -19.31928 | E22: ='FS QTR'!E14 -> -19.337477 | F22: ='FS QTR'!F14 -> -18.828244 | G22: ='FS QTR'!G14 -> -21.186238 | H22: ='FS QTR'!H14 -> -17.635771 | I22: ='FS QTR'!I14 -> -18.224652 | J22: ='FS QTR'!J14 -> -20.00184 | K22: ='FS QTR'!K14 -> -25.383783 | ... O22: ='FS QTR'!O14 -> -30.561187 | P22: =SUM(D22:G22) -> -78.67124 | Q22: =SUM(H22:K22) -> -81.246045 | R22: =SUM(L22:O22) -> -82.327577 | S22: ='P&L'!#REF! -> #REF! | T22: =IFERROR(R22/S22,0) -> 0 | U22: =IF(L22<>0,L22/H22-1,0) -> -0.14547503 | V22: =IF(M22<>0,M22/I22-1,0) -> 0.043732971 | W22: =IF(N22<>0,N22/J22-1,0) -> -0.11635564 | X22: =IF(O22<>0,O22/K22-1,0) -> 0.20396504
B23: Operating profit | D23: ='FS QTR'!D15 -> 4.8659608 | E23: ='FS QTR'!E15 -> 15.961745 | F23: ='FS QTR'!F15 -> 32.970587 | G23: ='FS QTR'!G15 -> 16.36953 | H23: ='FS QTR'!H15 -> -0.0874506 | I23: ='FS QTR'!I15 -> 29.254465 | J23: ='FS QTR'!J15 -> -4.3541914 | K23: ='FS QTR'!K15 -> 37.37825 | ... O23: ='FS QTR'!O15 -> 76.600228 | P23: =SUM(D23:G23) -> 70.167824 | Q23: =SUM(H23:K23) -> 62.191073 | R23: =SUM(L23:O23) -> 165.18516 | S23: ='P&L'!#REF! -> #REF! | T23: =IFERROR(R23/S23,0) -> 0 | U23: =IF(L23<>0,L23/H23-1,0) -> -315.73895 | V23: =IF(M23<>0,M23/I23-1,0) -> 0.76977025 | W23: =IF(N23<>0,N23/J23-1,0) -> -3.1329202 | X23: =IF(O23<>0,O23/K23-1,0) -> 1.0493262
B24: - Foreign Exchange (Losses) Gains | D24: ='FS QTR'!D16 -> 0 | E24: ='FS QTR'!E16 -> 0 | F24: ='FS QTR'!F16 -> 0 | G24: ='FS QTR'!G16 -> 0 | H24: ='FS QTR'!H16 -> 0 | I24: ='FS QTR'!I16 -> 0 | J24: ='FS QTR'!J16 -> 0 | K24: ='FS QTR'!K16 -> 0 | ... O24: ='FS QTR'!O16 -> 0 | P24: =SUM(D24:G24) -> 0 | Q24: =SUM(H24:K24) -> 0 | R24: =SUM(L24:O24) -> 0 | S24: ='P&L'!#REF! -> #REF! | T24: =IFERROR(R24/S24,0) -> 0 | U24: =IF(L24<>0,L24/H24-1,0) -> 0 | V24: =IF(M24<>0,M24/I24-1,0) -> 0 | W24: =IF(N24<>0,N24/J24-1,0) -> 0 | X24: =IF(O24<>0,O24/K24-1,0) -> 0
B25: - Non-Operating (Losses) Gains | D25: ='FS QTR'!D17 -> 1.554492 | E25: ='FS QTR'!E17 -> -0.3978238 | F25: ='FS QTR'!F17 -> 2.3575704 | G25: ='FS QTR'!G17 -> 12.048193 | H25: ='FS QTR'!H17 -> 1.9822024 | I25: ='FS QTR'!I17 -> 1.4841765 | J25: ='FS QTR'!J17 -> 43.70519 | K25: ='FS QTR'!K17 -> 11.466231 | ... O25: ='FS QTR'!O17 -> 88.26157 | P25: =SUM(D25:G25) -> 15.562432 | Q25: =SUM(H25:K25) -> 58.6378 | R25: =SUM(L25:O25) -> 101.26315 | S25: ='P&L'!#REF! -> #REF! | T25: =IFERROR(R25/S25,0) -> 0 | U25: =IF(L25<>0,L25/H25-1,0) -> -0.32577354 | V25: =IF(M25<>0,M25/I25-1,0) -> 2.8176455 | W25: =IF(N25<>0,N25/J25-1,0) -> -0.86273778 | X25: =IF(O25<>0,O25/K25-1,0) -> 6.697522
B26: EBIT | D26: ='FS QTR'!D18 -> 6.4204528 | E26: ='FS QTR'!E18 -> 15.563921 | F26: ='FS QTR'!F18 -> 35.328158 | G26: ='FS QTR'!G18 -> 28.417724 | H26: ='FS QTR'!H18 -> 1.8947518 | I26: ='FS QTR'!I18 -> 30.738641 | J26: ='FS QTR'!J18 -> 39.350998 | K26: ='FS QTR'!K18 -> 48.844482 | ... O26: ='FS QTR'!O18 -> 164.8618 | P26: =SUM(D26:G26) -> 85.730256 | Q26: =SUM(H26:K26) -> 120.82887 | R26: =SUM(L26:O26) -> 266.44832 | S26: ='P&L'!#REF! -> #REF! | T26: =IFERROR(R26/S26,0) -> 0 | U26: =IF(L26<>0,L26/H26-1,0) -> 14.231844 | V26: =IF(M26<>0,M26/I26-1,0) -> 0.86864932 | W26: =IF(N26<>0,N26/J26-1,0) -> -0.6115419 | X26: =IF(O26<>0,O26/K26-1,0) -> 2.375239
B27: - Interest Expense [link from Debt Sweep] | D27: ='FS QTR'!D19 -> -3.709756 | E27: ='FS QTR'!E19 -> -1.7768341 | F27: ='FS QTR'!F19 -> -1.0733554 | G27: ='FS QTR'!G19 -> -0.0565102 | H27: ='FS QTR'!H19 -> -0.0455231 | I27: ='FS QTR'!I19 -> -0.0551752 | J27: ='FS QTR'!J19 -> -0.0322711 | K27: ='FS QTR'!K19 -> -0.2098597 | ... O27: ='FS QTR'!O19 -> -0.0246881 | P27: =SUM(D27:G27) -> -6.6164557 | Q27: =SUM(H27:K27) -> -0.3428291 | R27: =SUM(L27:O27) -> -0.0792908 | S27: ='P&L'!#REF! -> #REF! | T27: =IFERROR(R27/S27,0) -> 0 | U27: =IF(L27<>0,L27/H27-1,0) -> -0.26171987 | V27: =IF(M27<>0,M27/I27-1,0) -> -0.79890603 | W27: =IF(N27<>0,N27/J27-1,0) -> -0.69327045 | X27: =IF(O27<>0,O27/K27-1,0) -> -0.88235902
B28: EBT | D28: ='FS QTR'!D20 -> 2.7106968 | E28: ='FS QTR'!E20 -> 13.787087 | F28: ='FS QTR'!F20 -> 34.254802 | G28: ='FS QTR'!G20 -> 28.361213 | H28: ='FS QTR'!H20 -> 1.8492287 | I28: ='FS QTR'!I20 -> 30.683466 | J28: ='FS QTR'!J20 -> 39.318727 | K28: ='FS QTR'!K20 -> 48.634622 | ... O28: ='FS QTR'!O20 -> 164.83711 | P28: =SUM(D28:G28) -> 79.1138 | Q28: =SUM(H28:K28) -> 120.48604 | R28: =SUM(L28:O28) -> 266.36903 | S28: ='P&L'!#REF! -> #REF! | T28: =IFERROR(R28/S28,0) -> 0 | U28: =IF(L28<>0,L28/H28-1,0) -> 14.588637 | V28: =IF(M28<>0,M28/I28-1,0) -> 0.87164793 | W28: =IF(N28<>0,N28/J28-1,0) -> -0.61147482 | X28: =IF(O28<>0,O28/K28-1,0) -> 2.3892956
B29: - Income Tax Expense | D29: ='FS QTR'!D21 -> -4.0322641 | E29: ='FS QTR'!E21 -> -4.4655487 | F29: ='FS QTR'!F21 -> -7.0392748 | G29: ='FS QTR'!G21 -> -4.481864 | H29: ='FS QTR'!H21 -> -1.939814 | I29: ='FS QTR'!I21 -> -10.032337 | J29: ='FS QTR'!J21 -> -9.4907923 | K29: ='FS QTR'!K21 -> -9.2932007 | ... O29: ='FS QTR'!O21 -> -29.52315 | P29: =SUM(D29:G29) -> -20.018952 | Q29: =SUM(H29:K29) -> -30.756144 | R29: =SUM(L29:O29) -> -53.321005 | S29: ='P&L'!#REF! -> #REF! | T29: =IFERROR(R29/S29,0) -> 0 | U29: =IF(L29<>0,L29/H29-1,0) -> 2.4283197 | V29: =IF(M29<>0,M29/I29-1,0) -> 0.26216982 | W29: =IF(N29<>0,N29/J29-1,0) -> -0.52743247 | X29: =IF(O29<>0,O29/K29-1,0) -> 2.1768548
... B36: Outstanding shares (million shares) | D36: ='FS QTR'!D28 -> 32 | E36: ='FS QTR'!E28 -> 32 | F36: ='FS QTR'!F28 -> 32 | G36: ='FS QTR'!G28 -> 37 | H36: ='FS QTR'!H28 -> 42 | I36: ='FS QTR'!I28 -> 47.249841 | J36: ='FS QTR'!J28 -> 52.649681 | K36: ='FS QTR'!K28 -> 52.799681 | ... O36: ='FS QTR'!O28 -> 75 | P36: =SUM(D36:G36) -> 133 | Q36: =SUM(H36:K36) -> 194.6992 | R36: =SUM(L36:O36) -> 288.89984 | S36: ='P&L'!#REF! -> #REF! | T36: =IFERROR(R36/S36,0) -> 0 | U36: =IF(L36<>0,L36/H36-1,0) -> 0.52142477 | V36: =IF(M36<>0,M36/I36-1,0) -> 0.58730695 | W36: =IF(N36<>0,N36/J36-1,0) -> 0.42451006 | X36: =IF(O36<>0,O36/K36-1,0) -> 0.42046313
B38: BALANCE SHEET
B39: Assets
B40: + Cash & Near Cash Items | D40: ='FS QTR'!D31 -> 53.75065 | E40: ='FS QTR'!E31 -> 55.688726 | F40: ='FS QTR'!F31 -> 68.524952 | G40: ='FS QTR'!G31 -> 136.05265 | H40: ='FS QTR'!H31 -> 110.70893 | I40: ='FS QTR'!I31 -> 120.15917 | J40: ='FS QTR'!J31 -> 59.468312 | K40: ='FS QTR'!K31 -> 72.88629 | ... O40: ='FS QTR'!O31 -> 776.33899
B41: + Short-Term Investments | D41: ='FS QTR'!D32 -> 0 | E41: ='FS QTR'!E32 -> 0 | F41: ='FS QTR'!F32 -> 0 | G41: ='FS QTR'!G32 -> 0 | H41: ='FS QTR'!H32 -> 0 | I41: ='FS QTR'!I32 -> 0 | J41: ='FS QTR'!J32 -> 2.5 | K41: ='FS QTR'!K32 -> 0 | ... O41: ='FS QTR'!O32 -> 0
B42: + Accounts & Notes Receivable | D42: ='FS QTR'!D33 -> 65.074779 | E42: ='FS QTR'!E33 -> 90.663914 | F42: ='FS QTR'!F33 -> 110.7758 | G42: ='FS QTR'!G33 -> 125.80868 | H42: ='FS QTR'!H33 -> 95.291498 | I42: ='FS QTR'!I33 -> 130.27006 | J42: ='FS QTR'!J33 -> 111.40446 | K42: ='FS QTR'!K33 -> 131.2453 | ... O42: ='FS QTR'!O33 -> 119.20113
B43: + Inventories | D43: ='FS QTR'!D34 -> 96.877542 | E43: ='FS QTR'!E34 -> 243.3597 | F43: ='FS QTR'!F34 -> 168.31693 | G43: ='FS QTR'!G34 -> 129.20743 | H43: ='FS QTR'!H34 -> 327.79213 | I43: ='FS QTR'!I34 -> 288.10147 | J43: ='FS QTR'!J34 -> 296.15528 | K43: ='FS QTR'!K34 -> 432.78726 | ... O43: ='FS QTR'!O34 -> 499.21431
B44: + Other Current Assets | D44: ='FS QTR'!D35 -> 276.79123 | E44: ='FS QTR'!E35 -> 184.18461 | F44: ='FS QTR'!F35 -> 190.94864 | G44: ='FS QTR'!G35 -> 189.55619 | H44: ='FS QTR'!H35 -> 236.16121 | I44: ='FS QTR'!I35 -> 141.25336 | J44: ='FS QTR'!J35 -> 322.65622 | K44: ='FS QTR'!K35 -> 297.11363 | ... O44: ='FS QTR'!O35 -> 284.11639
B45: Total Current Assets | D45: ='FS QTR'!D36 -> 492.49421 | E45: ='FS QTR'!E36 -> 573.89695 | F45: ='FS QTR'!F36 -> 538.56633 | G45: ='FS QTR'!G36 -> 580.62496 | H45: ='FS QTR'!H36 -> 769.95377 | I45: ='FS QTR'!I36 -> 679.78406 | J45: ='FS QTR'!J36 -> 792.18427 | K45: ='FS QTR'!K36 -> 934.03248 | ... O45: ='FS QTR'!O36 -> 1678.8708
B46: + Gross Fixed Assets | D46: ='FS QTR'!D37 -> 45.365042 | E46: ='FS QTR'!E37 -> 46.600329 | F46: ='FS QTR'!F37 -> 46.602027 | G46: ='FS QTR'!G37 -> 46.413282 | H46: ='FS QTR'!H37 -> 46.368975 | I46: ='FS QTR'!I37 -> 45.064213 | J46: ='FS QTR'!J37 -> 46.540188 | K46: ='FS QTR'!K37 -> 44.852805 | ... O46: ='FS QTR'!O37 -> 42.124221
B47: - Accumulated Depreciation | D47: ='FS QTR'!D38 -> 6.445137 | E47: ='FS QTR'!E38 -> 7.4057501 | F47: ='FS QTR'!F38 -> 8.1760738 | G47: ='FS QTR'!G38 -> 8.9248649 | H47: ='FS QTR'!H38 -> 9.7054133 | I47: ='FS QTR'!I38 -> 9.6580492 | J47: ='FS QTR'!J38 -> 10.63883 | K47: ='FS QTR'!K38 -> 9.2843747 | ... O47: ='FS QTR'!O38 -> 9.8412946
B48: + Net Fixed Assets | D48: ='FS QTR'!D39 -> 38.919905 | E48: ='FS QTR'!E39 -> 39.194579 | F48: ='FS QTR'!F39 -> 38.425953 | G48: ='FS QTR'!G39 -> 37.488417 | H48: ='FS QTR'!H39 -> 36.663561 | I48: ='FS QTR'!I39 -> 35.406164 | J48: ='FS QTR'!J39 -> 35.901358 | K48: ='FS QTR'!K39 -> 35.56843 | ... O48: ='FS QTR'!O39 -> 32.282926
B49: + Long-Term Investments | D49: ='FS QTR'!D40 -> 180.27082 | E49: ='FS QTR'!E40 -> 151.31676 | F49: ='FS QTR'!F40 -> 179.72626 | G49: ='FS QTR'!G40 -> 110.14465 | H49: ='FS QTR'!H40 -> 110.14465 | I49: ='FS QTR'!I40 -> 155.69259 | J49: ='FS QTR'!J40 -> 110.25802 | K49: ='FS QTR'!K40 -> 110.14465 | ... O49: ='FS QTR'!O40 -> 0
B50: + Other Long-Term Assets | D50: ='FS QTR'!D41 -> 82.844039 | E50: ='FS QTR'!E41 -> 109.54275 | F50: ='FS QTR'!F41 -> 87.667519 | G50: ='FS QTR'!G41 -> 88.194154 | H50: ='FS QTR'!H41 -> 87.027956 | I50: ='FS QTR'!I41 -> 167.85271 | J50: ='FS QTR'!J41 -> 176.44258 | K50: ='FS QTR'!K41 -> 188.4695 | ... O50: ='FS QTR'!O41 -> 449.29909
B51: Total Long-Term Assets | D51: ='FS QTR'!D42 -> 302.03477 | E51: ='FS QTR'!E42 -> 300.0541 | F51: ='FS QTR'!F42 -> 305.81974 | G51: ='FS QTR'!G42 -> 235.82722 | H51: ='FS QTR'!H42 -> 233.83617 | I51: ='FS QTR'!I42 -> 358.95147 | J51: ='FS QTR'!J42 -> 322.60196 | K51: ='FS QTR'!K42 -> 334.18258 | ... O51: ='FS QTR'!O42 -> 481.58202
B52: Total Assets | D52: ='FS QTR'!D43 -> 794.52897 | E52: ='FS QTR'!E43 -> 873.95104 | F52: ='FS QTR'!F43 -> 844.38607 | G52: ='FS QTR'!G43 -> 816.45218 | H52: ='FS QTR'!H43 -> 1003.7899 | I52: ='FS QTR'!I43 -> 1038.7355 | J52: ='FS QTR'!J43 -> 1114.7862 | K52: ='FS QTR'!K43 -> 1268.2151 | ... O52: ='FS QTR'!O43 -> 2160.4528
B54: Liabilities & Stockholders' Equity
B55: + Accounts Payable | D55: ='FS QTR'!D46 -> 4.5999854 | E55: ='FS QTR'!E46 -> 22.244769 | F55: ='FS QTR'!F46 -> 27.617793 | G55: ='FS QTR'!G46 -> 35.76286 | H55: ='FS QTR'!H46 -> 26.918734 | I55: ='FS QTR'!I46 -> 22.456059 | J55: ='FS QTR'!J46 -> 15.647813 | K55: ='FS QTR'!K46 -> 21.303074 | ... O55: ='FS QTR'!O46 -> 55.022482
B56: + Short-term debt | D56: ='FS QTR'!D47 -> 71.95 | E56: ='FS QTR'!E47 -> 24.95 | F56: ='FS QTR'!F47 -> 24.95 | G56: ='FS QTR'!G47 -> 0.45 | H56: ='FS QTR'!H47 -> 1.18 | I56: ='FS QTR'!I47 -> 0.25 | J56: ='FS QTR'!J47 -> 0.25 | K56: ='FS QTR'!K47 -> 0 | ... O56: ='FS QTR'!O47 -> 1
B57: + Other short-term liabilities | D57: ='FS QTR'!D48 -> 251.82917 | E57: ='FS QTR'!E48 -> 352.34944 | F57: ='FS QTR'!F48 -> 290.1422 | G57: ='FS QTR'!G48 -> 196.74578 | H57: ='FS QTR'!H48 -> 395.07431 | I57: ='FS QTR'!I48 -> 413.6619 | J57: ='FS QTR'!J48 -> 464.62247 | K57: ='FS QTR'!K48 -> 509.92335 | ... O57: ='FS QTR'!O48 -> 909.34067
B58: Total Current Liabilities | D58: ='FS QTR'!D49 -> 328.37915 | E58: ='FS QTR'!E49 -> 399.54421 | F58: ='FS QTR'!F49 -> 342.70999 | G58: ='FS QTR'!G49 -> 232.95864 | H58: ='FS QTR'!H49 -> 423.17305 | I58: ='FS QTR'!I49 -> 436.36796 | J58: ='FS QTR'!J49 -> 480.52029 | K58: ='FS QTR'!K49 -> 531.22642 | ... O58: ='FS QTR'!O49 -> 965.36315
B59: + Long-term debt | D59: ='FS QTR'!D50 -> 12.088176 | E59: ='FS QTR'!E50 -> 12.061536 | F59: ='FS QTR'!F50 -> 12.034896 | G59: ='FS QTR'!G50 -> 0.11576 | H59: ='FS QTR'!H50 -> 0.08912 | I59: ='FS QTR'!I50 -> 0.06248 | J59: ='FS QTR'!J50 -> 0.35 | K59: ='FS QTR'!K50 -> 69.714 | ... O59: ='FS QTR'!O50 -> 119.10941
B60: + Other long-term liabilities | D60: ='FS QTR'!D51 -> 3.2471992 | E60: ='FS QTR'!E51 -> 3.2308047 | F60: ='FS QTR'!F51 -> 3.2621644 | G60: ='FS QTR'!G51 -> 3.7836345 | H60: ='FS QTR'!H51 -> 3.7951907 | I60: ='FS QTR'!I51 -> 3.6967469 | J60: ='FS QTR'!J51 -> 3.6783032 | K60: ='FS QTR'!K51 -> 3.6598596 | ... O60: ='FS QTR'!O51 -> 3.752779
B61: Total long-term liabilities | D61: ='FS QTR'!D52 -> 15.335375 | E61: ='FS QTR'!E52 -> 15.292341 | F61: ='FS QTR'!F52 -> 15.29706 | G61: ='FS QTR'!G52 -> 3.8993945 | H61: ='FS QTR'!H52 -> 3.8843107 | I61: ='FS QTR'!I52 -> 3.7592269 | J61: ='FS QTR'!J52 -> 4.0283032 | K61: ='FS QTR'!K52 -> 73.37386 | ... O61: ='FS QTR'!O52 -> 122.86219
B62: Total Liabilities | D62: ='FS QTR'!D53 -> 343.71453 | E62: ='FS QTR'!E53 -> 414.83655 | F62: ='FS QTR'!F53 -> 358.00705 | G62: ='FS QTR'!G53 -> 236.85803 | H62: ='FS QTR'!H53 -> 427.05736 | I62: ='FS QTR'!I53 -> 440.12719 | J62: ='FS QTR'!J53 -> 484.54859 | K62: ='FS QTR'!K53 -> 604.60028 | ... O62: ='FS QTR'!O53 -> 1088.2253
B63: + Total Preferred Equity | D63: ='FS QTR'!D54 -> 0 | E63: ='FS QTR'!E54 -> 0 | F63: ='FS QTR'!F54 -> 0 | G63: ='FS QTR'!G54 -> 0 | H63: ='FS QTR'!H54 -> 0 | I63: ='FS QTR'!I54 -> 0 | J63: ='FS QTR'!J54 -> 0 | K63: ='FS QTR'!K54 -> 0 | ... O63: ='FS QTR'!O54 -> 0
B64: + Additional paid in capital | D64: ='FS QTR'!D55 -> 32.185271 | E64: ='FS QTR'!E55 -> 32.185271 | F64: ='FS QTR'!F55 -> 32.185271 | G64: ='FS QTR'!G55 -> 31.980271 | H64: ='FS QTR'!H55 -> 31.980271 | I64: ='FS QTR'!I55 -> 10.982381 | J64: ='FS QTR'!J55 -> 10.982381 | K64: ='FS QTR'!K55 -> 10.982381 | ... O64: ='FS QTR'!O55 -> 10.867981
B65: + Share Capital | D65: ='FS QTR'!D56 -> 320 | E65: ='FS QTR'!E56 -> 320 | F65: ='FS QTR'!F56 -> 320 | G65: ='FS QTR'!G56 -> 420 | H65: ='FS QTR'!H56 -> 420 | I65: ='FS QTR'!I56 -> 524.99681 | J65: ='FS QTR'!J56 -> 527.99681 | K65: ='FS QTR'!K56 -> 527.99681 | ... O65: ='FS QTR'!O56 -> 750
B66: + Retained Earnings & Other Equity | D66: ='FS QTR'!D57 -> 49.229183 | E66: ='FS QTR'!E57 -> 54.917076 | F66: ='FS QTR'!F57 -> 80.410414 | G66: ='FS QTR'!G57 -> 103.75583 | H66: ='FS QTR'!H57 -> 102.32484 | I66: ='FS QTR'!I57 -> 38.400855 | J66: ='FS QTR'!J57 -> 65.480141 | K66: ='FS QTR'!K57 -> 94.153804 | ... O66: ='FS QTR'!O57 -> 241.89213
... B69: Total Liabilities & Equity | D69: ='FS QTR'!D60 -> 794.52897 | E69: ='FS QTR'!E60 -> 873.95104 | F69: ='FS QTR'!F60 -> 844.38607 | G69: ='FS QTR'!G60 -> 816.45218 | H69: ='FS QTR'!H60 -> 1003.7899 | I69: ='FS QTR'!I60 -> 1038.7355 | J69: ='FS QTR'!J60 -> 1114.7862 | K69: ='FS QTR'!K60 -> 1268.2151 | ... O69: ='FS QTR'!O60 -> 2160.4528
B71: CASH FLOW STATEMENT
B72: Beginning cash | D72: ='FS QTR'!D64 -> 0 | E72: ='FS QTR'!E64 -> 53.75065 | F72: ='FS QTR'!F64 -> 55.688726 | G72: ='FS QTR'!G64 -> 68.524952 | H72: ='FS QTR'!H64 -> 136.05265 | I72: ='FS QTR'!I64 -> 110.70893 | J72: ='FS QTR'!J64 -> 120.15917 | K72: ='FS QTR'!K64 -> 59.468312 | ... O72: ='FS QTR'!O64 -> 373.82149
B73: + Net Income | D73: ='FS QTR'!D65 -> 2.5543208 | E73: ='FS QTR'!E65 -> 5.6878931 | F73: ='FS QTR'!F65 -> 25.493338 | G73: ='FS QTR'!G65 -> 24.124399 | H73: ='FS QTR'!H65 -> 1.4047609 | I73: ='FS QTR'!I65 -> 20.074934 | J73: ='FS QTR'!J65 -> 30.079286 | K73: ='FS QTR'!K65 -> 31.205013 | ... O73: ='FS QTR'!O65 -> 114.21945
B74: + Depreciation & Amortization | D74: ='FS QTR'!D66 -> 0.9597071 | E74: ='FS QTR'!E66 -> 0.7043371 | F74: ='FS QTR'!F66 -> 0.7853574 | G74: ='FS QTR'!G66 -> 1.6653115 | H74: ='FS QTR'!H66 -> 1.0149951 | I74: ='FS QTR'!I66 -> 0.9478054 | J74: ='FS QTR'!J66 -> 0.8813634 | K74: ='FS QTR'!K66 -> 0.6953571 | ... O74: ='FS QTR'!O66 -> 0.8382924
B75: + Other Non-Cash Adjustments | D75: ='FS QTR'!D67 -> -6.5866421 | E75: ='FS QTR'!E67 -> 11.088254 | F75: ='FS QTR'!F67 -> -38.79726 | G75: ='FS QTR'!G67 -> -4.0608151 | H75: ='FS QTR'!H67 -> -7.951832 | I75: ='FS QTR'!I67 -> -0.4424351 | J75: ='FS QTR'!J67 -> -133.43557 | K75: ='FS QTR'!K67 -> 100.66317 | ... O75: ='FS QTR'!O67 -> -257.96647
B76: + Changes in Non-Cash Capital | D76: ='FS QTR'!D68 -> -2.6137703 | E76: ='FS QTR'!E68 -> 34.196132 | F76: ='FS QTR'!F68 -> 26.203231 | G76: ='FS QTR'!G68 -> 33.913307 | H76: ='FS QTR'!H68 -> -20.369786 | I76: ='FS QTR'!I68 -> 78.666343 | J76: ='FS QTR'!J68 -> -78.86143 | K76: ='FS QTR'!K68 -> -105.46869 | ... O76: ='FS QTR'!O68 -> 382.41334
B77: Cash From Operating Activities | D77: ='FS QTR'!D69 -> -5.6863844 | E77: ='FS QTR'!E69 -> 51.676616 | F77: ='FS QTR'!F69 -> 13.684666 | G77: ='FS QTR'!G69 -> 55.642203 | H77: ='FS QTR'!H69 -> -25.901862 | I77: ='FS QTR'!I69 -> 99.246647 | J77: ='FS QTR'!J69 -> -181.33636 | K77: ='FS QTR'!K69 -> 27.094852 | ... O77: ='FS QTR'!O69 -> 239.50461
B78: + Disposal of Fixed Assets | D78: ='FS QTR'!D70 -> 0 | E78: ='FS QTR'!E70 -> 0.0145455 | F78: ='FS QTR'!F70 -> 0 | G78: ='FS QTR'!G70 -> 0.003 | H78: ='FS QTR'!H70 -> 0 | I78: ='FS QTR'!I70 -> 0.1841546 | J78: ='FS QTR'!J70 -> 0 | K78: ='FS QTR'!K70 -> 0.4848182 | ... O78: ='FS QTR'!O70 -> 0
B79: + Capital Expenditures | D79: ='FS QTR'!D71 -> -0.0360727 | E79: ='FS QTR'!E71 -> -1.4208486 | F79: ='FS QTR'!F71 -> -0.1289487 | G79: ='FS QTR'!G71 -> -1.1974727 | H79: ='FS QTR'!H71 -> -0.1452265 | I79: ='FS QTR'!I71 -> -0.581018 | J79: ='FS QTR'!J71 -> -0.133 | K79: ='FS QTR'!K71 -> -1.6246152 | ... O79: ='FS QTR'!O71 -> -1.8175199
B80: + Increase in Investments | D80: ='FS QTR'!D72 -> 0 | E80: ='FS QTR'!E72 -> 0 | F80: ='FS QTR'!F72 -> 0 | G80: ='FS QTR'!G72 -> 0 | H80: ='FS QTR'!H72 -> 0 | I80: ='FS QTR'!I72 -> 0 | J80: ='FS QTR'!J72 -> 0 | K80: ='FS QTR'!K72 -> 0 | ... O80: ='FS QTR'!O72 -> 0
B81: + Decrease in Investments | D81: ='FS QTR'!D73 -> 0 | E81: ='FS QTR'!E73 -> 0 | F81: ='FS QTR'!F73 -> 0 | G81: ='FS QTR'!G73 -> 0 | H81: ='FS QTR'!H73 -> 0 | I81: ='FS QTR'!I73 -> 0 | J81: ='FS QTR'!J73 -> 0 | K81: ='FS QTR'!K73 -> 0 | ... O81: ='FS QTR'!O73 -> 0
B82: + Other Investing Activities | D82: ='FS QTR'!D74 -> -6.3786455 | E82: ='FS QTR'!E74 -> -0.178816 | F82: ='FS QTR'!F74 -> -0.3282315 | G82: ='FS QTR'!G74 -> -36.218216 | H82: ='FS QTR'!H74 -> 0 | I82: ='FS QTR'!I74 -> -92.682241 | J82: ='FS QTR'!J74 -> 122.75136 | K82: ='FS QTR'!K74 -> -195.71519 | ... O82: ='FS QTR'!O74 -> 115.91935
B83: Cash From Investing Activities | D83: ='FS QTR'!D75 -> -6.4147182 | E83: ='FS QTR'!E75 -> -1.5851191 | F83: ='FS QTR'!F75 -> -0.4571802 | G83: ='FS QTR'!G75 -> -37.412689 | H83: ='FS QTR'!H75 -> -0.1452265 | I83: ='FS QTR'!I75 -> -93.079104 | J83: ='FS QTR'!J75 -> 122.61836 | K83: ='FS QTR'!K75 -> -196.85498 | ... O83: ='FS QTR'!O75 -> 114.10183
... B93: Ending cash | D93: ='FS QTR'!D85 -> -53.61115 | E93: ='FS QTR'!E85 -> 55.688726 | F93: ='FS QTR'!F85 -> 68.524952 | G93: ='FS QTR'!G85 -> 136.05265 | H93: ='FS QTR'!H85 -> 110.70893 | I93: ='FS QTR'!I85 -> 120.15917 | J93: ='FS QTR'!J85 -> 55.748664 | K93: ='FS QTR'!K85 -> 76.605938 | ... O93: ='FS QTR'!O85 -> 776.33899

Sheet Price
B7: =ticker -> DXG VN EQUITY
B9: Start Date | C9: =TODAY() -> 45874 | G9: 3M | H9: 6M | I9: 12M
B10: End Date | C10: =C9-366 -> 45508 | F10: VNIndex | G10: =F382/F351-1 -> 0.035264308 | H10: =F381/F198-1 -> 0.12092732 | I10: =F382/F17-1 -> 0.19239594
F11: =B7 -> DXG VN EQUITY | G11: =C382/C351-1 -> 0.053691275 | H11: =C382/C198-1 -> 0.21705426 | I11: =C382/C17-1 -> 0.75317526
F12: Relative to index | G12: =G11-G10 -> 0.018426968 | H12: =H11-H10 -> 0.096126945 | I12: =I11-I10 -> 0.56077931
C14: PX_LAST | D14: PE_RATIO | E14: PX TO BOOK RATIO | F14: PX_LAST
B15: Date | C15: PRICE | D15: P/E | E15: P/B | F15: INDEX | G15: =LEFT(F11,3) -> DXG | H15: =index -> VNIndex | L15: VOLUIME
B16: =_xll.BDH(ticker,$C$14:$E$14,C10,C9,"Dir=V","Dts=S","Sort=A","Quote=C","QtTyp=Y","Days=A","Per=cd","DtFmt=D","Fill=P","UseDPDF=Y","cols=4;rows=367") -> #NAME? | C16: 9149.86 | D16: 5.5488 | E16: 0.8592 | F16: =_xll.BDH("VNINDEX Index","PX_LAST",C10,C9,"Dir=V","Dts=H","Sort=A","Quote=C","QtTyp=Y","Days=A","Per=cd","DtFmt=D","Fill=P","cols=1;rows=367") -> #NAME? | G16: 472.76 | K16: =_xll.BDH(ticker,"VOLUME",C9-60,C9+1,"Dir=V","Dts=S","Sort=D","Quote=C","QtTyp=Y","Days=T","Per=cd","DtFmt=D","cols=2;rows=45") -> #NAME? | L16: 1708610
B17: 41473 | C17: 8955.18 | D17: 5.4307 | E17: 0.8409 | F17: 496.84 | G17: =C17/C$17-1 -> 0 | H17: =F17/F$17-1 -> 0 | K17: 41837 | L17: 368410
B18: 41474 | C18: 9052.52 | D18: 5.4898 | E18: 0.85 | F18: 503.76 | G18: =C18/C$17-1 -> 0.010869687 | H18: =F18/F$17-1 -> 0.013928025 | K18: 41836 | L18: 1015450
B19: 41475 | C19: 9052.52 | D19: 5.4898 | E19: 0.85 | F19: 503.76 | G19: =C19/C$17-1 -> 0.010869687 | H19: =F19/F$17-1 -> 0.013928025 | K19: 41835 | L19: 466240
B20: 41476 | C20: 9052.52 | D20: 5.4898 | E20: 0.85 | F20: 503.76 | G20: =C20/C$17-1 -> 0.010869687 | H20: =F20/F$17-1 -> 0.013928025 | K20: 41834 | L20: 170860
B21: 41477 | C21: 8857.84 | D21: 5.3717 | E21: 0.8318 | F21: 506.16 | G21: =C21/C$17-1 -> -0.010869687 | H21: =F21/F$17-1 -> 0.018758554 | K21: 41831 | L21: 322430
B22: 41478 | C22: 8565.82 | D22: 5.1946 | E22: 0.8043 | F22: 504.29 | G22: =C22/C$17-1 -> -0.043478746 | H22: =F22/F$17-1 -> 0.014994767 | K22: 41830 | L22: 880210
B23: 41479 | C23: 8663.16 | D23: 5.2536 | E23: 0.8135 | F23: 494.18 | G23: =C23/C$17-1 -> -0.03260906 | H23: =F23/F$17-1 -> -0.0053538362 | K23: 41829 | L23: 901920
B24: 41480 | C24: 8663.16 | D24: 5.2536 | E24: 0.8135 | F24: 491.78 | G24: =C24/C$17-1 -> -0.03260906 | H24: =F24/F$17-1 -> -0.010184365 | K24: 41828 | L24: 522970
B25: 41481 | C25: 8565.82 | D25: 5.1946 | E25: 0.8043 | F25: 493.93 | G25: =C25/C$17-1 -> -0.043478746 | H25: =F25/F$17-1 -> -0.0058570163 | K25: 41827 | L25: 880670
B26: 41482 | C26: 8565.82 | D26: 5.1946 | E26: 0.8043 | F26: 493.93 | G26: =C26/C$17-1 -> -0.043478746 | H26: =F26/F$17-1 -> -0.0058570163 | K26: 41824 | L26: 532630
B27: 41483 | C27: 8565.82 | D27: 5.1946 | E27: 0.8043 | F27: 493.93 | G27: =C27/C$17-1 -> -0.043478746 | H27: =F27/F$17-1 -> -0.0058570163 | K27: 41823 | L27: 1159700
B28: 41484 | C28: 8079.13 | D28: 4.8995 | E28: 0.7586 | F28: 485.69 | G28: =C28/C$17-1 -> -0.097826063 | H28: =F28/F$17-1 -> -0.022441832 | K28: 41822 | L28: 3980520
... B60: 41516 | C60: 7981.79 | D60: 4.8404 | E60: 0.7495 | F60: 472.7 | G60: =C60/C$17-1 -> -0.10869575 | H60: =F60/F$17-1 -> -0.04858707 | K60: 41778 | L60: 326720
B61: 41517 | C61: 7981.79 | D61: 4.8404 | E61: 0.7495 | F61: 472.7 | G61: =C61/C$17-1 -> -0.10869575 | H61: =F61/F$17-1 -> -0.04858707
B62: 41518 | C62: 7981.79 | D62: 4.8404 | E62: 0.7495 | F62: 472.7 | G62: =C62/C$17-1 -> -0.10869575 | H62: =F62/F$17-1 -> -0.04858707
B63: 41519 | C63: 7981.79 | D63: 4.8404 | E63: 0.7495 | F63: 472.7 | G63: =C63/C$17-1 -> -0.10869575 | H63: =F63/F$17-1 -> -0.04858707
B64: 41520 | C64: 7884.45 | D64: 4.7814 | E64: 0.7404 | F64: 472.17 | G64: =C64/C$17-1 -> -0.11956544 | H64: =F64/F$17-1 -> -0.049653812
B65: 41521 | C65: 7689.77 | D65: 4.6633 | E65: 0.7221 | F65: 471.45 | G65: =C65/C$17-1 -> -0.14130481 | H65: =F65/F$17-1 -> -0.051102971
B66: 41522 | C66: 7884.45 | D66: 4.7814 | E66: 0.7404 | F66: 477.57 | G66: =C66/C$17-1 -> -0.11956544 | H66: =F66/F$17-1 -> -0.038785122
B67: 41523 | C67: 7884.45 | D67: 4.7814 | E67: 0.7404 | F67: 480.03 | G67: =C67/C$17-1 -> -0.11956544 | H67: =F67/F$17-1 -> -0.03383383
B68: 41524 | C68: 7884.45 | D68: 4.7814 | E68: 0.7404 | F68: 480.03 | G68: =C68/C$17-1 -> -0.11956544 | H68: =F68/F$17-1 -> -0.03383383
B69: 41525 | C69: 7884.45 | D69: 4.7814 | E69: 0.7404 | F69: 480.03 | G69: =C69/C$17-1 -> -0.11956544 | H69: =F69/F$17-1 -> -0.03383383
B70: 41526 | C70: 7592.43 | D70: 4.6043 | E70: 0.7129 | F70: 470.16 | G70: =C70/C$17-1 -> -0.1521745 | H70: =F70/F$17-1 -> -0.05369938
B71: 41527 | C71: 7884.45 | D71: 4.7814 | E71: 0.7404 | F71: 474.53 | G71: =C71/C$17-1 -> -0.11956544 | H71: =F71/F$17-1 -> -0.044903792
B72: 41528 | C72: 7981.79 | D72: 4.8404 | E72: 0.7495 | F72: 476.4 | G72: =C72/C$17-1 -> -0.10869575 | H72: =F72/F$17-1 -> -0.041140005
... B382: 41838 | C382: 15700 | D382: 7.781 | E382: 1.3564 | F382: 592.43 | G382: =C382/C$17-1 -> 0.75317526 | H382: =F382/F$17-1 -> 0.19239594

Sheet Sales
B7: =ticker -> DXG VN EQUITY
C8: Historical | G8: Year 1 | H8: Year 2 | I8: Year 3 | J8: Year 4 | K8: Year 5 | L8: Year 6 | M8: Year 7 | N8: Year 8 | O8: Year 9 | P8: Year 10
B9: SELLING PRICE AND COGS | C9: ='FS Year'!K9 -> 2020 | D9: ='FS Year'!L9 -> 2021 | E9: =D9+1 -> 2022 | F9: =E9+1 -> 2023 | G9: =F9+1 -> 2024 | H9: =G9+1 -> 2025 | I9: =H9+1 -> 2026 | J9: =I9+1 -> 2027 | K9: =J9+1 -> 2028 | L9: =K9+1 -> 2029 | ... P9: =O9+1 -> 2033
B11: SALES | C11: ='FS Year'!K10 -> 374.25504 | D11: ='FS Year'!L10 -> 286.38626 | E11: ='FS Year'!M10 -> 403.50298 | F11: ='FS Year'!N10 -> 342.59114 | G11: =G12*G13 -> 359.7207 | H11: =H12*H13 -> 377.70673 | I11: =I12*I13 -> 396.59207 | J11: =J12*J13 -> 416.42167 | K11: =K12*K13 -> 437.24276 | L11: =L12*L13 -> 459.10489 | M11: =M12*M13 -> 482.06014 | N11: =N12*N13 -> 506.16315 | ... P11: =P12*P13 -> 558.04487
B12: Volume (unit) | C12: =IF(C11<>0,1,0) -> 1 | D12: =IF(D11<>0,1,0) -> 1 | E12: =IF(E11<>0,1,0) -> 1 | F12: =IF(F11<>0,1,0) -> 1 | G12: =F12*(1+G21) -> 1.05 | H12: =G12*(1+H21) -> 1.1025 | I12: =H12*(1+I21) -> 1.157625 | J12: =I12*(1+J21) -> 1.2155063 | K12: =J12*(1+K21) -> 1.2762816 | L12: =K12*(1+L21) -> 1.3400956 | M12: =L12*(1+M21) -> 1.4071004 | N12: =M12*(1+N21) -> 1.4774554 | ... P12: =O12*(1+P21) -> 1.6288946
B13: Selling price per unit | C13: =IFERROR(C11/C12,0) -> 374.25504 | D13: =IFERROR(D11/D12,0) -> 286.38626 | E13: =IFERROR(E11/E12,0) -> 403.50298 | F13: =IFERROR(F11/F12,0) -> 342.59114 | G13: =F13*(1+G22) -> 342.59114 | H13: =G13*(1+H22) -> 342.59114 | I13: =H13*(1+I22) -> 342.59114 | J13: =I13*(1+J22) -> 342.59114 | K13: =J13*(1+K22) -> 342.59114 | L13: =K13*(1+L22) -> 342.59114 | M13: =L13*(1+M22) -> 342.59114 | N13: =M13*(1+N22) -> 342.59114 | ... P13: =O13*(1+P22) -> 342.59114
B15: COGS | C15: =-'FS Year'!K11 -> 204.97795 | D15: =-'FS Year'!L11 -> 80.303295 | E15: =-'FS Year'!M11 -> 210.6182 | F15: =-'FS Year'!N11 -> 136.66021 | G15: =SUM(G16:G18) -> 136.66021 | H15: =SUM(H16:H18) -> 136.66021 | I15: =SUM(I16:I18) -> 136.66021 | J15: =SUM(J16:J18) -> 136.66021 | K15: =SUM(K16:K18) -> 136.66021 | L15: =SUM(L16:L18) -> 136.66021 | M15: =SUM(M16:M18) -> 136.66021 | N15: =SUM(N16:N18) -> 136.66021 | ... P15: =SUM(P16:P18) -> 136.66021
B16: Raw material | C16: 0 | D16: 0 | E16: 0 | F16: =F15 -> 136.66021 | G16: =F16*(1+G26) -> 136.66021 | H16: =G16*(1+H26) -> 136.66021 | I16: =H16*(1+I26) -> 136.66021 | J16: =I16*(1+J26) -> 136.66021 | K16: =J16*(1+K26) -> 136.66021 | L16: =K16*(1+L26) -> 136.66021 | M16: =L16*(1+M26) -> 136.66021 | N16: =M16*(1+N26) -> 136.66021 | ... P16: =O16*(1+P26) -> 136.66021
B17: Labor | C17: 0 | D17: 0 | E17: 0 | F17: 0 | G17: =F17*(1+G27) -> 0 | H17: =G17*(1+H27) -> 0 | I17: =H17*(1+I27) -> 0 | J17: =I17*(1+J27) -> 0 | K17: =J17*(1+K27) -> 0 | L17: =K17*(1+L27) -> 0 | M17: =L17*(1+M27) -> 0 | N17: =M17*(1+N27) -> 0 | ... P17: =O17*(1+P27) -> 0
B18: Depreciation | C18: 0 | D18: 0 | E18: 0 | F18: 0 | G18: =F18*(1+G28) -> 0 | H18: =G18*(1+H28) -> 0 | I18: =H18*(1+I28) -> 0 | J18: =I18*(1+J28) -> 0 | K18: =J18*(1+K28) -> 0 | L18: =K18*(1+L28) -> 0 | M18: =L18*(1+M28) -> 0 | N18: =M18*(1+M28) -> 0 | O18: =N18*(1+O28) -> 0 | P18: =O18*(1+P28) -> 0
B20: ASSUMPTIONS FOR SALES GROWTH %
B21: Volume growth % | D21: =IFERROR(D12/C12-1,0) -> 0 | E21: =IFERROR(E12/D12-1,0) -> 0 | F21: =IFERROR(F12/E12-1,0) -> 0 | G21: 0.05 | H21: 0.05 | I21: 0.05 | J21: 0.05 | K21: 0.05 | L21: 0.05 | M21: 0.05 | N21: 0.05 | O21: 0.05 | P21: 0.05
B22: Price increase % | D22: =IFERROR(D13/C13-1,0) -> -0.23478315 | E22: =IFERROR(E13/D13-1,0) -> 0.40894671 | F22: =IFERROR(F13/E13-1,0) -> -0.1509576 | G22: 0 | H22: 0 | I22: 0 | J22: 0 | K22: 0 | L22: 0 | M22: 0 | N22: 0 | O22: 0 | P22: 0
B23: Revenue growth % [link to assumptions] | D23: =IFERROR(D11/C11-1,0) -> -0.23478315 | E23: =IFERROR(E11/D11-1,0) -> 0.40894671 | F23: =IFERROR(F11/E11-1,0) -> -0.1509576 | G23: =IF(G11<>0,G11/F11-1,0) -> 0.05 | H23: =IF(H11<>0,H11/G11-1,0) -> 0.05 | I23: =IF(I11<>0,I11/H11-1,0) -> 0.05 | J23: =IF(J11<>0,J11/I11-1,0) -> 0.05 | K23: =IF(K11<>0,K11/J11-1,0) -> 0.05 | L23: =IF(L11<>0,L11/K11-1,0) -> 0.05 | M23: =IF(M11<>0,M11/L11-1,0) -> 0.05 | N23: =IF(N11<>0,N11/M11-1,0) -> 0.05 | ... P23: =IF(P11<>0,P11/O11-1,0) -> 0.05
B25: ASSUMPTIONS FOR GROSS MARGIN %
B26: Raw material cost increase % | C26: 0 | D26: 0 | E26: 0 | F26: 0 | G26: 0 | H26: 0 | I26: 0 | J26: 0 | K26: 0 | L26: 0 | M26: 0 | N26: 0 | O26: 0 | P26: 0
B27: Labor cost increase % | C27: 0 | D27: 0 | E27: 0 | F27: 0 | G27: 0 | H27: 0 | I27: 0 | J27: 0 | K27: 0 | L27: 0 | M27: 0 | N27: 0 | O27: 0 | P27: 0
B28: Depreciation cost increase % | C28: 0 | D28: 0 | E28: 0 | F28: 0 | G28: 0 | H28: 0 | I28: 0 | J28: 0 | K28: 0 | L28: 0 | M28: 0 | N28: 0 | O28: 0 | P28: 0
B29: Raw material as % of sales | C29: 0 | D29: 0 | E29: 0 | F29: 0 | G29: =G16/G11 -> 0.37990645 | H29: =H16/H11 -> 0.36181567 | I29: =I16/I11 -> 0.34458635 | J29: =J16/J11 -> 0.32817747 | K29: =K16/K11 -> 0.31254998 | L29: =L16/L11 -> 0.29766664 | M29: =M16/M11 -> 0.28349204 | N29: =N16/N11 -> 0.26999242 | ... P29: =P16/P11 -> 0.24489108
B30: Labor as % of sales | C30: 0 | D30: 0 | E30: 0 | F30: 0 | G30: =G17/G11 -> 0 | H30: =H17/H11 -> 0 | I30: =I17/I11 -> 0 | J30: =J17/J11 -> 0 | K30: =K17/K11 -> 0 | L30: =L17/L11 -> 0 | M30: =M17/M11 -> 0 | N30: =N17/N11 -> 0 | ... P30: =P17/P11 -> 0
B31: Depreciation as % of sales | C31: 0 | D31: 0 | E31: 0 | F31: 0 | G31: =G18/G11 -> 0 | H31: =H18/H11 -> 0 | I31: =I18/I11 -> 0 | J31: =J18/J11 -> 0 | K31: =K18/K11 -> 0 | L31: =L18/L11 -> 0 | M31: =M18/M11 -> 0 | N31: =N18/N11 -> 0 | ... P31: =P18/P11 -> 0
B32: COGS % of sales | C32: =-'FS Year'!K156 -> 0.54769589 | D32: =-'FS Year'!L156 -> 0.28040205 | E32: =-'FS Year'!M156 -> 0.52197432 | F32: =-'FS Year'!N156 -> 0.39890177 | G32: =SUM(G29:G31) -> 0.37990645 | H32: =SUM(H29:H31) -> 0.36181567 | I32: =SUM(I29:I31) -> 0.34458635 | J32: =SUM(J29:J31) -> 0.32817747 | K32: =SUM(K29:K31) -> 0.31254998 | L32: =SUM(L29:L31) -> 0.29766664 | M32: =SUM(M29:M31) -> 0.28349204 | N32: =SUM(N29:N31) -> 0.26999242 | ... P32: =SUM(P29:P31) -> 0.24489108
B33: Gross margin % [link to assumptions] | C33: ='FS Year'!K108 -> 0.45230411 | D33: ='FS Year'!L108 -> 0.71959795 | E33: ='FS Year'!M108 -> 0.47802568 | F33: ='FS Year'!N108 -> 0.60109823 | G33: =IF(G32<>0,1-G32,0) -> 0.62009355 | H33: =IF(H32<>0,1-H32,0) -> 0.63818433 | I33: =IF(I32<>0,1-I32,0) -> 0.65541365 | J33: =IF(J32<>0,1-J32,0) -> 0.67182253 | K33: =IF(K32<>0,1-K32,0) -> 0.68745002 | L33: =IF(L32<>0,1-L32,0) -> 0.70233336 | M33: =IF(M32<>0,1-M32,0) -> 0.71650796 | N33: =IF(N32<>0,1-N32,0) -> 0.73000758 | ... P33: =IF(P32<>0,1-P32,0) -> 0.75510892
B35: Check | C35: =SUM(C29:C31)-C32 -> -0.54769589 | D35: =SUM(D29:D31)-D32 -> -0.28040205 | E35: =SUM(E29:E31)-E32 -> -0.52197432 | F35: =SUM(F29:F31)-F32 -> -0.39890177 | G35: =SUM(G29:G31)-G32 -> 0 | H35: =SUM(H29:H31)-H32 -> 0 | I35: =SUM(I29:I31)-I32 -> 0 | J35: =SUM(J29:J31)-J32 -> 0 | ... P35: =SUM(P29:P31)-P32 -> 0

Sheet Assumption
B7: =ticker -> DXG VN EQUITY | G7: 1 | H7: 2 | I7: 3 | J7: 4 | K7: 5 | L7: 6 | M7: 7 | N7: 8 | O7: 9 | P7: 10
C8: Historical | G8: Year 1 | H8: Year 2 | I8: Year 3 | J8: Year 4 | K8: Year 5 | L8: Year 6 | M8: Year 7 | N8: Year 8 | O8: Year 9 | P8: Year 10 | R8: Notes
B9: INCOME STATEMENT ASSUMPTIONS | C9: ='FS Year'!K9 -> 2020 | D9: ='FS Year'!L9 -> 2021 | E9: =D9+1 -> 2022 | F9: =E9+1 -> 2023 | G9: =F9+1 -> 2024 | H9: =G9+1 -> 2025 | I9: =H9+1 -> 2026 | J9: =I9+1 -> 2027 | K9: =J9+1 -> 2028 | L9: =K9+1 -> 2029 | ... P9: =O9+1 -> 2033
B10: Revenue CAGR for forecast period | C10: =((1+C11))^(1)-1 -> 3.407698 | D10: =((1+C11)*(1+D11))^(1/2)-1 -> 0.83653064 | E10: =((1+C11)*(1+D11)*(1+E11))^(1/3)-1 -> 0.6812423 | F10: =((1+D11)*(1+E11)*(1+F11))^(1/3)-1 -> -0.029036682 | G10: =((1+G11))^(1/G7)-1 -> 0.05 | H10: =((1+G11)*(1+H11))^(1/H7)-1 -> 0.05 | I10: =((1+G11)*(1+H11)*(1+I11))^(1/I7)-1 -> 0.05 | J10: =((1+G11)*(1+H11)*(1+I11)*(1+J11))^(1/J7)-1 -> 0.05 | K10: =((1+G11)*(1+H11)*(1+I11)*(1+J11)*(1+K11))^(1/K7)-1 -> 0.05 | L10: =((1+G11)*(1+H11)*(1+I11)*(1+J11)*(1+K11)*(1+L11))^(1/L7)-1 -> 0.05 | M10: =((1+G11)*(1+H11)*(1+I11)*(1+J11)*(1+K11)*(1+L11)*(1+M11))^(1/M7)-1 -> 0.05 | N10: =((1+G11)*(1+H11)*(1+I11)*(1+J11)*(1+K11)*(1+L11)*(1+M11)*(1+N11))^(1/N7)-1 -> 0.05 | O10: =((1+G11)*(1+H11)*(1+I11)*(1+J11)*(1+K11)*(1+L11)*(1+M11)*(1+N11)*(1+O11))^(1/O7)-1 -> 0.05 | P10: =((1+G11)*(1+H11)*(1+I11)*(1+J11)*(1+K11)*(1+L11)*(1+M11)*(1+N11)*(1+O11)*(1+P11))^(1/P7)-1 -> 0.05
B11: Revenue growth % [link Sales & COGS] | C11: ='FS Year'!K173 -> 3.407698 | D11: ='FS Year'!L173 -> -0.23478315 | E11: ='FS Year'!M173 -> 0.40894671 | F11: ='FS Year'!N173 -> -0.1509576 | G11: =Sales!G23 -> 0.05 | H11: =Sales!H23 -> 0.05 | I11: =Sales!I23 -> 0.05 | J11: =Sales!J23 -> 0.05 | K11: =Sales!K23 -> 0.05 | L11: =Sales!L23 -> 0.05 | M11: =Sales!M23 -> 0.05 | N11: =Sales!N23 -> 0.05 | ... P11: =Sales!P23 -> 0.05 | R11: Constant; assume no changes
B12: COGS % of sales [link Sales & COGS] | C12: =-'FS Year'!K156 -> 0.54769589 | D12: =-'FS Year'!L156 -> 0.28040205 | E12: =-'FS Year'!M156 -> 0.52197432 | F12: =-'FS Year'!N156 -> 0.39890177 | G12: =Sales!G32 -> 0.37990645 | H12: =Sales!H32 -> 0.36181567 | I12: =Sales!I32 -> 0.34458635 | J12: =Sales!J32 -> 0.32817747 | K12: =Sales!K32 -> 0.31254998 | L12: =Sales!L32 -> 0.29766664 | M12: =Sales!M32 -> 0.28349204 | N12: =Sales!N32 -> 0.26999242 | ... P12: =Sales!P32 -> 0.24489108
B13: Gross margin % [link Sales & COGS] | C13: ='FS Year'!K108 -> 0.45230411 | D13: ='FS Year'!L108 -> 0.71959795 | E13: ='FS Year'!M108 -> 0.47802568 | F13: ='FS Year'!N108 -> 0.60109823 | G13: =1-G12 -> 0.62009355 | H13: =1-H12 -> 0.63818433 | I13: =1-I12 -> 0.65541365 | J13: =1-J12 -> 0.67182253 | K13: =1-K12 -> 0.68745002 | L13: =1-L12 -> 0.70233336 | M13: =1-M12 -> 0.71650796 | N13: =1-N12 -> 0.73000758 | ... P13: =1-P12 -> 0.75510892 | R13: Constant; assume no changes
B14: Depreciation % of sales [link Sales & COGS] | C14: =-'FS Year'!K151 -> 0.0053309395 | D14: =-'FS Year'!L151 -> 0.01018567 | E14: =-'FS Year'!M151 -> 0.0073337254 | F14: =-'FS Year'!N151 -> 0.0063993307 | G14: =#REF! -> #REF! | H14: =#REF! -> #REF! | I14: =#REF! -> #REF! | J14: =#REF! -> #REF! | K14: =#REF! -> #REF! | L14: =#REF! -> #REF! | M14: =#REF! -> #REF! | N14: =#REF! -> #REF! | ... P14: =#REF! -> #REF!
B15: - Sales exp % sales | C15: =-'FS Year'!K158 -> 0.095753107 | D15: =-'FS Year'!L158 -> 0.15789977 | E15: =-'FS Year'!M158 -> 0.10915836 | F15: =-'FS Year'!N158 -> 0.18241514 | G15: =F15 -> 0.18241514 | H15: =G15 -> 0.18241514 | I15: =H15 -> 0.18241514 | J15: =I15 -> 0.18241514 | K15: =J15 -> 0.18241514 | L15: =K15 -> 0.18241514 | M15: =L15 -> 0.18241514 | N15: =M15 -> 0.18241514 | ... P15: =O15 -> 0.18241514 | R15: Constant; assume no changes
B16: - General and admin exp % sales | C16: =-'FS Year'!K159 -> 0.14492075 | D16: =-'FS Year'!L159 -> 0.29238811 | E16: =-'FS Year'!M159 -> 0.19497065 | F16: =-'FS Year'!N159 -> 0.23715162 | G16: =F16 -> 0.23715162 | H16: =G16 -> 0.23715162 | I16: =H16 -> 0.23715162 | J16: =I16 -> 0.23715162 | K16: =J16 -> 0.23715162 | L16: =K16 -> 0.23715162 | M16: =L16 -> 0.23715162 | N16: =M16 -> 0.23715162 | ... P16: =O16 -> 0.23715162 | R16: Constant; assume no changes
B17: - Foreign exchange losses (gains) | C17: =-'FS Year'!K161 -> 0 | D17: =-'FS Year'!L161 -> 0 | E17: =-'FS Year'!M161 -> -0.00010415041 | F17: =-'FS Year'!N161 -> 0 | G17: =F17 -> 0 | H17: =G17 -> 0 | I17: =H17 -> 0 | J17: =I17 -> 0 | K17: =J17 -> 0 | L17: =K17 -> 0 | M17: =L17 -> 0 | N17: =M17 -> 0 | ... P17: =O17 -> 0 | R17: Constant; assume no changes
B18: - Income tax % | C18: =IF(C12<>0,1-'FS Year'!K115,0) -> 0.29346057 | D18: =IF(D12<>0,1-'FS Year'!L115,0) -> 0.40317734 | E18: =IF(E12<>0,1-'FS Year'!M115,0) -> 0.25303995 | F18: =IF(F12<>0,1-'FS Year'!N115,0) -> 0.25526727 | G18: 0.22 | H18: =G18 -> 0.22 | I18: =H18 -> 0.22 | J18: =I18 -> 0.22 | K18: =J18 -> 0.22 | L18: =K18 -> 0.22 | M18: =L18 -> 0.22 | N18: =M18 -> 0.22 | O18: =N18 -> 0.22 | P18: =O18 -> 0.22 | R18: Constant; assume no changes
B19: - Minority Interests % as EBT | C19: =IFERROR(-'FS Year'!K23/'FS Year'!K20,0) -> 0.05241317 | D19: =IFERROR(-'FS Year'!L23/'FS Year'!L20,0) -> 0.15288224 | E19: =IFERROR(-'FS Year'!M23/'FS Year'!M20,0) -> 0.015609123 | F19: =IFERROR(-'FS Year'!N23/'FS Year'!N20,0) -> 0.057815048 | G19: ='P&L'!G29/'P&L'!G12 -> -0.14980534 | H19: -0.1 | I19: =H19 -> -0.1 | J19: =I19 -> -0.1 | K19: =J19 -> -0.1 | L19: =K19 -> -0.1 | M19: =L19 -> -0.1 | N19: =M19 -> -0.1 | O19: =N19 -> -0.1 | P19: =O19 -> -0.1 | R19: Constant; assume no changes
B20: BALANCE SHEET ASSUMPTIONS | R20: Constant; assume no changes
B21: Days inventory on hand | C21: ='FS Year'!K121 -> 371.19916 | D21: ='FS Year'!L121 -> 758.01037 | E21: ='FS Year'!M121 -> 184.82913 | F21: ='FS Year'!N121 -> 750.50396 | G21: =F21 -> 750.50396 | H21: =G21 -> 750.50396 | I21: =H21 -> 750.50396 | J21: =H21 -> 750.50396 | K21: =I21 -> 750.50396 | L21: =J21 -> 750.50396 | M21: =K21 -> 750.50396 | N21: =L21 -> 750.50396 | O21: =M21 -> 750.50396 | P21: =N21 -> 750.50396 | R21: Constant; assume no changes
B22: Days acounts receivables outstanding | C22: ='FS Year'!K122 -> 26.152575 | D22: ='FS Year'!L122 -> 120.91939 | E22: ='FS Year'!M122 -> 119.22943 | F22: ='FS Year'!N122 -> 136.93393 | G22: 136.9 | H22: =G22 -> 136.9 | I22: =H22 -> 136.9 | J22: =I22 -> 136.9 | K22: =J22 -> 136.9 | L22: =K22 -> 136.9 | M22: =L22 -> 136.9 | N22: =M22 -> 136.9 | O22: =N22 -> 136.9 | P22: =O22 -> 136.9 | R22: Constant; assume no changes
B23: Days accounts payable outstanding | C23: ='FS Year'!K123 -> 2.0625634 | D23: ='FS Year'!L123 -> 13.009597 | E23: ='FS Year'!M123 -> 34.706816 | F23: ='FS Year'!N123 -> 76.207499 | G23: ='FS Year'!O123 -> 68.159339 | H23: =G23 -> 68.159339 | I23: =H23 -> 68.159339 | J23: =I23 -> 68.159339 | K23: =J23 -> 68.159339 | L23: =K23 -> 68.159339 | M23: =L23 -> 68.159339 | N23: =M23 -> 68.159339 | O23: =N23 -> 68.159339 | P23: =O23 -> 68.159339 | R23: Constant; assume no changes
B24: Other short-term liabilities % inventory | C24: =IFERROR('FS Year'!K50/'FS Year'!K36,0) -> 0.80091814 | D24: =IFERROR('FS Year'!L50/'FS Year'!L36,0) -> 3.5742214 | E24: =IFERROR('FS Year'!M50/'FS Year'!M36,0) -> 1.5227126 | F24: =IFERROR('FS Year'!N50/'FS Year'!N36,0) -> 1.1782309 | G24: =F24 -> 1.1782309 | H24: =G24 -> 1.1782309 | I24: =H24 -> 1.1782309 | J24: =I24 -> 1.1782309 | K24: =J24 -> 1.1782309 | L24: =K24 -> 1.1782309 | M24: =L24 -> 1.1782309 | N24: =M24 -> 1.1782309 | ... P24: =O24 -> 1.1782309 | R24: Constant; assume no changes
B25: Short-term debt-to-total assets ratio | C25: ='FS Year'!K134 -> 0.2613161 | D25: ='FS Year'!L134 -> 0.12282175 | E25: ='FS Year'!M134 -> 0.00055116517 | F25: ='FS Year'!N134 -> 0 | G25: =F25 -> 0 | H25: =G25 -> 0 | I25: =H25 -> 0 | J25: =I25 -> 0 | K25: =J25 -> 0 | L25: =K25 -> 0 | M25: =L25 -> 0 | N25: =M25 -> 0 | ... P25: =O25 -> 0
B26: CASH FLOW ASSUMPTIONS | R26: Constant; assume no changes
B27: Minimum cash balance as % sales | C27: =IFERROR('FS Year'!K33/'FS Year'!K10,0) -> 0.43169615 | D27: =IFERROR('FS Year'!L33/'FS Year'!L10,0) -> 0.3748846 | E27: =IFERROR('FS Year'!M33/'FS Year'!M10,0) -> 0.33717881 | F27: =IFERROR('FS Year'!N33/'FS Year'!N10,0) -> 0.21275007 | G27: 0.1 | H27: =G27 -> 0.1 | I27: =H27 -> 0.1 | J27: =I27 -> 0.1 | K27: =J27 -> 0.1 | L27: =K27 -> 0.1 | M27: =L27 -> 0.1 | N27: =M27 -> 0.1 | O27: =N27 -> 0.1 | P27: =O27 -> 0.1 | R27: Constant; assume no changes
B28: Capex as % sales | C28: =IFERROR(-'FS Year'!K73/'FS Year'!K10,0) -> 0.016898193 | D28: =IFERROR(-'FS Year'!L73/'FS Year'!L10,0) -> 0.01850742 | E28: =IFERROR(-'FS Year'!M73/'FS Year'!M10,0) -> 0.0068979485 | F28: =IFERROR(-'FS Year'!N73/'FS Year'!N10,0) -> 0.0072502161 | G28: =#REF! -> #REF! | H28: =#REF! -> #REF! | I28: =#REF! -> #REF! | J28: =#REF! -> #REF! | K28: =#REF! -> #REF! | L28: =#REF! -> #REF! | M28: =#REF! -> #REF! | N28: =#REF! -> #REF! | ... P28: =#REF! -> #REF! | R28: Constant; assume no changes
B29: Dividend payout ratio | C29: ='FS Year'!K145 -> 0.592181 | D29: ='FS Year'!L145 -> 0 | E29: ='FS Year'!M145 -> 0 | F29: ='FS Year'!N145 -> 0 | G29: =F29 -> 0 | H29: =G29 -> 0 | I29: =H29 -> 0 | J29: =I29 -> 0 | K29: =J29 -> 0 | L29: =K29 -> 0 | M29: =L29 -> 0 | N29: =M29 -> 0 | ... P29: =O29 -> 0 | R29: Constant; assume no changes
B30: INTEREST RATE ASSUMPTIONS
B31: Short-term investment interest rate | G31: 0 | H31: 0 | I31: 0 | J31: 0 | K31: 0 | L31: 0 | M31: 0 | N31: 0 | O31: 0 | P31: 0
B32: Debt interest rate % (ST & LT debt) | C32: =IFERROR(-'FS Year'!K19/'FS Year'!K101,0) -> 0.0064614087 | D32: =IFERROR(-'FS Year'!L19/'FS Year'!L101,0) -> 0.24607708 | E32: =IFERROR(-'FS Year'!M19/'FS Year'!M101,0) -> 0.10888545 | F32: =IFERROR(-'FS Year'!N19/'FS Year'!N101,0) -> 0.0049176493 | G32: 0.1 | H32: =G32 -> 0.1 | I32: =H32 -> 0.1 | J32: =I32 -> 0.1 | K32: =J32 -> 0.1 | L32: =K32 -> 0.1 | M32: =L32 -> 0.1 | N32: =M32 -> 0.1 | O32: =N32 -> 0.1 | P32: =O32 -> 0.1 | R32: Constant; assume no changes
R33: Constant; assume no changes
B34: Income / loss from equity and other comprehensive income must be entered manually (if applicable for forecast period), interest income from short-term investments is based on short-term interest rate assumption
B35: Non-Operating (Losses) Gains | G35: =SUM(G36:G38)*'P&L'!#REF! -> #REF! | H35: =SUM(H36:H38)*'P&L'!H7 -> #REF! | I35: =SUM(I36:I38)*'P&L'!I7 -> #REF! | J35: =SUM(J36:J38)*'P&L'!J7 -> #REF! | K35: =SUM(K36:K38)*'P&L'!K7 -> #REF! | L35: =SUM(L36:L38)*'P&L'!L7 -> #REF! | M35: =SUM(M36:M38)*'P&L'!M7 -> #REF! | N35: =SUM(N36:N38)*'P&L'!N7 -> #REF! | O35: =SUM(O36:O38)*'P&L'!O7 -> #REF! | P35: =SUM(P36:P38)*'P&L'!P7 -> #REF!
B36: - Interest income (from short-term investments) | G36: =#REF!*Assumption!G31 -> #REF! | H36: =#REF!*Assumption!H31 -> #REF! | I36: =#REF!*Assumption!I31 -> #REF! | J36: =#REF!*Assumption!J31 -> #REF! | K36: =#REF!*Assumption!K31 -> #REF! | L36: =#REF!*Assumption!L31 -> #REF! | M36: =#REF!*Assumption!M31 -> #REF! | N36: =#REF!*Assumption!N31 -> #REF! | ... P36: =#REF!*Assumption!P31 -> #REF!
B37: - income/loss from equity in affliaties, JVs
B38: - other comprehensive income
C40: Use charts to check for consistency in assumptions

Sheet Client
B1: Location | C1: 1H15 | D1: 2015 | E1: 2016 | F1: 2017
A2: Brokerage | C2: ='1H15'!C30 -> 323.6 | D2: ='Rev_NPAT (new)'!K62/10^3 -> 545.14063 | E2: ='Rev_NPAT (new)'!L62/10^3 -> 626.91172 | F2: ='Rev_NPAT (new)'!M62/10^3 -> 689.6029
A4: Real estate
A5: Gold Hill | B5: Dong Nai | C5: ='1H15'!C32 -> 14.8 | D5: ='Rev_NPAT (new)'!K65/10^3 -> #REF! | E5: ='Rev_NPAT (new)'!L65/10^3 -> #REF! | F5: ='Rev_NPAT (new)'!M65/10^3 -> #REF!
A6: Sunview Town | B6: Thu Duc | D6: ='Rev_NPAT (new)'!K66/10^3 -> #REF! | E6: ='Rev_NPAT (new)'!L66/10^3 -> #REF! | F6: ='Rev_NPAT (new)'!M66/10^3 -> #REF!
A7: Riverside Garden | B7: Thu Duc | D7: ='Rev_NPAT (new)'!K67/10^3 -> #REF! | E7: ='Rev_NPAT (new)'!L67/10^3 -> #REF! | F7: ='Rev_NPAT (new)'!M67/10^3 -> #REF!
A8: Green City | B8: District 9 | D8: ='Rev_NPAT (new)'!K68/10^3 -> #REF! | E8: ='Rev_NPAT (new)'!L68/10^3 -> #REF! | F8: ='Rev_NPAT (new)'!M68/10^3 -> #REF!
C9: =SUM(C5:C8) -> 14.8 | D9: =SUM(D5:D8) -> #REF! | E9: =SUM(E5:E8) -> #REF! | F9: =SUM(F5:F8) -> #REF!
A11: Construction | C11: ='1H15'!C31 -> 45.4 | D11: ='Rev_NPAT (new)'!K63/10^3 -> 111.4325 | E11: ='Rev_NPAT (new)'!L63/10^3 -> 144.86225 | F11: ='Rev_NPAT (new)'!M63/10^3 -> 188.32093
C12: =C2+C9+C11 -> 383.8 | D12: =D2+D9+D11 -> #REF! | E12: =E2+E9+E11 -> #REF! | F12: =F2+F9+F11 -> #REF!
A14: Check | D14: =D12-SUM('Rev_NPAT (new)'!K62:K69)/1000 -> #REF! | E14: =E12-SUM('Rev_NPAT (new)'!L62:L69)/1000 -> #REF! | F14: =F12-SUM('Rev_NPAT (new)'!M62:M69)/1000 -> #REF!

Sheet 1H15
B1: 1H14 | C1: 1H15 | D1: Delta
A2: Revenue | B2: 210.3 | C2: 383.9
A3: Revenue deduction | B3: -0.3 | C3: 0
A4: Net revenue | B4: =B2-B3 -> 210.6 | C4: =C2-C3 -> 383.9 | D4: =C4/B4-1 -> 0.82288699 | I4: Revenue | K4: 2015 | L4: Q1 | M4: Q2 | N4: Q3 | O4: Q4
A5: COGS | B5: -77.3 | C5: -141.9
A6: Gross profit | B6: =SUM(B4:B5) -> 133.3 | C6: =SUM(C4:C5) -> 242 | J6: Revenue | K6: 1544142 | L6: 171843 | M6: 533138.67 | N6: 378207.33 | O6: 462338.32
A7: Selling expense | B7: -19.3 | C7: -43.1
A8: SG&A expense | B8: -34.1 | C8: -54.9 | J8: RE | K8: 1091568.9 | L8: 1500 | M8: 382280.97 | N8: 327006.96 | O8: 382280.97
A9: Operating profit | B9: =SUM(B6:B8) -> 79.9 | C9: =SUM(C6:C8) -> 144 | J9: Gold Hill | K9: 110548.03 | L9: 1500 | M9: 55274.016 | O9: 55274.016
A10: Financial income | B10: 6.2 | C10: 18.5 | D10: =C10/B10-1 -> 1.983871 | J10: Sunview Town | K10: 981020.87 | L10: 0 | M10: 327006.96 | N10: 327006.96 | O10: 327006.96
A11: Financial expense | B11: -0.044 | C11: -3.6 | J11: Green City | K11: 0 | O11: 0
A12: Other income | B12: 0.55 | C12: 55.9 | D12: =C12/B12-1 -> 100.63636
A13: Other expense | B13: -1 | C13: -3.1 | J13: Construction | K13: 89146 | L13: 14743 | M13: 29715.333 | N13: 14857.667 | O13: 29715.333
A14: Profit/(loss) shared | B14: 1.1 | C14: 24.4 | J14: Brokerage | K14: 363427.09 | L14: 155600 | M14: 121142.36 | N14: 36342.709 | O14: 50342.015
A15: PBT | B15: 86.2 | C15: 235.7
A16: NPAT | B16: 66.9 | C16: 202.4 | D16: =C16/B16-1 -> 2.0254111
A17: Minority interest | B17: -14.2 | C17: -49.2 | J17: Net profit | K17: 248641.49 | L17: 80939 | M17: 83948.896 | N17: 51090.928 | O17: 32547.75
A18: NPAT common | B18: =SUM(B16:B17) -> 52.7 | C18: =SUM(C16:C17) -> 153.2 | D18: =C18/B18-1 -> 1.9070209
A20: Basic EPS | B20: 775 | C20: 1529
A21: Diluted EPS | B21: 775 | C21: 1382
A23: GPM | B23: =B6/B4 -> 0.63295347 | C23: =C6/C4 -> 0.63037249
A24: NP margin | B24: =B16/B2 -> 0.31811698 | C24: =C16/C2 -> 0.52722063
A25: SG&A | B25: =(B7+B8)/B2 -> -0.25392297 | C25: =(C7+C8)/C2 -> -0.25527481
A27: Inventory | B27: 499.2 | C27: 808.4 | D27: =C27/B27-1 -> 0.61939103
A29: Rev.
A30: Brokerage | B30: 121 | C30: 323.6 | D30: =C30/B30-1 -> 1.6743802
A31: Construction | B31: 87.5 | C31: 45.4 | D31: =C31/B31-1 -> -0.48114286
A32: RE | B32: 1.7 | C32: 14.8 | D32: =C32/B32-1 -> 7.7058824
B33: =SUM(B30:B32) -> 210.2 | C33: =SUM(C30:C32) -> 383.8
A35: Brokerage | B35: =B30/B$33 -> 0.57564225 | C35: =C30/C$33 -> 0.84314747
A36: Construction | B36: =B31/B$33 -> 0.41627022 | C36: =C31/C$33 -> 0.11829078
A37: RE | B37: =B32/B$33 -> 0.0080875357 | C37: =C32/C$33 -> 0.038561751
A39: COGS
A40: Brokerage | B40: 34.2 | C40: 88.5
A41: Construction | B41: 42.2 | C41: 44.3
A42: RE | B42: 0.8 | C42: 9
B43: =SUM(B40:B42) -> 77.2 | C43: =SUM(C40:C42) -> 141.8
A45: GPM
A46: Brokerage | B46: =1-B40/B30 -> 0.71735537 | C46: =1-C40/C30 -> 0.72651422
A47: Construction | B47: =1-B41/B31 -> 0.51771429 | C47: =1-C41/C31 -> 0.024229075
A48: RE | B48: =1-B42/B32 -> 0.52941176 | C48: =1-C42/C32 -> 0.39189189

Sheet DCF
F1: Rf | G1: 0.12 | H1: 0.11 | I1: =H1*(1-$R1) -> 0.1078 | J1: =I1*(1-$R1) -> 0.105644 | K1: =J1*(1-$R1) -> 0.10353112 | L1: =K1*(1-$R1) -> 0.1014605 | M1: =L1*(1-$R1) -> 0.099431288 | N1: =M1*(1-$R1) -> 0.097442662 | O1: =N1*(1-$R1) -> 0.095493809 | P1: =O1*(1-$R1) -> 0.093583932 | Q1: =P1*(1-$R1) -> 0.091712254 | R1: 0.02
F2: Risk premium | G2: 0.12 | H2: 0.12 | I2: =H2*(1-$R2) -> 0.1176 | J2: =I2*(1-$R2) -> 0.115248 | K2: =J2*(1-$R2) -> 0.11294304 | L2: =K2*(1-$R2) -> 0.11068418 | M2: =L2*(1-$R2) -> 0.1084705 | N2: =M2*(1-$R2) -> 0.10630109 | O2: =N2*(1-$R2) -> 0.10417506 | P2: =O2*(1-$R2) -> 0.10209156 | Q2: =P2*(1-$R2) -> 0.10004973 | R2: 0.02
F3: Beta | G3: 1.2 | H3: 1.2 | I3: 1.2 | J3: 1.2 | K3: 1.2 | L3: 1.2 | M3: 1.2 | N3: 1.2 | O3: 1.2 | P3: 1.2 | Q3: 1.2
F4: Cost of equity | G4: =G1+G3*G2 -> 0.264 | H4: =H1+H3*H2 -> 0.254 | I4: =I1+I3*I2 -> 0.24892 | J4: =J1+J3*J2 -> 0.2439416 | K4: =K1+K3*K2 -> 0.23906277 | L4: =L1+L3*L2 -> 0.23428151 | M4: =M1+M3*M2 -> 0.22959588 | N4: =N1+N3*N2 -> 0.22500396 | ... Q4: =Q1+Q3*Q2 -> 0.21177193
F5: Cost of debt | G5: 0.22 | H5: 0.22 | I5: 0.22 | J5: 0.22 | K5: 0.22 | L5: 0.22 | M5: 0.22 | N5: 0.22 | O5: 0.22 | P5: 0.22 | Q5: 0.22
F6: Terminal growth | G6: 0.03
B7: =ticker -> DXG VN EQUITY | F7: Terminal year tax rate (marginal rate) | G7: 0.25
B9: Multi-stage DCF Valuation | C9: FCFF | D9: FCFE | G9: =IF(G11>end_year,0,1) -> 1 | H9: =IF(H11<=end_year,1,0) -> 1 | I9: =IF(I11<=end_year,1,0) -> 1 | J9: =IF(J11<=end_year,1,0) -> 1 | K9: =IF(K11<=end_year,1,0) -> 1 | L9: =IF(L11<=end_year,1,0) -> 1 | M9: =IF(M11<=end_year,1,0) -> 1 | N9: =IF(N11<=end_year,1,0) -> 1 | O9: =IF(O11<=end_year,1,0) -> 1 | ... Q9: =IF(Q11<=end_year,1,0) -> 1
B10: Forecast length in years | C10: 10 | D10: =C10 -> 10 | H10: 1 | I10: 2 | J10: 3 | K10: 4 | L10: 5 | M10: 6 | N10: 7 | O10: 8 | P10: 9 | Q10: 10
B11: PV of FCF | C11: =IFERROR(HLOOKUP(C10,J10:Q19,10),0) -> 0 | D11: =IFERROR(HLOOKUP(D10,J10:Q32,23),0) -> 0 | F11: FCFF | G11: ='FS Year'!N9 -> 2023 | H11: =G11+1 -> 2024 | I11: =H11+1 -> 2025 | J11: =I11+1 -> 2026 | K11: =J11+1 -> 2027 | L11: =K11+1 -> 2028 | M11: =L11+1 -> 2029 | N11: =M11+1 -> 2030 | O11: =N11+1 -> 2031 | ... Q11: =P11+1 -> 2033
B12: PV of Terminal value | C12: =HLOOKUP(C10,H10:Q21,12) -> #REF! | D12: =HLOOKUP(D10,H10:Q34,25) -> #REF! | F12: EBIT * (1 - tax) | G12: ='P&L'!#REF! -> #REF! | H12: ='P&L'!#REF! -> #REF! | I12: ='P&L'!#REF! -> #REF! | J12: ='P&L'!#REF! -> #REF! | K12: ='P&L'!#REF! -> #REF! | L12: ='P&L'!#REF! -> #REF! | M12: ='P&L'!#REF! -> #REF! | N12: ='P&L'!#REF! -> #REF! | ... Q12: ='P&L'!#REF! -> #REF!
B13: Terminal year FCF * terminal growth | C13: =HLOOKUP(C10,J10:Q20,11)*(1+terminal_g) -> #REF! | D13: =HLOOKUP(D10,H10:Q33,24)*(1+terminal_g) -> #REF! | F13: less: tax | G13: =-G12*(G37) -> #REF! | H13: =-H12*(H37) -> #REF! | I13: =-I12*(I37) -> #REF! | J13: =-J12*(J37) -> #REF! | K13: =-K12*(K37) -> #REF! | L13: =-L12*(L37) -> #REF! | M13: =-M12*(M37) -> #REF! | N13: =-N12*(N37) -> #REF! | ... Q13: =-Q12*(Q37) -> #REF!
B14: Terminal value % of total PV of FCF | C14: =IF(ISERROR(C12/C15),0,C12/C15) -> 0 | D14: =IF(ISERROR(D12/D15),0,D12/D15) -> 0 | F14: add: depreciation | G14: =-'P&L'!F34 -> 2.192354 | H14: =-'P&L'!#REF! -> #REF! | I14: =-'P&L'!H34 -> 0.0053 | J14: =-'P&L'!I34 -> 0.0039 | K14: =-'P&L'!J34 -> 0.004845 | L14: =-'P&L'!K34 -> 0.00579 | M14: =-'P&L'!L34 -> 0.006735 | N14: =-'P&L'!M34 -> 0 | O14: =-'P&L'!N34 -> #REF! | P14: =-'P&L'!O34 -> #REF! | Q14: =-'P&L'!P34 -> #REF!
B15: Total PV of FCF + PV of Terminal value | C15: =SUM(C11:C12) -> #REF! | D15: =SUM(D11:D12) -> #REF! | F15: less: capex | G15: =#REF! -> #REF! | H15: =#REF! -> #REF! | I15: =#REF! -> #REF! | J15: =#REF! -> #REF! | K15: =#REF! -> #REF! | L15: =#REF! -> #REF! | M15: =#REF! -> #REF! | N15: =#REF! -> #REF! | ... Q15: =#REF! -> #REF!
B16: add: cash & ST investments | C16: =#REF!+#REF! -> #REF! | D16: =C16 -> #REF! | F16: (increase) / decreace in NWC | G16: =#REF! -> #REF! | H16: =#REF! -> #REF! | I16: =#REF! -> #REF! | J16: =#REF! -> #REF! | K16: =#REF! -> #REF! | L16: =#REF! -> #REF! | M16: =#REF! -> #REF! | N16: =#REF! -> #REF! | ... Q16: =#REF! -> #REF!
B17: add: short and long-term debt | C17: =(#REF!+#REF!) -> #REF! | D17: 0 | F17: Unlevered free cash flow | G17: =SUM(G12:G16) -> #REF! | H17: =SUM(H12:H16) -> #REF! | I17: =SUM(I12:I16) -> #REF! | J17: =SUM(J12:J16) -> #REF! | K17: =SUM(K12:K16) -> #REF! | L17: =SUM(L12:L16) -> #REF! | M17: =SUM(M12:M16) -> #REF! | N17: =SUM(N12:N16) -> #REF! | ... Q17: =SUM(Q12:Q16) -> #REF!
B18: Enterprise value (EV) | C18: =SUM(C15:C17) -> #REF! | D18: =SUM(D15:D17) -> #REF! | F18: PV of FCF | H18: =H17/(1+H38) -> #REF! | I18: =I17/((1+H38)*(1+I38)) -> #REF! | J18: =J17/((1+H38)*(1+I38)*(1+J38)) -> #REF! | K18: =K17/((1+H38)*(1+I38)*(1+J38)*(1+K38)) -> #REF! | L18: =L17/((1+H38)*(1+I38)*(1+J38)*(1+K38)*(1+L38)) -> #REF! | M18: =M17/((1+H38)*(1+I38)*(1+J38)*(1+K38)*(1+L38)*(1+M38)) -> #REF! | N18: =N17/((1+H38)*(1+I38)*(1+J38)*(1+K38)*(1+L38)*(1+M38)*(1+N38)) -> #REF! | O18: =O17/((1+H38)*(1+I38)*(1+J38)*(1+K38)*(1+L38)*(1+M38)*(1+N38)*(1+O38)) -> #REF! | P18: =P17/((1+H38)*(1+I38)*(1+J38)*(1+K38)*(1+L38)*(1+M38)*(1+N38)*(1+O38)*(1+P38)) -> #REF! | Q18: =Q17/((1+H38)*(1+I38)*(1+J38)*(1+K38)*(1+L38)*(1+M38)*(1+N38)*(1+O38)*(1+P38)*(1+Q38)) -> #REF!
B19: Equity value including minority interest | C19: =C15+C16-C17 -> #REF! | D19: =D15+D16-D17 -> #REF! | F19: Cumulative sum PV of FCF | H19: =SUM($H18:H18)*H9 -> #REF! | I19: =SUM($H18:I18)*I9 -> #REF! | J19: =SUM($H18:J18)*J9 -> #REF! | K19: =SUM($H18:K18)*K9 -> #REF! | L19: =SUM($H18:L18)*L9 -> #REF! | M19: =SUM($H18:M18)*M9 -> #REF! | N19: =SUM($H18:N18)*N9 -> #REF! | O19: =SUM($H18:O18)*O9 -> #REF! | ... Q19: =SUM($H18:Q18)*Q9 -> #REF!
B20: P/B of equity including minority interest | C20: =IF(ISERROR(C19/#REF!),0,C19/#REF!) -> 0 | D20: =IF(ISERROR(D19/#REF!),0,D19/#REF!) -> 0 | F20: Terminal cashflow (using marginal tax rate) | G20: =G12*(1-marginal_tax)+SUM(G14:G16) -> #REF! | H20: =H12*(1-marginal_tax)+SUM(H14:H16) -> #REF! | I20: =I12*(1-marginal_tax)+SUM(I14:I16) -> #REF! | J20: =J12*(1-marginal_tax)+SUM(J14:J16) -> #REF! | K20: =K12*(1-marginal_tax)+SUM(K14:K16) -> #REF! | L20: =L12*(1-marginal_tax)+SUM(L14:L16) -> #REF! | M20: =M12*(1-marginal_tax)+SUM(M14:M16) -> #REF! | N20: =N12*(1-marginal_tax)+SUM(N14:N16) -> #REF! | ... Q20: =Q12*(1-marginal_tax)+SUM(Q14:Q16) -> #REF!
B21: Minority interest (book value) | C21: =#REF! -> #REF! | D21: =C21 -> #REF! | F21: PV of terminal value | H21: =(H20/(H$43-terminal_g))/(1+H$43) -> #REF! | I21: =(I20/(I$43-terminal_g))/((1+H43)*(1+I$43)) -> #REF! | J21: =(J20/(J$43-terminal_g))/((1+H43)*(1+I43)*(1+J$43)) -> #REF! | K21: =(K20/(K$43-terminal_g))/((1+H43)*(1+I43)*(1+J43)*(1+K$43)) -> #REF! | L21: =(L20/(L$43-terminal_g))/((1+H43)*(1+I43)*(1+J43)*(1+K43)*(1+L$43)) -> #REF! | M21: =(M20/(M$43-terminal_g))/((1+H43)*(1+I43)*(1+J43)*(1+K43)*(1+L43)*(1+M$43)) -> #REF! | N21: =(N20/(N$43-terminal_g))/((1+H43)*(1+I43)*(1+J43)*(1+K43)*(1+L43)*(1+M43)*(1+N$43)) -> #REF! | O21: =(O20/(O$43-terminal_g))/((1+H43)*(1+I43)*(1+J43)*(1+K43)*(1+L43)*(1+M43)*(1+N43)*(1+O$43)) -> #REF! | P21: =(P20/(P$43-terminal_g))/((1+H43)*(1+I43)*(1+J43)*(1+K43)*(1+L43)*(1+M43)*(1+N43)*(1+O43)*(1+P$43)) -> #REF! | Q21: =(Q20/(Q$43-terminal_g))/((1+H43)*(1+I43)*(1+J43)*(1+K43)*(1+L43)*(1+M43)*(1+N43)*(1+O43)*(1+P43)*(1+Q$43)) -> #REF!
B22: Fair value minority interest using P/B x | C22: =C20*C21 -> #REF! | D22: =D20*D21 -> #REF!
B23: Equity less fair value of minority interest | C23: =C19-C22 -> #REF! | D23: =D19-D22 -> #REF! | F23: FCFE | G23: =G11 -> 2023 | H23: =H11 -> 2024 | I23: =I11 -> 2025 | J23: =J11 -> 2026 | K23: =K11 -> 2027 | L23: =L11 -> 2028 | M23: =M11 -> 2029 | N23: =N11 -> 2030 | ... Q23: =Q11 -> 2033
B24: Outstanding shares (million) | C24: =shares -> 75 | D24: =shares -> 75 | F24: Earnings before tax | G24: ='P&L'!#REF! -> #REF! | H24: ='P&L'!#REF! -> #REF! | I24: ='P&L'!#REF! -> #REF! | J24: ='P&L'!#REF! -> #REF! | K24: ='P&L'!#REF! -> #REF! | L24: ='P&L'!#REF! -> #REF! | M24: ='P&L'!#REF! -> #REF! | N24: ='P&L'!#REF! -> #REF! | ... Q24: ='P&L'!#REF! -> #REF!
